Workbook

Sheet Read_Me
A1: IFRS 9 VERIFIED MASTER
A2: Generated (UTC) | B2: 2026-10-11T12:47:05+00:00
A3: Baseline | B3: 47 selected bank-years (inputs/IFRS9_Selected_Data_Updated_20261010.csv, unchanged; SHA-256 verified).
A4: This run | B4: 71 new bank-years admitted; 9 blank fields filled; 0 corrections. See Progress.
A5: Units | B5: Monetary amounts NGN million; ratios in percentage points. Blank = not admitted or unavailable, never zero.
A6: Entity rule | B6: Historical Nigerian operating bank only; never holding company, consolidated group, foreign subsidiary or segment.
A7: Formulas | B7: Calculated_Ratios holds live formulas over Panel_Inputs; Formula_Check compares them with the Python recomputation.
A8: Evidence | B8: Evidence_Long: inherited records are labelled inherited_not_rechecked_this_run; only reviewed admissions are verified_reported.
A9: Caution | B9: A report link is not a verified value; a verified value is not a complete bank-year; no regressions are estimated here.
A10: allr | B10: allowance_grossloans_pct = 100 * customer-loan allowance / gross customer loans
A11: average_assets | B11: (matched opening assets + closing assets) / 2; both positive
A12: balance_residual | B12: assets - liabilities - equity (NGN million)
A13: broad_coverage | B13: broad_NPL_coverage_pct = 100 * total customer-loan allowance / NPL amount (not NPL-specific)
... A25: stage3_ratio | B25: 100 * Stage 3 gross / gross loans (not a regulatory NPL ratio)

Sheet Panel_Inputs
A1: Admitted operating-bank inputs. NGN million; percentage points. Blank = not admitted, never zero.
A3: bank | B3: year | C3: tier | D3: regime | E3: pat | F3: assets | G3: liabilities | H3: equity | I3: ocf | J3: opening_assets | K3: gross_loans | L3: loan_allowance | M3: net_loans | N3: total_impairment | O3: npl_amount | P3: regulatory_capital | Q3: rwa | R3: stage3_gross | S3: stage3_allowance | T3: car | U3: car_minimum | V3: liquidity | W3: liquidity_admissible | X3: gcu | Y3: source_url | Z3: version_note | AA3: origin
A4: Access | B4: 2013 | C4: Tier 1 | D4: IAS 39 | E4: 26211.844 | F4: 1704094 | G4: 1458912 | H4: 245182 | N4: -7508.216 | O4: 17924.178 | Y4: https://www.accessbankplc.com/access/media/Financial-Report/Quarterly%20Reports/2014-Financial-Statement-Abridged-Report.pdf?ext=.pdf | Z4: Prior source-selection policy retained; original evidence preserved in accompanying pack. | AA4: Prior selected evidence
A5: Access | B5: 2014 | C5: Tier 1 | D5: IAS 39 | E5: 39941.126 | F5: 1981955.7 | G5: 1707799.9 | H5: 274155.78 | J5: 1704094 | N5: 10609.3 | O5: 19966.521 | Y5: https://www.accessbankplc.com/access/media/Financial-Report/Quarterly%20Reports/2014-Financial-Statement-Abridged-Report.pdf?ext=.pdf | Z5: Prior source-selection policy retained; original evidence preserved in accompanying pack. | AA5: Prior selected evidence
A6: Access | B6: 2015 | C6: Tier 1 | D6: IAS 39 | E6: 58924.745 | F6: 2411944.1 | G6: 2051515.2 | H6: 360428.9 | I6: -181246.61 | J6: 1981955.7 | K6: 1270121.4 | L6: 26906.083 | M6: 1243215.3 | N6: 13287.613 | P6: 340521.19 | Q6: 1887612.1 | T6: 18 | U6: 16 | X6: 0 | Y6: https://doclib.ngxgroup.com/Financial_NewsDocs/12658_ACCESS_BANK_-_2015_AUDITED_ACCTS_FINANCIAL_STATEMENTS_MARCH_2016.pdf | Z6: 2015 annual report, as originally reported | AA6: Admitted this run
A7: Access | B7: 2016 | C7: Tier 1 | D7: IAS 39 | E7: 64026.135 | F7: 3094960.5 | G7: 2673281.9 | H7: 421678.62 | I7: -124135.58 | J7: 2411944.1 | K7: 1624837.9 | L7: 30275.514 | M7: 1594562.3 | N7: 17641.127 | P7: 419807.32 | Q7: 2146850 | T7: 19.55 | U7: 16 | X7: 0 | Y7: https://doclib.ngxgroup.com/Financial_NewsDocs/16624_ACCESS_BANK_-_2016_AUDITED_ACCTS_FINANCIAL_STATEMENTS_MARCH_2017.pdf | Z7: 2016 annual report, as originally reported | AA7: Admitted this run
A8: Access | B8: 2017 | C8: Tier 1 | D8: IAS 39 | E8: 53238.822 | F8: 3499684 | G8: 3030192.9 | H8: 469491.1 | I8: 104360.68 | J8: 3094960.5 | K8: 1827572.1 | L8: 56289.402 | M8: 1771282.7 | N8: 29149.849 | P8: 420096.3 | Q8: 2311370.7 | T8: 18.18 | U8: 16 | X8: 0 | Y8: https://doclib.ngxgroup.com/Financial_NewsDocs/21306_ACCESS_BANK_PLC._FINANCIAL_STATEMENTS_MARCH_2018.pdf | Z8: 2017 annual report, as originally reported | AA8: Admitted this run
A9: Access | B9: 2018 | C9: Tier 1 | D9: IFRS 9 | E9: 73596.295 | F9: 3968114.6 | G9: 3527314.9 | H9: 440799.76 | I9: 366002.39 | M9: 1681761.9 | N9: 10702.144 | Y9: https://doclib.ngxgroup.com/Financial_NewsDocs/29309_ACCESS_BANK_PLC._FINANCIAL_STATEMENTS_MARCH_2020.pdf | Z9: 2019 report comparative (not labelled restated) | AA9: Admitted this run
A10: Access | B10: 2019 | C10: Tier 1 | D10: IFRS 9 | E10: 73569.054 | F10: 6311041.3 | G10: 5768100.2 | H10: 542941.1 | I10: 1094573.3 | J10: 3968114.6 | K10: 2662623.1 | L10: 180999.42 | M10: 2481623.7 | N10: 21055.479 | X10: 0 | Y10: https://doclib.ngxgroup.com/Financial_NewsDocs/29309_ACCESS_BANK_PLC._FINANCIAL_STATEMENTS_MARCH_2020.pdf | Z10: 2019 annual report, as originally reported | AA10: Admitted this run
A11: Access | B11: 2020 | C11: Tier 1 | D11: IFRS 9 | E11: 80039.328 | F11: 7624979.7 | G11: 6971084.1 | H11: 653895.66 | I11: -65407.286 | J11: 6307588.2 | K11: 2937918.3 | L11: 119042.54 | M11: 2818875.7 | N11: 39650.58 | P11: 488756.27 | Q11: 3078989.1 | T11: 15.87 | U11: 16 | X11: 0 | Y11: https://doclib.ngxgroup.com/Financial_NewsDocs/32900_ACCESS_BANK_PLC%20_AUDITED_FINANCIAL_STATEMENT_FOR_2020.pdf | Z11: 2020 annual report, as originally reported | AA11: Admitted this run
A12: Access | B12: 2021 | C12: Tier 1 | D12: IFRS 9 | E12: 111326.49 | F12: 9660760.6 | G12: 8789310.4 | H12: 871450.11 | I12: 500834.81 | J12: 7624979.7 | K12: 3343722.2 | L12: 87649.564 | M12: 3256072.7 | N12: 53800.935 | P12: 835939.16 | Q12: 3993848.7 | T12: 20.93 | X12: 0 | Y12: https://doclib.ngxgroup.com/Financial_NewsDocs/35310_ACCESS_BANK_PLC%20_AUDITED_FINANCIAL_STATEMENT_FOR_2021.pdf | Z12: 2021 annual report, as originally reported | AA12: Admitted this run
A13: Access | B13: 2022 | C13: Tier 1 | D13: IFRS 9 | E13: 166660 | F13: 12535280 | G13: 11466613 | H13: 1068667 | I13: 698528 | J13: 9660761 | K13: 4149413 | L13: 65061 | M13: 4084352 | N13: 118681 | P13: 863711 | Q13: 4839820 | T13: 17.85 | Y13: https://www.accessbankplc.com/access/media/Media-PDF-Attachment/2022-FY-Financial-Statement.pdf?ext=.pdf | Z13: 2022 financial statements, as originally reported | AA13: Admitted this run
A14: Ecobank Nigeria | B14: 2013 | C14: Tier 2 | D14: IAS 39 | E14: 11658 | F14: 1460811 | G14: 1304183 | H14: 156628 | I14: 4606 | J14: 1325315 | K14: 660730 | L14: 34823 | M14: 625907 | N14: 32606 | P14: 165746 | Q14: 953338 | T14: 17 | X14: 0 | Y14: https://www.ecobank.com/upload/publication/20160603050431876MVJZ65QMD2/20140717070804117617CS9N8RVrc92013.pdf | Z14: 2013 annual report, as originally reported | AA14: Admitted this run
A15: Ecobank Nigeria | B15: 2014 | C15: Tier 2 | D15: IAS 39 | E15: 29733 | F15: 1772922 | G15: 1574528 | H15: 198394 | I15: -110701 | J15: 1460811 | K15: 930956 | L15: 38235 | M15: 892721 | N15: 32994 | P15: 239281 | Q15: 1492373 | T15: 16 | X15: 0 | Y15: https://www.ecobank.com/upload/publication/20160603050328266BV9KK3KMGZ/20150424114643650413NqzAyDndnW2014.PDF | Z15: 2014 annual report, as originally reported | AA15: Admitted this run
A16: Ecobank Nigeria | B16: 2015 | C16: Tier 2 | D16: IAS 39 | E16: 11304 | F16: 1794348 | G16: 1566561 | H16: 227787 | I16: 24229 | J16: 1772922 | K16: 885701 | L16: 68353 | M16: 817348 | N16: 55740 | P16: 254109 | Q16: 1357098 | T16: 19 | X16: 0 | Y16: https://www.ecobank.com/upload/publication/20160810051714162FAUN9WFV76/20160810051700933X.pdf | Z16: 2015 annual report, as originally reported | AA16: Admitted this run
A17: Ecobank Nigeria | B17: 2016 | C17: Tier 2 | D17: IAS 39 | E17: 5780 | F17: 1808503 | G17: 1587728 | H17: 220775 | N17: 82783 | Y17: https://www.financialafrik.com/wp-content/uploads/2018/05/FINANCIAL_STATEMENT_EBN_2017-2.pdf | Z17: Prior source-selection policy retained; original evidence preserved in accompanying pack. | AA17: Prior selected evidence
A18: Ecobank Nigeria | B18: 2017 | C18: Tier 2 | D18: IAS 39 | E18: 20204 | F18: 1829761 | G18: 1562432 | H18: 267329 | J18: 1808503 | N18: 59901 | Y18: https://www.financialafrik.com/wp-content/uploads/2018/05/FINANCIAL_STATEMENT_EBN_2017-2.pdf | Z18: Prior source-selection policy retained; original evidence preserved in accompanying pack. | AA18: Prior selected evidence
A19: Ecobank Nigeria | B19: 2018 | C19: Tier 2 | D19: IFRS 9 | E19: 27155 | F19: 1956830 | G19: 1709348 | H19: 247482 | I19: 31236 | J19: 1829761 | K19: 926546 | L19: 84071 | M19: 842475 | N19: 27360 | O19: 126844 | P19: 205312 | Q19: 1433545 | T19: 14.3 | X19: 0 | Y19: https://www.ecobank.com/upload/publication/201908161135521993YH9XK3GUU/201908161135142514.pdf | Z19: 2018 annual report, as originally reported | AA19: Admitted this run
A20: Ecobank Nigeria | B20: 2019 | C20: Tier 2 | D20: IFRS 9 | E20: 1256 | F20: 1991040 | G20: 1726770 | H20: 264270 | I20: 49052 | J20: 1927889 | K20: 913082 | L20: 101476 | M20: 811606 | N20: 2704 | O20: 218515 | P20: 236196 | Q20: 1447830 | T20: 16.31 | X20: 0 | Y20: https://www.ecobank.com/upload/publication/20200901042621276B6RH5TBQ22/20200901042502327T.pdf | Z20: 2019 annual report, as originally reported | AA20: Admitted this run
A21: Ecobank Nigeria | B21: 2020 | C21: Tier 2 | D21: IFRS 9 | E21: 8087 | F21: 2186712 | G21: 1887991 | H21: 298721 | I21: -13271 | J21: 1991040 | K21: 993191 | L21: 111609 | M21: 881582 | N21: 9164 | O21: 197204 | P21: 301364 | Q21: 1405676 | T21: 21.44 | X21: 0 | Y21: https://www.ecobank.com/upload/publication/20210803011222677VJB2VFNZ2Y/20210803011214097V.pdf | Z21: 2020 annual report, as originally reported | AA21: Admitted this run
A22: Ecobank Nigeria | B22: 2021 | C22: Tier 2 | D22: IFRS 9 | E22: 9766 | F22: 2475079 | G22: 2196302 | H22: 278777 | I22: -86740 | J22: 2186711 | K22: 1113022 | L22: 97419 | M22: 1015603 | N22: 7041 | O22: 181954 | P22: 170600 | Q22: 1486056 | T22: 11.48 | X22: 0 | Y22: https://www.ecobank.com/upload/publication/20220707035014829GBVPAXGW87/20220707034953065D.pdf | Z22: 2021 annual report, as originally reported | AA22: Admitted this run
A23: Ecobank Nigeria | B23: 2022 | C23: Tier 2 | D23: IFRS 9 | E23: 10396 | F23: 2917689 | G23: 2623076 | H23: 294613 | I23: -75642 | J23: 2475079 | K23: 1190306 | L23: 62880 | M23: 1127426 | N23: 12377 | O23: 82348 | P23: 232070 | Q23: 1748560 | T23: 13.27 | X23: 0 | Y23: https://www.ecobank.com/upload/publication/20240318051756025XSA3RCX9NN/20240318051750118B.pdf | Z23: 2022 annual report, as originally reported | AA23: Admitted this run
A24: Fidelity | B24: 2013 | C24: Tier 2 | D24: IAS 39 | E24: 7721 | F24: 1081217 | G24: 917762 | H24: 163455 | I24: 15048 | J24: 914360 | K24: 442649 | L24: 16573 | N24: 7630 | T24: 26 | Y24: https://www.fidelitybank.ng/documents/FYE%202013%20Audited%20Financial%20Results.pdf | Z24: Prior source-selection policy retained; original evidence preserved in accompanying pack. | AA24: Prior selected evidence
A25: Fidelity | B25: 2014 | C25: Tier 2 | D25: IAS 39 | E25: 13796 | F25: 1187025 | G25: 1013914 | H25: 173111 | I25: 53565 | J25: 1081217 | K25: 559137 | L25: 17451 | M25: 541686 | N25: 4306 | P25: 198886 | Q25: 821527 | T25: 24.21 | U25: 15 | X25: 0 | Y25: https://www.annualreports.com/HostedData/AnnualReportArchive/f/fidelity-bank-plc_2014.pdf | Z25: 2014 annual report, as originally reported | AA25: Admitted this run
A26: Fidelity | B26: 2015 | C26: Tier 2 | D26: IAS 39 | E26: 13904 | F26: 1231722 | G26: 1048206 | H26: 183516 | I26: 107132 | J26: 1187025 | K26: 598978 | L26: 20776 | M26: 578203 | N26: 5764 | P26: 191595 | Q26: 1012062 | T26: 19 | U26: 15 | X26: 0 | Y26: https://www.annualreports.com/HostedData/AnnualReportArchive/f/fidelity-bank-plc_2015.pdf | Z26: 2015 annual report, as originally reported | AA26: Admitted this run
A27: Fidelity | B27: 2016 | C27: Tier 2 | D27: IAS 39 | E27: 9734 | F27: 1298141 | G27: 1112739 | H27: 185402 | I27: -56907 | J27: 1231722 | K27: 743120 | L27: 24719 | M27: 718401 | N27: 8671 | P27: 196913 | Q27: 1138258 | T27: 17.22 | U27: 15 | X27: 0 | Y27: https://www.annualreports.com/HostedData/AnnualReportArchive/f/fidelity-bank-plc_2016.pdf | Z27: 2016 annual report, as originally reported | AA27: Admitted this run
A28: Fidelity | B28: 2017 | C28: Tier 2 | D28: IAS 39 | E28: 18857 | F28: 1379214 | G28: 1175899 | H28: 203315 | I28: -38026 | J28: 1298141 | K28: 795315 | L28: 26578 | M28: 768737 | N28: 11315 | P28: 179341 | Q28: 1118786 | T28: 16.03 | U28: 15 | X28: 0 | Y28: https://www.annualreports.com/HostedData/AnnualReportArchive/f/fidelity-bank-plc_2017.pdf | Z28: 2017 annual report, as originally reported | AA28: Admitted this run
A29: Fidelity | B29: 2018 | C29: Tier 2 | D29: IFRS 9 | E29: 22926 | F29: 1719883 | G29: 1525467 | H29: 194416 | N29: 4215 | Y29: https://www.fidelitybank.ng/documents/2019%20Annual%20report%20Final%20Web%20Version.pdf | Z29: Prior source-selection policy retained; original evidence preserved in accompanying pack. | AA29: Prior selected evidence
A30: Fidelity | B30: 2019 | C30: Tier 2 | D30: IFRS 9 | E30: 28425 | F30: 2114037 | G30: 1880007 | H30: 234030 | J30: 1719883 | N30: -5292 | X30: 0 | Y30: https://www.fidelitybank.ng/documents/2019%20Annual%20report%20Final%20Web%20Version.pdf | Z30: Prior source-selection policy retained; original evidence preserved in accompanying pack. | AA30: Prior selected evidence
A31: Fidelity | B31: 2020 | C31: Tier 2 | D31: IFRS 9 | E31: 26650 | F31: 2758148 | G31: 2484615 | H31: 273533 | I31: 242619 | J31: 2114037 | K31: 1393624 | L31: 67518 | M31: 1326106 | N31: 16858 | P31: 243690 | Q31: 1340211 | T31: 18.18 | U31: 15 | X31: 0 | Y31: https://www.annualreports.com/HostedData/AnnualReportArchive/f/fidelity-bank-plc_2020.pdf | Z31: 2020 annual report, as originally reported | AA31: Admitted this run
A32: Fidelity | B32: 2021 | C32: Tier 2 | D32: IFRS 9 | E32: 23104 | F32: 3280454 | G32: 2995160 | H32: 285294 | I32: -107190 | K32: 1732543 | L32: 74131 | M32: 1658412 | N32: 7034 | P32: 292323 | Q32: 1526722 | T32: 19.15 | U32: 15 | Y32: https://www.fidelitybank.ng/documents/Fidelity-Bank-Plc-2022-Annual-Report.pdf | Z32: 2022 annual report; 2021 restated comparative | AA32: Admitted this run
A33: Fidelity | B33: 2022 | C33: Tier 2 | D33: IFRS 9 | E33: 46724 | F33: 3989009 | G33: 3674649 | H33: 314360 | I33: 297592 | J33: 3280454 | K33: 2196760 | L33: 80548 | M33: 2116212 | N33: 5443 | P33: 289500 | Q33: 1595729 | T33: 18.14 | U33: 15 | X33: 0 | Y33: https://www.fidelitybank.ng/documents/Fidelity-Bank-Plc-2022-Annual-Report.pdf | Z33: 2022 annual report, as originally reported | AA33: Admitted this run
A34: First Bank | B34: 2013 | C34: Tier 1 | D34: IAS 39 | E34: 59365 | F34: 3246579 | G34: 2895870 | H34: 350709 | I34: 179950 | K34: 1515288 | L34: 41449 | N34: 19838 | T34: 13.54 | Y34: https://first-holdco.com/wp-content/uploads/2021/02/First_Bank_of_Nigeria_Ltd_2014_Annual_Report.pdf | Z34: Prior source-selection policy retained; original evidence preserved in accompanying pack. | AA34: Prior selected evidence
A35: First Bank | B35: 2014 | C35: Tier 1 | D35: IAS 39 | E35: 79351 | F35: 3490871 | G35: 3067824 | H35: 423047 | I35: -506665 | J35: 3246579 | K35: 1832107 | L35: 38070 | N35: 20924 | T35: 15.78 | Y35: https://first-holdco.com/wp-content/uploads/2021/02/First_Bank_of_Nigeria_Ltd_2014_Annual_Report.pdf | Z35: Prior source-selection policy retained; original evidence preserved in accompanying pack. | AA35: Prior selected evidence
A36: First Bank | B36: 2015 | C36: Tier 1 | D36: IAS 39 | E36: 37 | F36: 3332375 | G36: 2872628 | H36: 459747 | I36: 305952 | J36: 3490871 | K36: 1594936 | L36: 137651 | M36: 1457285 | N36: 120046 | P36: 430099 | Q36: 2518285 | T36: 17.08 | U36: 15 | Y36: https://first-holdco.com/wp-content/uploads/2021/02/First_Bank_of_Nigeria_Ltd_2015_Annual_Report.pdf | Z36: 2015 annual report, as originally reported | AA36: Admitted this run
A37: First Bank | B37: 2016 | C37: Tier 1 | D37: IAS 39 | E37: 50072 | F37: 3557782 | G37: 3071695 | H37: 486087 | I37: -171230 | K37: 1933407 | L37: 240695 | M37: 1692712 | P37: 501256 | Q37: 2818158 | T37: 17.79 | U37: 15 | X37: 0 | Y37: https://first-holdco.com/wp-content/uploads/2021/02/First-Bank-of-Nigeria-Ltd-FY-2017-Financial-Statements.pdf | Z37: FY2017 financial statements; 2016 comparative, not labelled restated | AA37: Admitted this run
A38: First Bank | B38: 2017 | C38: Tier 1 | D38: IAS 39 | E38: 46918 | F38: 3777039 | G38: 3197196 | H38: 579843 | I38: 113212 | J38: 3557782 | K38: 1837515 | L38: 178719 | M38: 1658796 | P38: 535692 | Q38: 3019880 | T38: 17.74 | U38: 15 | Y38: https://first-holdco.com/wp-content/uploads/2021/02/First-Bank-of-Nigeria-Ltd-FY-2017-Financial-Statements.pdf | Z38: FY2017 financial statements, as originally reported | AA38: Admitted this run
A39: First Bank | B39: 2018 | C39: Tier 1 | D39: IFRS 9 | E39: 56952 | F39: 3985907 | G39: 3543223 | H39: 442684 | I39: 327497 | J39: 3777039 | K39: 1728964 | L39: 277549 | M39: 1451415 | N39: 61865 | P39: 269341 | Q39: 2527208 | T39: 10.66 | X39: 0 | Y39: https://ise-prodnr-eu-west-1-data-integration.s3-eu-west-1.amazonaws.com/legacy/Prospectus+-+Standalone_bccce739-ac65-4a0d-82bc-7ef4406d2573.PDF | Z39: FY2018 financial statements, as originally reported (reproduced in FBN Finance prospectus) | AA39: Admitted this run
A40: First Bank | B40: 2019 | C40: Tier 1 | D40: IFRS 9 | E40: 43917 | F40: 4668279 | G40: 4128814 | H40: 539465 | I40: -218752 | J40: 3985907 | K40: 1618817 | L40: 59314 | M40: 1559504 | N40: 46640 | P40: 332265 | Q40: 2978121 | T40: 11.16 | X40: 0 | Y40: https://ise-prodnr-eu-west-1-data-integration.s3-eu-west-1.amazonaws.com/legacy/Prospectus+-+Standalone_bccce739-ac65-4a0d-82bc-7ef4406d2573.PDF | Z40: FY2019 financial statements, as originally reported (reproduced in FBN Finance prospectus) | AA40: Admitted this run
A41: First Bank | B41: 2022 | C41: Tier 1 | D41: IFRS 9 | E41: 91415 | F41: 8125060 | G41: 7372174 | H41: 752886 | M41: 3301779 | N41: 49773 | Y41: https://cdn.businessday.ng/wp-content/uploads/2024/05/BD_20240529.pdf | Z41: FY2023 audited summary financial statements, 2022 comparative (later-year presentation; not the 2022 annual report) | AA41: Admitted this run
A42: GTBank | B42: 2013 | C42: Tier 1 | D42: IAS 39 | E42: 85546 | F42: 1904366 | G42: 1574719 | H42: 329647 | O42: 27707 | Y42: https://gtbank-plc.files.svdcdn.com/production/financial-information/2014-Financial-Statement-Summary.pdf?dm=1517101701 | Z42: Prior source-selection policy retained; original evidence preserved in accompanying pack. | AA42: Prior selected evidence
A43: GTBank | B43: 2014 | C43: Tier 1 | D43: IAS 39 | E43: 93432 | F43: 2126608 | G43: 1757078 | H43: 369530 | J43: 1904366 | O43: 32616 | Y43: https://gtbank-plc.files.svdcdn.com/production/financial-information/2014-Financial-Statement-Summary.pdf?dm=1517101701 | Z43: Prior source-selection policy retained; original evidence preserved in accompanying pack. | AA43: Prior selected evidence
A44: GTBank | B44: 2015 | C44: Tier 1 | D44: IAS 39 | E44: 94308.123 | F44: 2277629.2 | G44: 1872020.9 | H44: 405608.35 | I44: 10429.148 | J44: 2126608.3 | K44: 1291516.2 | L44: 26308.785 | M44: 1265207.4 | N44: 11769.374 | P44: 333426.14 | Q44: 1835072.1 | T44: 18.17 | X44: 0 | Y44: https://gtbank-plc.files.svdcdn.com/production/financial-information/2015-Year-End-Audited-Results.pdf | Z44: 2015 annual report, as originally reported | AA44: Admitted this run
A45: GTBank | B45: 2016 | C45: Tier 1 | D45: IAS 39 | E45: 126836.79 | F45: 2613340.1 | G45: 2136422.2 | H45: 476917.85 | I45: 286884.14 | J45: 2277629.2 | K45: 1491117.7 | L45: 73899.764 | M45: 1417218 | N45: 63542.64 | P45: 405526.63 | Q45: 2049087.6 | T45: 19.79 | X45: 0 | Y45: https://www.annualreports.com/HostedData/AnnualReportArchive/g/guaranty-trust-bank-ltd_2016.pdf | Z45: 2016 annual report, as originally reported (public mirror copy) | AA45: Admitted this run
A46: GTBank | B46: 2017 | C46: Tier 1 | D46: IAS 39 | E46: 158727.7 | F46: 2824929 | G46: 2246352.2 | H46: 578576.78 | I46: 353397.33 | J46: 2613340.1 | K46: 1326250.4 | L46: 60278.707 | M46: 1265971.7 | N46: 11531.292 | Y46: https://gtbank-plc.files.svdcdn.com/production/financial-information/GTBank_AnnualReport_2018.pdf | Z46: 2018 annual report; 2017 restated comparative | AA46: Admitted this run
A47: GTBank | B47: 2018 | C47: Tier 1 | D47: IFRS 9 | E47: 166919.77 | F47: 2712521.5 | G47: 2200679.2 | H47: 511842.26 | I47: 224625.66 | J47: 2824929 | K47: 1158980.8 | L47: 90981.784 | M47: 1067999 | N47: 1384.004 | S47: 74667.995 | X47: 0 | Y47: https://gtbank-plc.files.svdcdn.com/production/financial-information/GTBank_AnnualReport_2018.pdf | Z47: 2018 annual report, as originally reported | AA47: Admitted this run
A48: GTBank | B48: 2019 | C48: Tier 1 | D48: IFRS 9 | E48: 175125.28 | F48: 3097248.5 | G48: 2491358.9 | H48: 605889.6 | I48: 197853.67 | J48: 2712521.5 | K48: 1357066.2 | L48: 56245.599 | M48: 1300820.6 | N48: 1859.247 | P48: 418652.17 | Q48: 2026402.6 | S48: 45503.961 | T48: 20.66 | X48: 0 | Y48: https://gtbank-plc.files.svdcdn.com/production/annual-reports/2019-annual-report/2019-Annual-Report.pdf?dm=1584983538 | Z48: 2019 annual report, as originally reported | AA48: Admitted this run
A49: GTBank | B49: 2020 | C49: Tier 1 | D49: IFRS 9 | E49: 178188.4 | F49: 4061543.6 | G49: 3359144.1 | H49: 702399.53 | I49: 327793.45 | J49: 3097248.5 | K49: 1473498.4 | L49: 62920.622 | M49: 1410577.7 | N49: 10555.467 | P49: 467871.04 | Q49: 2393202.2 | T49: 19.55 | U49: 16 | X49: 0 | Y49: https://doclib.ngxgroup.com/Financial_NewsDocs/32621_GUARANTY_TRUST_BANK_PLC%20_AUDITED_FINANCIAL_STATEMENT_.pdf | Z49: 2020 annual report, as originally reported | AA49: Admitted this run
A50: GTBank | B50: 2021 | C50: Tier 1 | D50: IFRS 9 | E50: 146184.07 | F50: 4357033.1 | G50: 3610197.6 | H50: 746835.58 | I50: 364670.77 | J50: 4061543.6 | M50: 1475674.2 | Y50: https://gtco-plc.files.svdcdn.com/production/financial-information/2021-ANNUAL-REPORT.pdf?dm=1648469779 | Z50: GTCO 2021 annual report: audited HoldCo package - explicit operating-bank subsidiary disclosure (GT Bank Nigeria condensed results) | AA50: Admitted this run
A51: GTBank | B51: 2022 | C51: Tier 1 | D51: IFRS 9 | E51: 145296.21 | F51: 5208576.8 | G51: 4412624.5 | H51: 795952.29 | I51: 671361.46 | J51: 4357033.1 | M51: 1577191.7 | Y51: https://gtco-plc.files.svdcdn.com/production/financial-information/2022-Annual-Report.pdf?dm=1687801902 | Z51: GTCO 2022 annual report: audited HoldCo package - explicit operating-bank subsidiary disclosure (GT Bank Nigeria condensed results) | AA51: Admitted this run
A52: Stanbic | B52: 2013 | C52: Tier 2 | D52: IAS 39 | E52: 10129 | F52: 725100 | G52: 654520 | H52: 70580 | J52: 650470 | M52: 289747 | N52: 2667 | Y52: https://thevault.exchange/?get_group_doc=18%2F1447238936-StanbicIBTCannualreport2013.pdf | Z52: Stanbic IBTC Holdings 2013 annual report: audited HoldCo package - explicit operating-bank subsidiary disclosure (note 13.4, Stanbic IBTC Bank PLC) | AA52: Admitted this run
A53: Stanbic | B53: 2014 | C53: Tier 2 | D53: IAS 39 | E53: 19456 | F53: 911052 | G53: 829231 | H53: 81821 | J53: 725100 | M53: 398604 | N53: 3217 | Y53: https://thevault.exchange/?get_group_doc=18/1447238694-StanbicIBTCFY14Annualreport.pdf | Z53: Stanbic IBTC Holdings 2014 annual report: audited HoldCo package - explicit operating-bank subsidiary disclosure (note 13.4, Stanbic IBTC Bank PLC) | AA53: Admitted this run
A54: Stanbic | B54: 2015 | C54: Tier 2 | D54: IAS 39 | E54: 6232 | F54: 890580 | G54: 795663 | H54: 94917 | J54: 908429 | M54: 353513 | N54: 14931 | Y54: https://www.thevault.exchange/?get_group_doc=635%2F1484830056-Annualreport2015final.pdf | Z54: Stanbic IBTC Holdings 2015 annual report: audited HoldCo package - explicit operating-bank subsidiary disclosure (note 13.4, Stanbic IBTC Bank PLC) | AA54: Admitted this run
A55: Stanbic | B55: 2016 | C55: Tier 2 | D55: IAS 39 | E55: 15030 | F55: 993759 | G55: 884443 | H55: 109316 | J55: 890580 | M55: 352965 | N55: 19803 | Y55: https://thevault.exchange?get_group_doc=635/1502962292-2016AnnualReport.pdf | Z55: Stanbic IBTC Holdings 2016 annual report: audited HoldCo package - explicit operating-bank subsidiary disclosure (note 13.4, Stanbic IBTC Bank PLC) | AA55: Admitted this run
A56: Stanbic | B56: 2017 | C56: Tier 2 | D56: IAS 39 | E56: 28842 | F56: 1332669 | G56: 1193969 | H56: 138700 | J56: 993759 | M56: 372088 | N56: 25577 | Y56: https://www.thevault.exchange/?get_group_doc=635%2F1526287152-2017AnnualReport-StanbicIBTCHoldingsPLC.pdf | Z56: Stanbic IBTC Holdings 2017 annual report: audited HoldCo package - explicit operating-bank subsidiary disclosure (note 13.4, Stanbic IBTC Bank PLC) | AA56: Admitted this run
A57: Stanbic | B57: 2018 | C57: Tier 2 | D57: IFRS 9 | E57: 49912 | F57: 1599245 | G57: 1428904 | H57: 170341 | J57: 1332723 | M57: 432713 | N57: -2988 | X57: 0 | Y57: https://www.stanbicibtcbank.com/static_file/Nigeria/nigeriabank/Annual%20Reports/2018%20Annual%20Report%20for%20Stanbic%20IBTC%20Bank.pdf | Z57: 2018 audited financial statements, as originally reported (issuer-hosted scanned extract) | AA57: Admitted this run
A58: Stanbic | B58: 2019 | C58: Tier 2 | D58: IFRS 9 | E58: 52287 | F58: 1792320 | G58: 1590980 | H58: 201340 | J58: 1599245 | M58: 532124 | N58: 1664 | X58: 0 | Y58: https://www.stanbicibtcbank.com/static_file/Nigeria/nigeriabank/Annual%20Reports/2019%20Annual%20Report%20for%20Stanbic%20IBTC%20Bank.pdf | Z58: 2019 audited financial statements, as originally reported (issuer-hosted scanned extract) | AA58: Admitted this run
A59: Stanbic | B59: 2020 | C59: Tier 2 | D59: IFRS 9 | E59: 59489 | F59: 2370347 | G59: 2128226 | H59: 242121 | I59: 465539 | K59: 655292 | L59: 30153 | M59: 625139 | N59: 10170 | P59: 221408 | Q59: 1140396 | S59: 21963 | T59: 19.4 | Y59: https://www.stanbicibtcbank.com/static_file/Nigeria/nigeriabank/Annual%20Reports/Stanbic%20IBTC%20Bank%20PLC%20Audited%20Financial%20Statement-%202021.pdf | Z59: 2021 audited financial statements; 2020 comparative, not labelled restated | AA59: Admitted this run
A60: Stanbic | B60: 2021 | C60: Tier 2 | D60: IFRS 9 | E60: 29570 | F60: 2614087 | G60: 2362312 | H60: 251775 | I60: 55771 | J60: 2370347 | K60: 946259 | L60: 25215 | M60: 921044 | N60: -1208 | P60: 226940 | Q60: 1405941 | S60: 15907 | T60: 16.1 | X60: 0 | Y60: https://www.stanbicibtcbank.com/static_file/Nigeria/nigeriabank/Annual%20Reports/Stanbic%20IBTC%20Bank%20PLC%20Audited%20Financial%20Statement-%202021.pdf | Z60: 2021 audited financial statements, as originally reported | AA60: Admitted this run
A61: Stanbic | B61: 2022 | C61: Tier 2 | D61: IFRS 9 | E61: 55150 | F61: 2854509 | G61: 2575402 | H61: 279107 | I61: -144391 | J61: 2614087 | K61: 1238195 | L61: 33410 | M61: 1204785 | N61: 10147 | P61: 284446 | Q61: 1545117 | S61: 20616 | T61: 18.4 | U61: 10 | X61: 0 | Y61: https://www.stanbicibtcbank.com/static_file/Nigeria/nigeriabank/Annual%20Reports/Stanbic%20IBTC%20Bank%20PLC%20Audited%20Financial%20Statement%20-2022.pdf | Z61: 2022 audited financial statements, as originally reported | AA61: Admitted this run
A62: Sterling | B62: 2013 | C62: Tier 2 | D62: IAS 39 | E62: 8274.864 | F62: 707797.18 | G62: 644339.29 | H62: 63457.896 | I62: -41953.972 | K62: 328664.9 | L62: 6921.156 | N62: 8259.094 | T62: 14 | Y62: https://sterling.ng/wp-content/uploads/2023/09/2014.pdf | Z62: Prior source-selection policy retained; original evidence preserved in accompanying pack. | AA62: Prior selected evidence
A63: Sterling | B63: 2014 | C63: Tier 2 | D63: IAS 39 | E63: 9004.973 | F63: 824539.43 | G63: 739824.14 | H63: 84715.285 | I63: -755.006 | J63: 707797.18 | K63: 380924.4 | L63: 9678.127 | N63: 7389.159 | T63: 14 | V63: 34 | W63: 1 | X63: 0 | Y63: https://sterling.ng/wp-content/uploads/2023/09/2014.pdf | Z63: Prior source-selection policy retained; original evidence preserved in accompanying pack. | AA63: Prior selected evidence
A64: Sterling | B64: 2015 | C64: Tier 2 | D64: IAS 39 | E64: 10292.577 | F64: 799451.42 | G64: 703885.67 | H64: 95565.747 | I64: 54691.995 | J64: 824539.43 | K64: 354474.86 | L64: 15748.585 | M64: 338726.27 | N64: 8151.338 | P64: 85262.476 | Q64: 487486.58 | T64: 17.49 | U64: 10 | X64: 0 | Y64: https://doclib.ngxgroup.com/Financial_NewsDocs/12716_STERLING_BANK_PLC_AUDITED_DEC_2015_FINANCIAL_STATEMENTS_MARCH_2016.pdf | Z64: 2015 annual report, as originally reported | AA64: Admitted this run
A65: Sterling | B65: 2016 | C65: Tier 2 | D65: IAS 39 | E65: 5180.964 | F65: 830802.22 | G65: 745123.6 | H65: 85678.622 | I65: -124892.48 | J65: 799451.42 | K65: 476713.16 | L65: 8463.293 | M65: 468249.87 | N65: 11713.968 | P65: 72046.139 | Q65: 675917.68 | T65: 10.66 | U65: 10 | X65: 0 | Y65: https://doclib.ngxgroup.com/Financial_NewsDocs/17024_STERLING_BANK_-_AUDITED_DEC_2016_FINANCIAL_STATEMENTS_MARCH_2017.pdf | Z65: 2016 annual report, as originally reported | AA65: Admitted this run
A66: Sterling | B66: 2017 | C66: Tier 2 | D66: IAS 39 | E66: 8455 | F66: 1068798 | G66: 965905 | H66: 102893 | I66: -46542 | J66: 830805 | K66: 617577 | L66: 19504 | M66: 598073 | N66: 12267 | P66: 83076 | Q66: 708114 | T66: 11.73 | U66: 10 | X66: 0 | Y66: https://doclib.ngxgroup.com/Financial_NewsDocs/21778_STERLING_BANK_PLC._FINANCIAL_STATEMENTS_APRIL_2018.pdf | Z66: 2017 annual report, as originally reported | AA66: Admitted this run
A67: Sterling | B67: 2018 | C67: Tier 2 | D67: IFRS 9 | E67: 9468 | F67: 1085876 | G67: 987867 | H67: 98009 | I67: 35086 | K67: 640678 | L67: 19661 | N67: 5832 | T67: 12.86 | U67: 10 | Y67: https://sterling.ng/wp-content/uploads/2020/03/FY-%E2%80%93-2019-Audited-Financials.pdf | Z67: Prior source-selection policy retained; original evidence preserved in accompanying pack. | AA67: Prior selected evidence
A68: Sterling | B68: 2019 | C68: Tier 2 | D68: IFRS 9 | E68: 10163 | F68: 1165509 | G68: 1046181 | H68: 119328 | I68: 114414 | J68: 1085876 | K68: 631698 | L68: 12966 | N68: 5842 | T68: 14.7 | U68: 10 | X68: 0 | Y68: https://sterling.ng/wp-content/uploads/2020/03/FY-%E2%80%93-2019-Audited-Financials.pdf | Z68: Prior source-selection policy retained; original evidence preserved in accompanying pack. | AA68: Prior selected evidence
A69: Sterling | B69: 2020 | C69: Tier 2 | D69: IFRS 9 | E69: 11110 | F69: 1281830 | G69: 1146440 | H69: 135390 | I69: 4406 | J69: 1165509 | K69: 613359 | L69: 16532 | M69: 596827 | N69: 7913 | P69: 138703 | Q69: 771587 | T69: 17.98 | U69: 10 | X69: 0 | Y69: https://doclib.ngxgroup.com/Financial_NewsDocs/32843_STERLING_BANK_PLC%20_AUDITED_FINANCIAL_STATEMENT_FOR_20.pdf | Z69: 2020 annual report, as originally reported | AA69: Admitted this run
A70: Sterling | B70: 2021 | C70: Tier 2 | D70: IFRS 9 | E70: 13403 | F70: 1611749 | G70: 1470733 | H70: 141016 | I70: 145027 | J70: 1281830 | K70: 726080 | L70: 14180 | M70: 711900 | N70: 9822 | P70: 140952 | Q70: 951379 | T70: 14.82 | U70: 10 | X70: 0 | Y70: https://doclib.ngxgroup.com/Financial_NewsDocs/35540_STERLING_BANK_PLC%20_AUDITED_FINANCIAL_STATEMENT_FOR_20.pdf | Z70: 2021 annual report, as originally reported | AA70: Admitted this run
A71: Sterling | B71: 2022 | C71: Tier 2 | D71: IFRS 9 | E71: 19327 | F71: 1840622 | G71: 1687070 | H71: 153552 | I71: 70837 | J71: 1606898 | K71: 758183 | L71: 20448 | M71: 737735 | N71: 9084 | P71: 148600 | Q71: 1012661 | T71: 14.67 | U71: 10 | X71: 0 | Y71: https://doclib.ngxgroup.com/Financial_NewsDocs/38472_STERLING_BANK_PLC.-_QUARTER_5_-_FINANCIAL_STATEMENT_FOR_2022_FINANCIAL_STATEMENTS_MAY_2023.pdf | Z71: 2022 annual report, as originally reported | AA71: Admitted this run
A72: UBA | B72: 2013 | C72: Tier 1 | D72: IAS 39 | E72: 46483 | F72: 2217417 | G72: 1957879 | H72: 259538 | I72: -136104 | K72: 805259 | L72: 8317 | N72: 181 | T72: 20 | Y72: https://www.ubagroup.com/wp-content/uploads/2018/08/2014-audited-financial-stateme_YQ8NW_20150414021324a7zd72ag66.pdf | Z72: Prior source-selection policy retained; original evidence preserved in accompanying pack. | AA72: Prior selected evidence
A73: UBA | B73: 2014 | C73: Tier 1 | D73: IAS 39 | E73: 40083 | F73: 2338858 | G73: 2056925 | H73: 281933 | I73: -92619 | J73: 2217417 | K73: 895109 | L73: 10522 | N73: 3073 | T73: 17 | Y73: https://www.ubagroup.com/wp-content/uploads/2018/08/2014-audited-financial-stateme_YQ8NW_20150414021324a7zd72ag66.pdf | Z73: Prior source-selection policy retained; original evidence preserved in accompanying pack. | AA73: Prior selected evidence
A74: UBA | B74: 2015 | C74: Tier 1 | D74: IAS 39 | E74: 47642 | F74: 2216337 | G74: 1878106 | H74: 338231 | I74: 58408 | J74: 2338858 | K74: 835737 | L74: 13043 | M74: 822694 | N74: 3491 | P74: 241091 | Q74: 1208372 | T74: 20 | V74: 52.57 | W74: 1 | Y74: https://www.ubagroup.com/wp-content/uploads/2018/08/UBA-Plc-2016-Annual-reports-and-Accounts_Low-Resolution.VAR_.pdf | Z74: 2016 report 2015 comparative Bank columns; opening assets retained from the prior selected 2014 statement. | AA74: Primary report checked in this update
A75: UBA | B75: 2016 | C75: Tier 1 | D75: IAS 39 | E75: 47541 | F75: 2539585 | G75: 2148685 | H75: 390900 | I75: -213392 | J75: 2216337 | K75: 1120096 | L75: 29741 | M75: 1090355 | N75: 25521 | P75: 262423 | Q75: 1331901 | T75: 20 | U75: 15 | V75: 38.57 | W75: 1 | Y75: https://www.ubagroup.com/wp-content/uploads/2018/08/UBA-Plc-2016-Annual-reports-and-Accounts_Low-Resolution.VAR_.pdf | Z75: 2016 report current-year Bank columns. | AA75: Primary report checked in this update
A76: UBA | B76: 2017 | C76: Tier 1 | D76: IAS 39 | E76: 41396 | F76: 2931826 | G76: 2530966 | H76: 400860 | I76: 59151 | J76: 2539585 | K76: 1204426 | L76: 31212 | M76: 1173214 | N76: 30433 | P76: 255027 | Q76: 1265087 | T76: 20 | V76: 49.69 | W76: 1 | Y76: https://www.ubagroup.com/wp-content/uploads/2019/09/UBA-Plc-2018-Annual-Report-and-Acocunts.pdf | Z76: Prior source-selection policy retained; original evidence preserved in accompanying pack. | AA76: Prior selected evidence
A77: UBA | B77: 2018 | C77: Tier 1 | D77: IFRS 9 | E77: 41047 | F77: 3591305 | G77: 3226707 | H77: 364598 | I77: 488626 | J77: 2931826 | K77: 1274112 | L77: 60311 | M77: 1213801 | N77: 4257 | P77: 245482 | Q77: 1248509 | S77: 36951 | T77: 20 | U77: 16 | V77: 55.84 | W77: 1 | Y77: https://www.ubagroup.com/wp-content/uploads/2019/09/UBA-Plc-2018-Annual-Report-and-Acocunts.pdf | Z77: Prior source-selection policy retained; original evidence preserved in accompanying pack. | AA77: Prior selected evidence
A78: UBA | B78: 2019 | C78: Tier 1 | D78: IFRS 9 | E78: 62750 | F78: 4136493 | G78: 3689971 | H78: 446522 | I78: -317453 | J78: 3591305 | K78: 1557358 | L78: 53978 | M78: 1503380 | N78: 16369 | P78: 285664 | Q78: 1328231 | S78: 21215 | T78: 22 | V78: 43.99 | W78: 1 | Y78: https://www.ubagroup.com/wp-content/uploads/2021/03/UBA-Plc-2020-Annual-Report-and-Accounts.pdf | Z78: Prior source-selection policy retained; original evidence preserved in accompanying pack. | AA78: Prior selected evidence
A79: UBA | B79: 2020 | C79: Tier 1 | D79: IFRS 9 | E79: 56911 | F79: 5207833 | G79: 4729893 | H79: 477940 | I79: 735114 | J79: 4136493 | K79: 1874858 | L79: 62322 | M79: 1812536 | N79: 21864 | P79: 276315 | Q79: 1402955 | S79: 21933 | T79: 20 | U79: 15 | V79: 44.3 | W79: 1 | Y79: https://www.ubagroup.com/wp-content/uploads/2021/03/UBA-Plc-2020-Annual-Report-and-Accounts.pdf | Z79: Prior source-selection policy retained; original evidence preserved in accompanying pack. | AA79: Prior selected evidence
A80: UBA | B80: 2021 | C80: Tier 1 | D80: IFRS 9 | E80: 58669 | F80: 5574976 | G80: 5073375 | H80: 501601 | I80: 671619 | J80: 5207833 | K80: 1913403 | L80: 65301 | M80: 1848102 | N80: 9749 | P80: 336784 | Q80: 1543338 | T80: 21.8 | V80: 47.56 | W80: 1 | Y80: https://doclib.ngxgroup.com/Financial_NewsDocs/37990_UNITED_BANK_FOR_AFRICA_PLC-_QUARTER_5_-_FINANCIAL_STATEMENT_FOR_2022_FINANCIAL_STATEMENTS_MARCH_2023.pdf | Z80: Prior source-selection policy retained; original evidence preserved in accompanying pack. | AA80: Prior selected evidence
A81: UBA | B81: 2022 | C81: Tier 1 | D81: IFRS 9 | E81: 133696 | F81: 7361044 | G81: 6775851 | H81: 585193 | I81: 1063228 | J81: 5574976 | K81: 2174779 | L81: 51682 | M81: 2123097 | N81: 10565 | P81: 369520 | Q81: 1690930 | T81: 21.9 | U81: 17 | V81: 59.03 | W81: 0 | Y81: https://doclib.ngxgroup.com/Financial_NewsDocs/37990_UNITED_BANK_FOR_AFRICA_PLC-_QUARTER_5_-_FINANCIAL_STATEMENT_FOR_2022_FINANCIAL_STATEMENTS_MARCH_2023.pdf | Z81: Prior source-selection policy retained; original evidence preserved in accompanying pack. | AA81: Prior selected evidence
A82: Union | B82: 2013 | C82: Tier 2 | D82: IAS 39 | E82: 5121 | F82: 882097 | G82: 694313 | H82: 187784 | I82: -93031 | K82: 230720 | L82: 20602 | O82: 13644 | T82: 24.8 | Y82: https://doclib.ngxgroup.com/Financial_NewsDocs/FinancialStatementFull_UNION%20BANK%20NIG.PLC._2015-04-15.pdf | Z82: Prior source-selection policy retained; original evidence preserved in accompanying pack. | AA82: Prior selected evidence
A83: Union | B83: 2014 | C83: Tier 2 | D83: IAS 39 | E83: 20486 | F83: 920936 | G83: 714962 | H83: 205974 | I83: -121957 | J83: 882097 | K83: 325748 | L83: 23376 | O83: 16756 | T83: 16.39 | Y83: https://doclib.ngxgroup.com/Financial_NewsDocs/FinancialStatementFull_UNION%20BANK%20NIG.PLC._2015-04-15.pdf | Z83: Prior source-selection policy retained; original evidence preserved in accompanying pack. | AA83: Prior selected evidence
A84: Union | B84: 2015 | C84: Tier 2 | D84: IAS 39 | E84: 18035 | F84: 1000976 | G84: 767469 | H84: 233507 | I84: 10975 | J84: 922755 | K84: 370949 | L84: 21965 | M84: 348984 | N84: 9177 | P84: 93697 | Q84: 587515 | T84: 15.9 | Y84: https://cdn.nairametrics.com/wp-content/uploads/2017/03/UNION_BANK_PLC_-_AUDITED_DEC_2016_FINANCIAL_STATEMENTS_MARCH_2017.pdf | Z84: 2016 annual report; 2015 restated comparative | AA84: Admitted this run
A85: Union | B85: 2016 | C85: Tier 2 | D85: IAS 39 | E85: 15885 | F85: 1123483 | G85: 872144 | H85: 251339 | I85: -70133 | J85: 1000976 | K85: 518349 | L85: 28459 | M85: 489890 | N85: 15769 | P85: 96309 | Q85: 724660 | T85: 13.3 | U85: 15 | X85: 0 | Y85: https://cdn.nairametrics.com/wp-content/uploads/2017/03/UNION_BANK_PLC_-_AUDITED_DEC_2016_FINANCIAL_STATEMENTS_MARCH_2017.pdf | Z85: 2016 annual report, as originally reported | AA85: Admitted this run
A86: Union | B86: 2017 | C86: Tier 2 | D86: IAS 39 | E86: 11239 | F86: 1334921 | G86: 1015802 | H86: 319119 | I86: 68160 | J86: 1123483 | K86: 531807 | L86: 43252 | M86: 488555 | N86: 25478 | O86: 110685 | P86: 137875 | Q86: 774497 | T86: 17.8 | U86: 15 | Y86: https://greenwichregistrars.com/wp-content/uploads/2021/06/2018-Annual-Report_UBN_New.pdf | Z86: 2018 report: restated 2017 main statements | AA86: New page-checked Union reports
A87: Union | B87: 2018 | C87: Tier 2 | D87: IFRS 9 | E87: 18438 | F87: 1324297 | G87: 1124210 | H87: 200087 | I87: 37394 | J87: 1334921 | K87: 473396 | L87: 45359 | M87: 428037 | N87: -3515 | O87: 38496 | P87: 88017 | Q87: 767770 | R87: 123328 | S87: 30149 | T87: 11.5 | U87: 15 | X87: 0 | Y87: https://greenwichregistrars.com/wp-content/uploads/2021/06/2018-Annual-Report_UBN_New.pdf | Z87: Original 2018 presentation; loan reinstatement alternatives held separately | AA87: New page-checked Union reports
A88: Union | B88: 2019 | C88: Tier 2 | D88: IFRS 9 | E88: 24375 | F88: 1711739 | G88: 1480547 | H88: 231192 | I88: 207318 | J88: 1324297 | K88: 595298 | L88: 44685 | M88: 550613 | N88: -504 | O88: 34760 | P88: 139997 | Q88: 880146 | R88: 58769 | S88: 16198 | T88: 15.91 | U88: 15 | Y88: https://doclib.ngxgroup.com/Financial_NewsDocs/32629_UNION_BANK_OF_NIGERIA_PLC%20_AUDITED_FINANCIAL_STATEMENT.pdf | Z88: 2020 audited-report comparative | AA88: New page-checked Union reports
A89: Union | B89: 2020 | C89: Tier 2 | D89: IFRS 9 | E89: 24653 | F89: 2073758 | G89: 1826237 | H89: 247521 | I89: -35912 | J89: 1711739 | K89: 736712 | L89: 43909 | M89: 692803 | N89: -2559 | P89: 156168 | Q89: 990958 | R89: 61895 | S89: 22564 | T89: 15.76 | U89: 15 | X89: 0 | Y89: https://doclib.ngxgroup.com/Financial_NewsDocs/32629_UNION_BANK_OF_NIGERIA_PLC%20_AUDITED_FINANCIAL_STATEMENT.pdf | Z89: 2020 audited-report current-year | AA89: New page-checked Union reports
A90: Union | B90: 2021 | C90: Tier 2 | D90: IFRS 9 | E90: 19180 | F90: 2567441 | G90: 2315954 | H90: 251487 | I90: 252140 | J90: 2073758 | K90: 899106 | L90: 30266 | M90: 868840 | N90: 286 | O90: 38660 | P90: 156040 | Q90: 1068135 | R90: 62064 | S90: 13274 | T90: 14.61 | Y90: https://doclib.ngxgroup.com/Financial_NewsDocs/38269_UNION_BANK_OF_NIGERIA_PLC-_QUARTER_5_-_FINANCIAL_STATEMENT_FOR_2022_FINANCIAL_STATEMENTS_APRIL_2023.pdf | Z90: 2022 audited-report comparative | AA90: New page-checked Union reports
A91: Union | B91: 2022 | C91: Tier 2 | D91: IFRS 9 | E91: 29009 | F91: 2793674 | G91: 2503824 | H91: 289850 | I91: 80277 | J91: 2567441 | K91: 1000903 | L91: 32015 | M91: 968888 | N91: 4475 | O91: 40276 | P91: 180613 | Q91: 1252579 | R91: 74070 | T91: 14.42 | U91: 10 | X91: 0 | Y91: https://doclib.ngxgroup.com/Financial_NewsDocs/38269_UNION_BANK_OF_NIGERIA_PLC-_QUARTER_5_-_FINANCIAL_STATEMENT_FOR_2022_FINANCIAL_STATEMENTS_APRIL_2023.pdf | Z91: 2022 audited-report current-year | AA91: New page-checked Union reports
A92: Unity | B92: 2013 | C92: Tier 2 | D92: IAS 39 | E92: -22582.339 | F92: 403629.29 | G92: 375416.65 | H92: 28212.639 | I92: 23788.331 | M92: 195229.57 | N92: 21592.692 | Y92: https://doclib.ngxgroup.com/Financial_NewsDocs/8794_UNITY_BANK_2014_AUDITED_ACCOUNTS_FINANCIAL_STATEMENTS_MARCH_2015.pdf | Z92: 2014 report comparative (not labelled restated) | AA92: Admitted this run
A93: Unity | B93: 2014 | C93: Tier 2 | D93: IAS 39 | E93: 10692.476 | F93: 413305.11 | G93: 337041.12 | H93: 76263.995 | I93: -32248.858 | J93: 403629.29 | M93: 219335.35 | N93: 15054.246 | Y93: https://doclib.ngxgroup.com/Financial_NewsDocs/8794_UNITY_BANK_2014_AUDITED_ACCOUNTS_FINANCIAL_STATEMENTS_MARCH_2015.pdf | Z93: 2014 annual report, as originally reported | AA93: Admitted this run
A94: Unity | B94: 2015 | C94: Tier 2 | D94: IAS 39 | E94: 4689.157 | F94: 443321.01 | G94: 360746.48 | H94: 82574.531 | I94: -36691.17 | J94: 413305.11 | K94: 311897.55 | L94: 65754.418 | M94: 246143.13 | N94: 27122.182 | X94: 0 | Y94: https://doclib.ngxgroup.com/Financial_NewsDocs/13702_UNITY_BANK_-_2015_AUDITED_ACCOUNTS_FINANCIAL_STATEMENTS_MAY_2016.pdf | Z94: 2015 annual report, as originally reported | AA94: Admitted this run
A95: Unity | B95: 2016 | C95: Tier 2 | D95: IAS 39 | E95: 2183.798 | F95: 492681.65 | G95: 409574.67 | H95: 83106.98 | I95: -23320.526 | J95: 443321.01 | K95: 378758.6 | L95: 101544.08 | M95: 277214.52 | N95: 35948.596 | P95: -217551.64 | Q95: 463106.4 | T95: -46.98 | X95: 0 | Y95: https://doclib.ngxgroup.com/Financial_NewsDocs/17362_UNITY_BANK_PLC_-_AUDITED_DEC_2016_FINANCIAL_STATEMENTS_APRIL_2017.pdf | Z95: 2016 annual report, as originally reported | AA95: Admitted this run
A96: Unity | B96: 2017 | C96: Tier 2 | D96: IAS 39 | E96: -14917.938 | F96: 156506.5 | G96: 398699.66 | H96: -242193.15 | I96: -6744.837 | J96: 492681.65 | K96: 9467.163 | L96: 509.036 | M96: 8958.127 | N96: 44254.863 | P96: -263292.55 | Q96: 132926.38 | T96: -198.07 | X96: 0 | Y96: https://doclib.ngxgroup.com/Financial_NewsDocs/24374_UNITY_BANK_PLC_FINANCIAL_STATEMENTS_NOVEMBER_2018.pdf | Z96: 2017 annual report, as originally reported | AA96: Admitted this run
A97: Unity | B97: 2018 | C97: Tier 2 | D97: IFRS 9 | E97: -7695.32 | F97: 210800.84 | G97: 495175.49 | H97: -284374.65 | I97: -442.603 | K97: 44841.156 | L97: 744.197 | N97: 5958.492 | T97: -214.8 | U97: 10 | Y97: https://doclib.ngxgroup.com/Financial_NewsDocs/30502_UNITY_BANK_PLC_FINANCIAL_STATEMENTS_JUNE_2020.pdf | Z97: Prior source-selection policy retained; original evidence preserved in accompanying pack. | AA97: Prior selected evidence
A98: Unity | B98: 2019 | C98: Tier 2 | D98: IFRS 9 | E98: 3383.189 | F98: 293052.07 | G98: 571907.96 | H98: -278855.89 | I98: -39427.662 | J98: 210800.84 | K98: 106913.81 | L98: 2896.088 | N98: 1921.923 | T98: -201.59 | U98: 10 | X98: 1 | Y98: https://doclib.ngxgroup.com/Financial_NewsDocs/30502_UNITY_BANK_PLC_FINANCIAL_STATEMENTS_JUNE_2020.pdf | Z98: Prior source-selection policy retained; original evidence preserved in accompanying pack. | AA98: Prior selected evidence
A99: Unity | B99: 2020 | C99: Tier 2 | D99: IFRS 9 | E99: 2086.393 | F99: 492020.33 | G99: 767430.12 | H99: -275409.8 | I99: 15353.812 | K99: 206205.54 | L99: 4124.689 | M99: 202080.86 | N99: -4127.332 | Y99: https://doclib.ngxgroup.com/Financial_NewsDocs/35987_UNITY_BANK_PLC%20_AUDITED_FINANCIAL_STATEMENT_FOR_2021_F.pdf | Z99: 2021 report comparative (not labelled restated) | AA99: Admitted this run
A100: Unity | B100: 2021 | C100: Tier 2 | D100: IFRS 9 | E100: 3173.254 | F100: 538868.76 | G100: 815022.21 | H100: -276153.46 | I100: -64852.553 | J100: 492020.33 | K100: 272468.9 | L100: 3199.184 | M100: 269269.72 | N100: -2563.927 | P100: -278060.63 | Q100: 322639.56 | R100: 105.854 | S100: 1.012 | T100: -86.18 | X100: 1 | Y100: https://doclib.ngxgroup.com/Financial_NewsDocs/35987_UNITY_BANK_PLC%20_AUDITED_FINANCIAL_STATEMENT_FOR_2021_F.pdf | Z100: 2021 annual report, as originally reported | AA100: Admitted this run
A101: Unity | B101: 2022 | C101: Tier 2 | D101: IFRS 9 | E101: 941.375 | F101: 510143.96 | G101: 785092.13 | H101: -274948.17 | I101: -26933.973 | J101: 538868.76 | K101: 292968.65 | L101: 3612.947 | M101: 289355.7 | N101: -1203.857 | P101: -288192.17 | Q101: 321334.34 | R101: 472.953 | S101: 121.67 | T101: -89.69 | X101: 1 | Y101: https://doclib.ngxgroup.com/Financial_NewsDocs/38722_UNITY_BANK_PLC-_QUARTER_5_-_FINANCIAL_STATEMENT_FOR_2022_FINANCIAL_STATEMENTS_JUNE_2023.pdf | Z101: 2022 annual report, as originally reported | AA101: Admitted this run
...

Sheet Calculated_Ratios
A1: Formulas reference Panel_Inputs. Python-recomputed values are compared in Formula_Check.
A3: bank | B3: year | C3: average_assets | D3: roa | E3: eqta | F3: ocf_ratio | G3: allr | H3: car_computed | I3: impairment_assets | J3: broad_coverage | K3: npl_calc | L3: stage3_ratio | M3: stage3_coverage | N3: roa_closing | O3: leverage | P3: ln_assets | Q3: balance_residual | R3: loan_residual | S3: liquidity_used | T3: car_buffer
A4: =Panel_Inputs!A4 -> Access | B4: =Panel_Inputs!B4 -> 2013 | C4: =IF(AND(ISNUMBER(Panel_Inputs!F4),ISNUMBER(Panel_Inputs!J4)),IF(AND(Panel_Inputs!F4>0,Panel_Inputs!J4>0),(Panel_Inputs!F4+Panel_Inputs!J4)/2,""),"") | D4: =IF(AND(ISNUMBER(Panel_Inputs!E4),ISNUMBER(C4)),IF(C4>0,100*Panel_Inputs!E4/C4,""),"") | E4: =IF(AND(ISNUMBER(Panel_Inputs!H4),ISNUMBER(Panel_Inputs!F4)),IF(Panel_Inputs!F4>0,100*Panel_Inputs!H4/Panel_Inputs!F4,""),"") -> 14.387821 | F4: =IF(AND(ISNUMBER(Panel_Inputs!I4),ISNUMBER(C4)),IF(C4>0,100*Panel_Inputs!I4/C4,""),"") | G4: =IF(AND(ISNUMBER(Panel_Inputs!L4),ISNUMBER(Panel_Inputs!K4)),IF(Panel_Inputs!K4>0,100*Panel_Inputs!L4/Panel_Inputs!K4,""),"") | H4: =IF(AND(ISNUMBER(Panel_Inputs!P4),ISNUMBER(Panel_Inputs!Q4)),IF(Panel_Inputs!Q4>0,100*Panel_Inputs!P4/Panel_Inputs!Q4,""),"") | I4: =IF(AND(ISNUMBER(Panel_Inputs!N4),ISNUMBER(C4)),IF(C4>0,100*Panel_Inputs!N4/C4,""),"") | J4: =IF(AND(ISNUMBER(Panel_Inputs!L4),ISNUMBER(Panel_Inputs!O4)),IF(Panel_Inputs!O4>0,100*Panel_Inputs!L4/Panel_Inputs!O4,""),"") | K4: =IF(AND(ISNUMBER(Panel_Inputs!O4),ISNUMBER(Panel_Inputs!K4)),IF(Panel_Inputs!K4>0,100*Panel_Inputs!O4/Panel_Inputs!K4,""),"") | L4: =IF(AND(ISNUMBER(Panel_Inputs!R4),ISNUMBER(Panel_Inputs!K4)),IF(Panel_Inputs!K4>0,100*Panel_Inputs!R4/Panel_Inputs!K4,""),"") | M4: =IF(AND(ISNUMBER(Panel_Inputs!S4),ISNUMBER(Panel_Inputs!R4)),IF(Panel_Inputs!R4>0,100*Panel_Inputs!S4/Panel_Inputs!R4,""),"") | N4: =IF(AND(ISNUMBER(Panel_Inputs!E4),ISNUMBER(Panel_Inputs!F4)),IF(Panel_Inputs!F4>0,100*Panel_Inputs!E4/Panel_Inputs!F4,""),"") -> 1.5381689 | O4: =IF(AND(ISNUMBER(Panel_Inputs!G4),ISNUMBER(Panel_Inputs!F4)),IF(Panel_Inputs!F4>0,100*Panel_Inputs!G4/Panel_Inputs!F4,""),"") -> 85.612179 | P4: =IF(ISNUMBER(Panel_Inputs!F4),IF(Panel_Inputs!F4>0,LN(Panel_Inputs!F4),""),"") -> 14.348544 | Q4: =IF(AND(ISNUMBER(Panel_Inputs!F4),ISNUMBER(Panel_Inputs!G4),ISNUMBER(Panel_Inputs!H4)),Panel_Inputs!F4-Panel_Inputs!G4-Panel_Inputs!H4,"") -> 0 | R4: =IF(AND(ISNUMBER(Panel_Inputs!K4),ISNUMBER(Panel_Inputs!L4),ISNUMBER(Panel_Inputs!M4)),Panel_Inputs!K4-Panel_Inputs!L4-Panel_Inputs!M4,"") | S4: =IF(AND(ISNUMBER(Panel_Inputs!V4),Panel_Inputs!W4=1),Panel_Inputs!V4,"") | T4: =IF(AND(ISNUMBER(Panel_Inputs!T4),ISNUMBER(Panel_Inputs!U4)),Panel_Inputs!T4-Panel_Inputs!U4,"")
A5: =Panel_Inputs!A5 -> Access | B5: =Panel_Inputs!B5 -> 2014 | C5: =IF(AND(ISNUMBER(Panel_Inputs!F5),ISNUMBER(Panel_Inputs!J5)),IF(AND(Panel_Inputs!F5>0,Panel_Inputs!J5>0),(Panel_Inputs!F5+Panel_Inputs!J5)/2,""),"") -> 1843024.9 | D5: =IF(AND(ISNUMBER(Panel_Inputs!E5),ISNUMBER(C5)),IF(C5>0,100*Panel_Inputs!E5/C5,""),"") -> 2.1671507 | E5: =IF(AND(ISNUMBER(Panel_Inputs!H5),ISNUMBER(Panel_Inputs!F5)),IF(Panel_Inputs!F5>0,100*Panel_Inputs!H5/Panel_Inputs!F5,""),"") -> 13.832589 | F5: =IF(AND(ISNUMBER(Panel_Inputs!I5),ISNUMBER(C5)),IF(C5>0,100*Panel_Inputs!I5/C5,""),"") | G5: =IF(AND(ISNUMBER(Panel_Inputs!L5),ISNUMBER(Panel_Inputs!K5)),IF(Panel_Inputs!K5>0,100*Panel_Inputs!L5/Panel_Inputs!K5,""),"") | H5: =IF(AND(ISNUMBER(Panel_Inputs!P5),ISNUMBER(Panel_Inputs!Q5)),IF(Panel_Inputs!Q5>0,100*Panel_Inputs!P5/Panel_Inputs!Q5,""),"") | I5: =IF(AND(ISNUMBER(Panel_Inputs!N5),ISNUMBER(C5)),IF(C5>0,100*Panel_Inputs!N5/C5,""),"") -> 0.57564606 | J5: =IF(AND(ISNUMBER(Panel_Inputs!L5),ISNUMBER(Panel_Inputs!O5)),IF(Panel_Inputs!O5>0,100*Panel_Inputs!L5/Panel_Inputs!O5,""),"") | K5: =IF(AND(ISNUMBER(Panel_Inputs!O5),ISNUMBER(Panel_Inputs!K5)),IF(Panel_Inputs!K5>0,100*Panel_Inputs!O5/Panel_Inputs!K5,""),"") | L5: =IF(AND(ISNUMBER(Panel_Inputs!R5),ISNUMBER(Panel_Inputs!K5)),IF(Panel_Inputs!K5>0,100*Panel_Inputs!R5/Panel_Inputs!K5,""),"") | M5: =IF(AND(ISNUMBER(Panel_Inputs!S5),ISNUMBER(Panel_Inputs!R5)),IF(Panel_Inputs!R5>0,100*Panel_Inputs!S5/Panel_Inputs!R5,""),"") | N5: =IF(AND(ISNUMBER(Panel_Inputs!E5),ISNUMBER(Panel_Inputs!F5)),IF(Panel_Inputs!F5>0,100*Panel_Inputs!E5/Panel_Inputs!F5,""),"") -> 2.015238 | O5: =IF(AND(ISNUMBER(Panel_Inputs!G5),ISNUMBER(Panel_Inputs!F5)),IF(Panel_Inputs!F5>0,100*Panel_Inputs!G5/Panel_Inputs!F5,""),"") -> 86.167411 | P5: =IF(ISNUMBER(Panel_Inputs!F5),IF(Panel_Inputs!F5>0,LN(Panel_Inputs!F5),""),"") -> 14.499595 | Q5: =IF(AND(ISNUMBER(Panel_Inputs!F5),ISNUMBER(Panel_Inputs!G5),ISNUMBER(Panel_Inputs!H5)),Panel_Inputs!F5-Panel_Inputs!G5-Panel_Inputs!H5,"") -> 0.0010000001 | R5: =IF(AND(ISNUMBER(Panel_Inputs!K5),ISNUMBER(Panel_Inputs!L5),ISNUMBER(Panel_Inputs!M5)),Panel_Inputs!K5-Panel_Inputs!L5-Panel_Inputs!M5,"") | S5: =IF(AND(ISNUMBER(Panel_Inputs!V5),Panel_Inputs!W5=1),Panel_Inputs!V5,"") | T5: =IF(AND(ISNUMBER(Panel_Inputs!T5),ISNUMBER(Panel_Inputs!U5)),Panel_Inputs!T5-Panel_Inputs!U5,"")
A6: =Panel_Inputs!A6 -> Access | B6: =Panel_Inputs!B6 -> 2015 | C6: =IF(AND(ISNUMBER(Panel_Inputs!F6),ISNUMBER(Panel_Inputs!J6)),IF(AND(Panel_Inputs!F6>0,Panel_Inputs!J6>0),(Panel_Inputs!F6+Panel_Inputs!J6)/2,""),"") -> 2196949.9 | D6: =IF(AND(ISNUMBER(Panel_Inputs!E6),ISNUMBER(C6)),IF(C6>0,100*Panel_Inputs!E6/C6,""),"") -> 2.682116 | E6: =IF(AND(ISNUMBER(Panel_Inputs!H6),ISNUMBER(Panel_Inputs!F6)),IF(Panel_Inputs!F6>0,100*Panel_Inputs!H6/Panel_Inputs!F6,""),"") -> 14.943502 | F6: =IF(AND(ISNUMBER(Panel_Inputs!I6),ISNUMBER(C6)),IF(C6>0,100*Panel_Inputs!I6/C6,""),"") -> -8.2499202 | G6: =IF(AND(ISNUMBER(Panel_Inputs!L6),ISNUMBER(Panel_Inputs!K6)),IF(Panel_Inputs!K6>0,100*Panel_Inputs!L6/Panel_Inputs!K6,""),"") -> 2.1183867 | H6: =IF(AND(ISNUMBER(Panel_Inputs!P6),ISNUMBER(Panel_Inputs!Q6)),IF(Panel_Inputs!Q6>0,100*Panel_Inputs!P6/Panel_Inputs!Q6,""),"") -> 18.039786 | I6: =IF(AND(ISNUMBER(Panel_Inputs!N6),ISNUMBER(C6)),IF(C6>0,100*Panel_Inputs!N6/C6,""),"") -> 0.60482094 | J6: =IF(AND(ISNUMBER(Panel_Inputs!L6),ISNUMBER(Panel_Inputs!O6)),IF(Panel_Inputs!O6>0,100*Panel_Inputs!L6/Panel_Inputs!O6,""),"") | K6: =IF(AND(ISNUMBER(Panel_Inputs!O6),ISNUMBER(Panel_Inputs!K6)),IF(Panel_Inputs!K6>0,100*Panel_Inputs!O6/Panel_Inputs!K6,""),"") | L6: =IF(AND(ISNUMBER(Panel_Inputs!R6),ISNUMBER(Panel_Inputs!K6)),IF(Panel_Inputs!K6>0,100*Panel_Inputs!R6/Panel_Inputs!K6,""),"") | M6: =IF(AND(ISNUMBER(Panel_Inputs!S6),ISNUMBER(Panel_Inputs!R6)),IF(Panel_Inputs!R6>0,100*Panel_Inputs!S6/Panel_Inputs!R6,""),"") | N6: =IF(AND(ISNUMBER(Panel_Inputs!E6),ISNUMBER(Panel_Inputs!F6)),IF(Panel_Inputs!F6>0,100*Panel_Inputs!E6/Panel_Inputs!F6,""),"") -> 2.4430395 | O6: =IF(AND(ISNUMBER(Panel_Inputs!G6),ISNUMBER(Panel_Inputs!F6)),IF(Panel_Inputs!F6>0,100*Panel_Inputs!G6/Panel_Inputs!F6,""),"") -> 85.056498 | P6: =IF(ISNUMBER(Panel_Inputs!F6),IF(Panel_Inputs!F6>0,LN(Panel_Inputs!F6),""),"") -> 14.695944 | Q6: =IF(AND(ISNUMBER(Panel_Inputs!F6),ISNUMBER(Panel_Inputs!G6),ISNUMBER(Panel_Inputs!H6)),Panel_Inputs!F6-Panel_Inputs!G6-Panel_Inputs!H6,"") -> 0 | R6: =IF(AND(ISNUMBER(Panel_Inputs!K6),ISNUMBER(Panel_Inputs!L6),ISNUMBER(Panel_Inputs!M6)),Panel_Inputs!K6-Panel_Inputs!L6-Panel_Inputs!M6,"") -> 0 | S6: =IF(AND(ISNUMBER(Panel_Inputs!V6),Panel_Inputs!W6=1),Panel_Inputs!V6,"") | T6: =IF(AND(ISNUMBER(Panel_Inputs!T6),ISNUMBER(Panel_Inputs!U6)),Panel_Inputs!T6-Panel_Inputs!U6,"") -> 2
A7: =Panel_Inputs!A7 -> Access | B7: =Panel_Inputs!B7 -> 2016 | C7: =IF(AND(ISNUMBER(Panel_Inputs!F7),ISNUMBER(Panel_Inputs!J7)),IF(AND(Panel_Inputs!F7>0,Panel_Inputs!J7>0),(Panel_Inputs!F7+Panel_Inputs!J7)/2,""),"") -> 2753452.3 | D7: =IF(AND(ISNUMBER(Panel_Inputs!E7),ISNUMBER(C7)),IF(C7>0,100*Panel_Inputs!E7/C7,""),"") -> 2.325304 | E7: =IF(AND(ISNUMBER(Panel_Inputs!H7),ISNUMBER(Panel_Inputs!F7)),IF(Panel_Inputs!F7>0,100*Panel_Inputs!H7/Panel_Inputs!F7,""),"") -> 13.624685 | F7: =IF(AND(ISNUMBER(Panel_Inputs!I7),ISNUMBER(C7)),IF(C7>0,100*Panel_Inputs!I7/C7,""),"") -> -4.5083614 | G7: =IF(AND(ISNUMBER(Panel_Inputs!L7),ISNUMBER(Panel_Inputs!K7)),IF(Panel_Inputs!K7>0,100*Panel_Inputs!L7/Panel_Inputs!K7,""),"") -> 1.8632945 | H7: =IF(AND(ISNUMBER(Panel_Inputs!P7),ISNUMBER(Panel_Inputs!Q7)),IF(Panel_Inputs!Q7>0,100*Panel_Inputs!P7/Panel_Inputs!Q7,""),"") -> 19.554571 | I7: =IF(AND(ISNUMBER(Panel_Inputs!N7),ISNUMBER(C7)),IF(C7>0,100*Panel_Inputs!N7/C7,""),"") -> 0.64069122 | J7: =IF(AND(ISNUMBER(Panel_Inputs!L7),ISNUMBER(Panel_Inputs!O7)),IF(Panel_Inputs!O7>0,100*Panel_Inputs!L7/Panel_Inputs!O7,""),"") | K7: =IF(AND(ISNUMBER(Panel_Inputs!O7),ISNUMBER(Panel_Inputs!K7)),IF(Panel_Inputs!K7>0,100*Panel_Inputs!O7/Panel_Inputs!K7,""),"") | L7: =IF(AND(ISNUMBER(Panel_Inputs!R7),ISNUMBER(Panel_Inputs!K7)),IF(Panel_Inputs!K7>0,100*Panel_Inputs!R7/Panel_Inputs!K7,""),"") | M7: =IF(AND(ISNUMBER(Panel_Inputs!S7),ISNUMBER(Panel_Inputs!R7)),IF(Panel_Inputs!R7>0,100*Panel_Inputs!S7/Panel_Inputs!R7,""),"") | N7: =IF(AND(ISNUMBER(Panel_Inputs!E7),ISNUMBER(Panel_Inputs!F7)),IF(Panel_Inputs!F7>0,100*Panel_Inputs!E7/Panel_Inputs!F7,""),"") -> 2.0687222 | O7: =IF(AND(ISNUMBER(Panel_Inputs!G7),ISNUMBER(Panel_Inputs!F7)),IF(Panel_Inputs!F7>0,100*Panel_Inputs!G7/Panel_Inputs!F7,""),"") -> 86.375315 | P7: =IF(ISNUMBER(Panel_Inputs!F7),IF(Panel_Inputs!F7>0,LN(Panel_Inputs!F7),""),"") -> 14.945286 | Q7: =IF(AND(ISNUMBER(Panel_Inputs!F7),ISNUMBER(Panel_Inputs!G7),ISNUMBER(Panel_Inputs!H7)),Panel_Inputs!F7-Panel_Inputs!G7-Panel_Inputs!H7,"") -> 0 | R7: =IF(AND(ISNUMBER(Panel_Inputs!K7),ISNUMBER(Panel_Inputs!L7),ISNUMBER(Panel_Inputs!M7)),Panel_Inputs!K7-Panel_Inputs!L7-Panel_Inputs!M7,"") -> 0 | S7: =IF(AND(ISNUMBER(Panel_Inputs!V7),Panel_Inputs!W7=1),Panel_Inputs!V7,"") | T7: =IF(AND(ISNUMBER(Panel_Inputs!T7),ISNUMBER(Panel_Inputs!U7)),Panel_Inputs!T7-Panel_Inputs!U7,"") -> 3.55
A8: =Panel_Inputs!A8 -> Access | B8: =Panel_Inputs!B8 -> 2017 | C8: =IF(AND(ISNUMBER(Panel_Inputs!F8),ISNUMBER(Panel_Inputs!J8)),IF(AND(Panel_Inputs!F8>0,Panel_Inputs!J8>0),(Panel_Inputs!F8+Panel_Inputs!J8)/2,""),"") -> 3297322.2 | D8: =IF(AND(ISNUMBER(Panel_Inputs!E8),ISNUMBER(C8)),IF(C8>0,100*Panel_Inputs!E8/C8,""),"") -> 1.6146078 | E8: =IF(AND(ISNUMBER(Panel_Inputs!H8),ISNUMBER(Panel_Inputs!F8)),IF(Panel_Inputs!F8>0,100*Panel_Inputs!H8/Panel_Inputs!F8,""),"") -> 13.415243 | F8: =IF(AND(ISNUMBER(Panel_Inputs!I8),ISNUMBER(C8)),IF(C8>0,100*Panel_Inputs!I8/C8,""),"") -> 3.1650131 | G8: =IF(AND(ISNUMBER(Panel_Inputs!L8),ISNUMBER(Panel_Inputs!K8)),IF(Panel_Inputs!K8>0,100*Panel_Inputs!L8/Panel_Inputs!K8,""),"") -> 3.0800099 | H8: =IF(AND(ISNUMBER(Panel_Inputs!P8),ISNUMBER(Panel_Inputs!Q8)),IF(Panel_Inputs!Q8>0,100*Panel_Inputs!P8/Panel_Inputs!Q8,""),"") -> 18.175202 | I8: =IF(AND(ISNUMBER(Panel_Inputs!N8),ISNUMBER(C8)),IF(C8>0,100*Panel_Inputs!N8/C8,""),"") -> 0.88404611 | J8: =IF(AND(ISNUMBER(Panel_Inputs!L8),ISNUMBER(Panel_Inputs!O8)),IF(Panel_Inputs!O8>0,100*Panel_Inputs!L8/Panel_Inputs!O8,""),"") | K8: =IF(AND(ISNUMBER(Panel_Inputs!O8),ISNUMBER(Panel_Inputs!K8)),IF(Panel_Inputs!K8>0,100*Panel_Inputs!O8/Panel_Inputs!K8,""),"") | L8: =IF(AND(ISNUMBER(Panel_Inputs!R8),ISNUMBER(Panel_Inputs!K8)),IF(Panel_Inputs!K8>0,100*Panel_Inputs!R8/Panel_Inputs!K8,""),"") | M8: =IF(AND(ISNUMBER(Panel_Inputs!S8),ISNUMBER(Panel_Inputs!R8)),IF(Panel_Inputs!R8>0,100*Panel_Inputs!S8/Panel_Inputs!R8,""),"") | N8: =IF(AND(ISNUMBER(Panel_Inputs!E8),ISNUMBER(Panel_Inputs!F8)),IF(Panel_Inputs!F8>0,100*Panel_Inputs!E8/Panel_Inputs!F8,""),"") -> 1.5212466 | O8: =IF(AND(ISNUMBER(Panel_Inputs!G8),ISNUMBER(Panel_Inputs!F8)),IF(Panel_Inputs!F8>0,100*Panel_Inputs!G8/Panel_Inputs!F8,""),"") -> 86.584757 | P8: =IF(ISNUMBER(Panel_Inputs!F8),IF(Panel_Inputs!F8>0,LN(Panel_Inputs!F8),""),"") -> 15.068183 | Q8: =IF(AND(ISNUMBER(Panel_Inputs!F8),ISNUMBER(Panel_Inputs!G8),ISNUMBER(Panel_Inputs!H8)),Panel_Inputs!F8-Panel_Inputs!G8-Panel_Inputs!H8,"") -> 0 | R8: =IF(AND(ISNUMBER(Panel_Inputs!K8),ISNUMBER(Panel_Inputs!L8),ISNUMBER(Panel_Inputs!M8)),Panel_Inputs!K8-Panel_Inputs!L8-Panel_Inputs!M8,"") -> -0.0010000002 | S8: =IF(AND(ISNUMBER(Panel_Inputs!V8),Panel_Inputs!W8=1),Panel_Inputs!V8,"") | T8: =IF(AND(ISNUMBER(Panel_Inputs!T8),ISNUMBER(Panel_Inputs!U8)),Panel_Inputs!T8-Panel_Inputs!U8,"") -> 2.18
A9: =Panel_Inputs!A9 -> Access | B9: =Panel_Inputs!B9 -> 2018 | C9: =IF(AND(ISNUMBER(Panel_Inputs!F9),ISNUMBER(Panel_Inputs!J9)),IF(AND(Panel_Inputs!F9>0,Panel_Inputs!J9>0),(Panel_Inputs!F9+Panel_Inputs!J9)/2,""),"") | D9: =IF(AND(ISNUMBER(Panel_Inputs!E9),ISNUMBER(C9)),IF(C9>0,100*Panel_Inputs!E9/C9,""),"") | E9: =IF(AND(ISNUMBER(Panel_Inputs!H9),ISNUMBER(Panel_Inputs!F9)),IF(Panel_Inputs!F9>0,100*Panel_Inputs!H9/Panel_Inputs!F9,""),"") -> 11.108544 | F9: =IF(AND(ISNUMBER(Panel_Inputs!I9),ISNUMBER(C9)),IF(C9>0,100*Panel_Inputs!I9/C9,""),"") | G9: =IF(AND(ISNUMBER(Panel_Inputs!L9),ISNUMBER(Panel_Inputs!K9)),IF(Panel_Inputs!K9>0,100*Panel_Inputs!L9/Panel_Inputs!K9,""),"") | H9: =IF(AND(ISNUMBER(Panel_Inputs!P9),ISNUMBER(Panel_Inputs!Q9)),IF(Panel_Inputs!Q9>0,100*Panel_Inputs!P9/Panel_Inputs!Q9,""),"") | I9: =IF(AND(ISNUMBER(Panel_Inputs!N9),ISNUMBER(C9)),IF(C9>0,100*Panel_Inputs!N9/C9,""),"") | J9: =IF(AND(ISNUMBER(Panel_Inputs!L9),ISNUMBER(Panel_Inputs!O9)),IF(Panel_Inputs!O9>0,100*Panel_Inputs!L9/Panel_Inputs!O9,""),"") | K9: =IF(AND(ISNUMBER(Panel_Inputs!O9),ISNUMBER(Panel_Inputs!K9)),IF(Panel_Inputs!K9>0,100*Panel_Inputs!O9/Panel_Inputs!K9,""),"") | L9: =IF(AND(ISNUMBER(Panel_Inputs!R9),ISNUMBER(Panel_Inputs!K9)),IF(Panel_Inputs!K9>0,100*Panel_Inputs!R9/Panel_Inputs!K9,""),"") | M9: =IF(AND(ISNUMBER(Panel_Inputs!S9),ISNUMBER(Panel_Inputs!R9)),IF(Panel_Inputs!R9>0,100*Panel_Inputs!S9/Panel_Inputs!R9,""),"") | N9: =IF(AND(ISNUMBER(Panel_Inputs!E9),ISNUMBER(Panel_Inputs!F9)),IF(Panel_Inputs!F9>0,100*Panel_Inputs!E9/Panel_Inputs!F9,""),"") -> 1.8546918 | O9: =IF(AND(ISNUMBER(Panel_Inputs!G9),ISNUMBER(Panel_Inputs!F9)),IF(Panel_Inputs!F9>0,100*Panel_Inputs!G9/Panel_Inputs!F9,""),"") -> 88.891456 | P9: =IF(ISNUMBER(Panel_Inputs!F9),IF(Panel_Inputs!F9>0,LN(Panel_Inputs!F9),""),"") -> 15.193802 | Q9: =IF(AND(ISNUMBER(Panel_Inputs!F9),ISNUMBER(Panel_Inputs!G9),ISNUMBER(Panel_Inputs!H9)),Panel_Inputs!F9-Panel_Inputs!G9-Panel_Inputs!H9,"") -> 0 | R9: =IF(AND(ISNUMBER(Panel_Inputs!K9),ISNUMBER(Panel_Inputs!L9),ISNUMBER(Panel_Inputs!M9)),Panel_Inputs!K9-Panel_Inputs!L9-Panel_Inputs!M9,"") | S9: =IF(AND(ISNUMBER(Panel_Inputs!V9),Panel_Inputs!W9=1),Panel_Inputs!V9,"") | T9: =IF(AND(ISNUMBER(Panel_Inputs!T9),ISNUMBER(Panel_Inputs!U9)),Panel_Inputs!T9-Panel_Inputs!U9,"")
A10: =Panel_Inputs!A10 -> Access | B10: =Panel_Inputs!B10 -> 2019 | C10: =IF(AND(ISNUMBER(Panel_Inputs!F10),ISNUMBER(Panel_Inputs!J10)),IF(AND(Panel_Inputs!F10>0,Panel_Inputs!J10>0),(Panel_Inputs!F10+Panel_Inputs!J10)/2,""),"") -> 5139577.9 | D10: =IF(AND(ISNUMBER(Panel_Inputs!E10),ISNUMBER(C10)),IF(C10>0,100*Panel_Inputs!E10/C10,""),"") -> 1.4314221 | E10: =IF(AND(ISNUMBER(Panel_Inputs!H10),ISNUMBER(Panel_Inputs!F10)),IF(Panel_Inputs!F10>0,100*Panel_Inputs!H10/Panel_Inputs!F10,""),"") -> 8.6030352 | F10: =IF(AND(ISNUMBER(Panel_Inputs!I10),ISNUMBER(C10)),IF(C10>0,100*Panel_Inputs!I10/C10,""),"") -> 21.296948 | G10: =IF(AND(ISNUMBER(Panel_Inputs!L10),ISNUMBER(Panel_Inputs!K10)),IF(Panel_Inputs!K10>0,100*Panel_Inputs!L10/Panel_Inputs!K10,""),"") -> 6.797786 | H10: =IF(AND(ISNUMBER(Panel_Inputs!P10),ISNUMBER(Panel_Inputs!Q10)),IF(Panel_Inputs!Q10>0,100*Panel_Inputs!P10/Panel_Inputs!Q10,""),"") | I10: =IF(AND(ISNUMBER(Panel_Inputs!N10),ISNUMBER(C10)),IF(C10>0,100*Panel_Inputs!N10/C10,""),"") -> 0.40967331 | J10: =IF(AND(ISNUMBER(Panel_Inputs!L10),ISNUMBER(Panel_Inputs!O10)),IF(Panel_Inputs!O10>0,100*Panel_Inputs!L10/Panel_Inputs!O10,""),"") | K10: =IF(AND(ISNUMBER(Panel_Inputs!O10),ISNUMBER(Panel_Inputs!K10)),IF(Panel_Inputs!K10>0,100*Panel_Inputs!O10/Panel_Inputs!K10,""),"") | L10: =IF(AND(ISNUMBER(Panel_Inputs!R10),ISNUMBER(Panel_Inputs!K10)),IF(Panel_Inputs!K10>0,100*Panel_Inputs!R10/Panel_Inputs!K10,""),"") | M10: =IF(AND(ISNUMBER(Panel_Inputs!S10),ISNUMBER(Panel_Inputs!R10)),IF(Panel_Inputs!R10>0,100*Panel_Inputs!S10/Panel_Inputs!R10,""),"") | N10: =IF(AND(ISNUMBER(Panel_Inputs!E10),ISNUMBER(Panel_Inputs!F10)),IF(Panel_Inputs!F10>0,100*Panel_Inputs!E10/Panel_Inputs!F10,""),"") -> 1.1657197 | O10: =IF(AND(ISNUMBER(Panel_Inputs!G10),ISNUMBER(Panel_Inputs!F10)),IF(Panel_Inputs!F10>0,100*Panel_Inputs!G10/Panel_Inputs!F10,""),"") -> 91.396965 | P10: =IF(ISNUMBER(Panel_Inputs!F10),IF(Panel_Inputs!F10>0,LN(Panel_Inputs!F10),""),"") -> 15.657811 | Q10: =IF(AND(ISNUMBER(Panel_Inputs!F10),ISNUMBER(Panel_Inputs!G10),ISNUMBER(Panel_Inputs!H10)),Panel_Inputs!F10-Panel_Inputs!G10-Panel_Inputs!H10,"") -> 0 | R10: =IF(AND(ISNUMBER(Panel_Inputs!K10),ISNUMBER(Panel_Inputs!L10),ISNUMBER(Panel_Inputs!M10)),Panel_Inputs!K10-Panel_Inputs!L10-Panel_Inputs!M10,"") -> -0.0010000002 | S10: =IF(AND(ISNUMBER(Panel_Inputs!V10),Panel_Inputs!W10=1),Panel_Inputs!V10,"") | T10: =IF(AND(ISNUMBER(Panel_Inputs!T10),ISNUMBER(Panel_Inputs!U10)),Panel_Inputs!T10-Panel_Inputs!U10,"")
A11: =Panel_Inputs!A11 -> Access | B11: =Panel_Inputs!B11 -> 2020 | C11: =IF(AND(ISNUMBER(Panel_Inputs!F11),ISNUMBER(Panel_Inputs!J11)),IF(AND(Panel_Inputs!F11>0,Panel_Inputs!J11>0),(Panel_Inputs!F11+Panel_Inputs!J11)/2,""),"") -> 6966284 | D11: =IF(AND(ISNUMBER(Panel_Inputs!E11),ISNUMBER(C11)),IF(C11>0,100*Panel_Inputs!E11/C11,""),"") -> 1.148953 | E11: =IF(AND(ISNUMBER(Panel_Inputs!H11),ISNUMBER(Panel_Inputs!F11)),IF(Panel_Inputs!F11>0,100*Panel_Inputs!H11/Panel_Inputs!F11,""),"") -> 8.5757036 | F11: =IF(AND(ISNUMBER(Panel_Inputs!I11),ISNUMBER(C11)),IF(C11>0,100*Panel_Inputs!I11/C11,""),"") -> -0.93891214 | G11: =IF(AND(ISNUMBER(Panel_Inputs!L11),ISNUMBER(Panel_Inputs!K11)),IF(Panel_Inputs!K11>0,100*Panel_Inputs!L11/Panel_Inputs!K11,""),"") -> 4.051935 | H11: =IF(AND(ISNUMBER(Panel_Inputs!P11),ISNUMBER(Panel_Inputs!Q11)),IF(Panel_Inputs!Q11>0,100*Panel_Inputs!P11/Panel_Inputs!Q11,""),"") -> 15.87392 | I11: =IF(AND(ISNUMBER(Panel_Inputs!N11),ISNUMBER(C11)),IF(C11>0,100*Panel_Inputs!N11/C11,""),"") -> 0.56917835 | J11: =IF(AND(ISNUMBER(Panel_Inputs!L11),ISNUMBER(Panel_Inputs!O11)),IF(Panel_Inputs!O11>0,100*Panel_Inputs!L11/Panel_Inputs!O11,""),"") | K11: =IF(AND(ISNUMBER(Panel_Inputs!O11),ISNUMBER(Panel_Inputs!K11)),IF(Panel_Inputs!K11>0,100*Panel_Inputs!O11/Panel_Inputs!K11,""),"") | L11: =IF(AND(ISNUMBER(Panel_Inputs!R11),ISNUMBER(Panel_Inputs!K11)),IF(Panel_Inputs!K11>0,100*Panel_Inputs!R11/Panel_Inputs!K11,""),"") | M11: =IF(AND(ISNUMBER(Panel_Inputs!S11),ISNUMBER(Panel_Inputs!R11)),IF(Panel_Inputs!R11>0,100*Panel_Inputs!S11/Panel_Inputs!R11,""),"") | N11: =IF(AND(ISNUMBER(Panel_Inputs!E11),ISNUMBER(Panel_Inputs!F11)),IF(Panel_Inputs!F11>0,100*Panel_Inputs!E11/Panel_Inputs!F11,""),"") -> 1.0496989 | O11: =IF(AND(ISNUMBER(Panel_Inputs!G11),ISNUMBER(Panel_Inputs!F11)),IF(Panel_Inputs!F11>0,100*Panel_Inputs!G11/Panel_Inputs!F11,""),"") -> 91.424296 | P11: =IF(ISNUMBER(Panel_Inputs!F11),IF(Panel_Inputs!F11>0,LN(Panel_Inputs!F11),""),"") -> 15.84694 | Q11: =IF(AND(ISNUMBER(Panel_Inputs!F11),ISNUMBER(Panel_Inputs!G11),ISNUMBER(Panel_Inputs!H11)),Panel_Inputs!F11-Panel_Inputs!G11-Panel_Inputs!H11,"") -> 0 | R11: =IF(AND(ISNUMBER(Panel_Inputs!K11),ISNUMBER(Panel_Inputs!L11),ISNUMBER(Panel_Inputs!M11)),Panel_Inputs!K11-Panel_Inputs!L11-Panel_Inputs!M11,"") -> 0 | S11: =IF(AND(ISNUMBER(Panel_Inputs!V11),Panel_Inputs!W11=1),Panel_Inputs!V11,"") | T11: =IF(AND(ISNUMBER(Panel_Inputs!T11),ISNUMBER(Panel_Inputs!U11)),Panel_Inputs!T11-Panel_Inputs!U11,"") -> -0.13
A12: =Panel_Inputs!A12 -> Access | B12: =Panel_Inputs!B12 -> 2021 | C12: =IF(AND(ISNUMBER(Panel_Inputs!F12),ISNUMBER(Panel_Inputs!J12)),IF(AND(Panel_Inputs!F12>0,Panel_Inputs!J12>0),(Panel_Inputs!F12+Panel_Inputs!J12)/2,""),"") -> 8642870.1 | D12: =IF(AND(ISNUMBER(Panel_Inputs!E12),ISNUMBER(C12)),IF(C12>0,100*Panel_Inputs!E12/C12,""),"") -> 1.2880731 | E12: =IF(AND(ISNUMBER(Panel_Inputs!H12),ISNUMBER(Panel_Inputs!F12)),IF(Panel_Inputs!F12>0,100*Panel_Inputs!H12/Panel_Inputs!F12,""),"") -> 9.0205125 | F12: =IF(AND(ISNUMBER(Panel_Inputs!I12),ISNUMBER(C12)),IF(C12>0,100*Panel_Inputs!I12/C12,""),"") -> 5.7947742 | G12: =IF(AND(ISNUMBER(Panel_Inputs!L12),ISNUMBER(Panel_Inputs!K12)),IF(Panel_Inputs!K12>0,100*Panel_Inputs!L12/Panel_Inputs!K12,""),"") -> 2.6213171 | H12: =IF(AND(ISNUMBER(Panel_Inputs!P12),ISNUMBER(Panel_Inputs!Q12)),IF(Panel_Inputs!Q12>0,100*Panel_Inputs!P12/Panel_Inputs!Q12,""),"") -> 20.930667 | I12: =IF(AND(ISNUMBER(Panel_Inputs!N12),ISNUMBER(C12)),IF(C12>0,100*Panel_Inputs!N12/C12,""),"") -> 0.62248922 | J12: =IF(AND(ISNUMBER(Panel_Inputs!L12),ISNUMBER(Panel_Inputs!O12)),IF(Panel_Inputs!O12>0,100*Panel_Inputs!L12/Panel_Inputs!O12,""),"") | K12: =IF(AND(ISNUMBER(Panel_Inputs!O12),ISNUMBER(Panel_Inputs!K12)),IF(Panel_Inputs!K12>0,100*Panel_Inputs!O12/Panel_Inputs!K12,""),"") | L12: =IF(AND(ISNUMBER(Panel_Inputs!R12),ISNUMBER(Panel_Inputs!K12)),IF(Panel_Inputs!K12>0,100*Panel_Inputs!R12/Panel_Inputs!K12,""),"") | M12: =IF(AND(ISNUMBER(Panel_Inputs!S12),ISNUMBER(Panel_Inputs!R12)),IF(Panel_Inputs!R12>0,100*Panel_Inputs!S12/Panel_Inputs!R12,""),"") | N12: =IF(AND(ISNUMBER(Panel_Inputs!E12),ISNUMBER(Panel_Inputs!F12)),IF(Panel_Inputs!F12>0,100*Panel_Inputs!E12/Panel_Inputs!F12,""),"") -> 1.1523574 | O12: =IF(AND(ISNUMBER(Panel_Inputs!G12),ISNUMBER(Panel_Inputs!F12)),IF(Panel_Inputs!F12>0,100*Panel_Inputs!G12/Panel_Inputs!F12,""),"") -> 90.979487 | P12: =IF(ISNUMBER(Panel_Inputs!F12),IF(Panel_Inputs!F12>0,LN(Panel_Inputs!F12),""),"") -> 16.083583 | Q12: =IF(AND(ISNUMBER(Panel_Inputs!F12),ISNUMBER(Panel_Inputs!G12),ISNUMBER(Panel_Inputs!H12)),Panel_Inputs!F12-Panel_Inputs!G12-Panel_Inputs!H12,"") -> 0 | R12: =IF(AND(ISNUMBER(Panel_Inputs!K12),ISNUMBER(Panel_Inputs!L12),ISNUMBER(Panel_Inputs!M12)),Panel_Inputs!K12-Panel_Inputs!L12-Panel_Inputs!M12,"") -> -0.0010000002 | S12: =IF(AND(ISNUMBER(Panel_Inputs!V12),Panel_Inputs!W12=1),Panel_Inputs!V12,"") | T12: =IF(AND(ISNUMBER(Panel_Inputs!T12),ISNUMBER(Panel_Inputs!U12)),Panel_Inputs!T12-Panel_Inputs!U12,"")
A13: =Panel_Inputs!A13 -> Access | B13: =Panel_Inputs!B13 -> 2022 | C13: =IF(AND(ISNUMBER(Panel_Inputs!F13),ISNUMBER(Panel_Inputs!J13)),IF(AND(Panel_Inputs!F13>0,Panel_Inputs!J13>0),(Panel_Inputs!F13+Panel_Inputs!J13)/2,""),"") -> 11098020 | D13: =IF(AND(ISNUMBER(Panel_Inputs!E13),ISNUMBER(C13)),IF(C13>0,100*Panel_Inputs!E13/C13,""),"") -> 1.5017092 | E13: =IF(AND(ISNUMBER(Panel_Inputs!H13),ISNUMBER(Panel_Inputs!F13)),IF(Panel_Inputs!F13>0,100*Panel_Inputs!H13/Panel_Inputs!F13,""),"") -> 8.5252743 | F13: =IF(AND(ISNUMBER(Panel_Inputs!I13),ISNUMBER(C13)),IF(C13>0,100*Panel_Inputs!I13/C13,""),"") -> 6.2941675 | G13: =IF(AND(ISNUMBER(Panel_Inputs!L13),ISNUMBER(Panel_Inputs!K13)),IF(Panel_Inputs!K13>0,100*Panel_Inputs!L13/Panel_Inputs!K13,""),"") -> 1.5679567 | H13: =IF(AND(ISNUMBER(Panel_Inputs!P13),ISNUMBER(Panel_Inputs!Q13)),IF(Panel_Inputs!Q13>0,100*Panel_Inputs!P13/Panel_Inputs!Q13,""),"") -> 17.845932 | I13: =IF(AND(ISNUMBER(Panel_Inputs!N13),ISNUMBER(C13)),IF(C13>0,100*Panel_Inputs!N13/C13,""),"") -> 1.0693889 | J13: =IF(AND(ISNUMBER(Panel_Inputs!L13),ISNUMBER(Panel_Inputs!O13)),IF(Panel_Inputs!O13>0,100*Panel_Inputs!L13/Panel_Inputs!O13,""),"") | K13: =IF(AND(ISNUMBER(Panel_Inputs!O13),ISNUMBER(Panel_Inputs!K13)),IF(Panel_Inputs!K13>0,100*Panel_Inputs!O13/Panel_Inputs!K13,""),"") | L13: =IF(AND(ISNUMBER(Panel_Inputs!R13),ISNUMBER(Panel_Inputs!K13)),IF(Panel_Inputs!K13>0,100*Panel_Inputs!R13/Panel_Inputs!K13,""),"") | M13: =IF(AND(ISNUMBER(Panel_Inputs!S13),ISNUMBER(Panel_Inputs!R13)),IF(Panel_Inputs!R13>0,100*Panel_Inputs!S13/Panel_Inputs!R13,""),"") | N13: =IF(AND(ISNUMBER(Panel_Inputs!E13),ISNUMBER(Panel_Inputs!F13)),IF(Panel_Inputs!F13>0,100*Panel_Inputs!E13/Panel_Inputs!F13,""),"") -> 1.3295275 | O13: =IF(AND(ISNUMBER(Panel_Inputs!G13),ISNUMBER(Panel_Inputs!F13)),IF(Panel_Inputs!F13>0,100*Panel_Inputs!G13/Panel_Inputs!F13,""),"") -> 91.474726 | P13: =IF(ISNUMBER(Panel_Inputs!F13),IF(Panel_Inputs!F13>0,LN(Panel_Inputs!F13),""),"") -> 16.344058 | Q13: =IF(AND(ISNUMBER(Panel_Inputs!F13),ISNUMBER(Panel_Inputs!G13),ISNUMBER(Panel_Inputs!H13)),Panel_Inputs!F13-Panel_Inputs!G13-Panel_Inputs!H13,"") -> 0 | R13: =IF(AND(ISNUMBER(Panel_Inputs!K13),ISNUMBER(Panel_Inputs!L13),ISNUMBER(Panel_Inputs!M13)),Panel_Inputs!K13-Panel_Inputs!L13-Panel_Inputs!M13,"") -> 0 | S13: =IF(AND(ISNUMBER(Panel_Inputs!V13),Panel_Inputs!W13=1),Panel_Inputs!V13,"") | T13: =IF(AND(ISNUMBER(Panel_Inputs!T13),ISNUMBER(Panel_Inputs!U13)),Panel_Inputs!T13-Panel_Inputs!U13,"")
A14: =Panel_Inputs!A14 -> Ecobank Nigeria | B14: =Panel_Inputs!B14 -> 2013 | C14: =IF(AND(ISNUMBER(Panel_Inputs!F14),ISNUMBER(Panel_Inputs!J14)),IF(AND(Panel_Inputs!F14>0,Panel_Inputs!J14>0),(Panel_Inputs!F14+Panel_Inputs!J14)/2,""),"") -> 1393063 | D14: =IF(AND(ISNUMBER(Panel_Inputs!E14),ISNUMBER(C14)),IF(C14>0,100*Panel_Inputs!E14/C14,""),"") -> 0.83686093 | E14: =IF(AND(ISNUMBER(Panel_Inputs!H14),ISNUMBER(Panel_Inputs!F14)),IF(Panel_Inputs!F14>0,100*Panel_Inputs!H14/Panel_Inputs!F14,""),"") -> 10.721989 | F14: =IF(AND(ISNUMBER(Panel_Inputs!I14),ISNUMBER(C14)),IF(C14>0,100*Panel_Inputs!I14/C14,""),"") -> 0.33063831 | G14: =IF(AND(ISNUMBER(Panel_Inputs!L14),ISNUMBER(Panel_Inputs!K14)),IF(Panel_Inputs!K14>0,100*Panel_Inputs!L14/Panel_Inputs!K14,""),"") -> 5.2703828 | H14: =IF(AND(ISNUMBER(Panel_Inputs!P14),ISNUMBER(Panel_Inputs!Q14)),IF(Panel_Inputs!Q14>0,100*Panel_Inputs!P14/Panel_Inputs!Q14,""),"") -> 17.385859 | I14: =IF(AND(ISNUMBER(Panel_Inputs!N14),ISNUMBER(C14)),IF(C14>0,100*Panel_Inputs!N14/C14,""),"") -> 2.3405977 | J14: =IF(AND(ISNUMBER(Panel_Inputs!L14),ISNUMBER(Panel_Inputs!O14)),IF(Panel_Inputs!O14>0,100*Panel_Inputs!L14/Panel_Inputs!O14,""),"") | K14: =IF(AND(ISNUMBER(Panel_Inputs!O14),ISNUMBER(Panel_Inputs!K14)),IF(Panel_Inputs!K14>0,100*Panel_Inputs!O14/Panel_Inputs!K14,""),"") | L14: =IF(AND(ISNUMBER(Panel_Inputs!R14),ISNUMBER(Panel_Inputs!K14)),IF(Panel_Inputs!K14>0,100*Panel_Inputs!R14/Panel_Inputs!K14,""),"") | M14: =IF(AND(ISNUMBER(Panel_Inputs!S14),ISNUMBER(Panel_Inputs!R14)),IF(Panel_Inputs!R14>0,100*Panel_Inputs!S14/Panel_Inputs!R14,""),"") | N14: =IF(AND(ISNUMBER(Panel_Inputs!E14),ISNUMBER(Panel_Inputs!F14)),IF(Panel_Inputs!F14>0,100*Panel_Inputs!E14/Panel_Inputs!F14,""),"") -> 0.79804985 | O14: =IF(AND(ISNUMBER(Panel_Inputs!G14),ISNUMBER(Panel_Inputs!F14)),IF(Panel_Inputs!F14>0,100*Panel_Inputs!G14/Panel_Inputs!F14,""),"") -> 89.278011 | P14: =IF(ISNUMBER(Panel_Inputs!F14),IF(Panel_Inputs!F14>0,LN(Panel_Inputs!F14),""),"") -> 14.194502 | Q14: =IF(AND(ISNUMBER(Panel_Inputs!F14),ISNUMBER(Panel_Inputs!G14),ISNUMBER(Panel_Inputs!H14)),Panel_Inputs!F14-Panel_Inputs!G14-Panel_Inputs!H14,"") -> 0 | R14: =IF(AND(ISNUMBER(Panel_Inputs!K14),ISNUMBER(Panel_Inputs!L14),ISNUMBER(Panel_Inputs!M14)),Panel_Inputs!K14-Panel_Inputs!L14-Panel_Inputs!M14,"") -> 0 | S14: =IF(AND(ISNUMBER(Panel_Inputs!V14),Panel_Inputs!W14=1),Panel_Inputs!V14,"") | T14: =IF(AND(ISNUMBER(Panel_Inputs!T14),ISNUMBER(Panel_Inputs!U14)),Panel_Inputs!T14-Panel_Inputs!U14,"")
A15: =Panel_Inputs!A15 -> Ecobank Nigeria | B15: =Panel_Inputs!B15 -> 2014 | C15: =IF(AND(ISNUMBER(Panel_Inputs!F15),ISNUMBER(Panel_Inputs!J15)),IF(AND(Panel_Inputs!F15>0,Panel_Inputs!J15>0),(Panel_Inputs!F15+Panel_Inputs!J15)/2,""),"") -> 1616866.5 | D15: =IF(AND(ISNUMBER(Panel_Inputs!E15),ISNUMBER(C15)),IF(C15>0,100*Panel_Inputs!E15/C15,""),"") -> 1.8389273 | E15: =IF(AND(ISNUMBER(Panel_Inputs!H15),ISNUMBER(Panel_Inputs!F15)),IF(Panel_Inputs!F15>0,100*Panel_Inputs!H15/Panel_Inputs!F15,""),"") -> 11.190227 | F15: =IF(AND(ISNUMBER(Panel_Inputs!I15),ISNUMBER(C15)),IF(C15>0,100*Panel_Inputs!I15/C15,""),"") -> -6.8466382 | G15: =IF(AND(ISNUMBER(Panel_Inputs!L15),ISNUMBER(Panel_Inputs!K15)),IF(Panel_Inputs!K15>0,100*Panel_Inputs!L15/Panel_Inputs!K15,""),"") -> 4.1070684 | H15: =IF(AND(ISNUMBER(Panel_Inputs!P15),ISNUMBER(Panel_Inputs!Q15)),IF(Panel_Inputs!Q15>0,100*Panel_Inputs!P15/Panel_Inputs!Q15,""),"") -> 16.033592 | I15: =IF(AND(ISNUMBER(Panel_Inputs!N15),ISNUMBER(C15)),IF(C15>0,100*Panel_Inputs!N15/C15,""),"") -> 2.0406137 | J15: =IF(AND(ISNUMBER(Panel_Inputs!L15),ISNUMBER(Panel_Inputs!O15)),IF(Panel_Inputs!O15>0,100*Panel_Inputs!L15/Panel_Inputs!O15,""),"") | K15: =IF(AND(ISNUMBER(Panel_Inputs!O15),ISNUMBER(Panel_Inputs!K15)),IF(Panel_Inputs!K15>0,100*Panel_Inputs!O15/Panel_Inputs!K15,""),"") | L15: =IF(AND(ISNUMBER(Panel_Inputs!R15),ISNUMBER(Panel_Inputs!K15)),IF(Panel_Inputs!K15>0,100*Panel_Inputs!R15/Panel_Inputs!K15,""),"") | M15: =IF(AND(ISNUMBER(Panel_Inputs!S15),ISNUMBER(Panel_Inputs!R15)),IF(Panel_Inputs!R15>0,100*Panel_Inputs!S15/Panel_Inputs!R15,""),"") | N15: =IF(AND(ISNUMBER(Panel_Inputs!E15),ISNUMBER(Panel_Inputs!F15)),IF(Panel_Inputs!F15>0,100*Panel_Inputs!E15/Panel_Inputs!F15,""),"") -> 1.6770619 | O15: =IF(AND(ISNUMBER(Panel_Inputs!G15),ISNUMBER(Panel_Inputs!F15)),IF(Panel_Inputs!F15>0,100*Panel_Inputs!G15/Panel_Inputs!F15,""),"") -> 88.809773 | P15: =IF(ISNUMBER(Panel_Inputs!F15),IF(Panel_Inputs!F15>0,LN(Panel_Inputs!F15),""),"") -> 14.38814 | Q15: =IF(AND(ISNUMBER(Panel_Inputs!F15),ISNUMBER(Panel_Inputs!G15),ISNUMBER(Panel_Inputs!H15)),Panel_Inputs!F15-Panel_Inputs!G15-Panel_Inputs!H15,"") -> 0 | R15: =IF(AND(ISNUMBER(Panel_Inputs!K15),ISNUMBER(Panel_Inputs!L15),ISNUMBER(Panel_Inputs!M15)),Panel_Inputs!K15-Panel_Inputs!L15-Panel_Inputs!M15,"") -> 0 | S15: =IF(AND(ISNUMBER(Panel_Inputs!V15),Panel_Inputs!W15=1),Panel_Inputs!V15,"") | T15: =IF(AND(ISNUMBER(Panel_Inputs!T15),ISNUMBER(Panel_Inputs!U15)),Panel_Inputs!T15-Panel_Inputs!U15,"")
... A121: =Panel_Inputs!A121 -> Zenith | B121: =Panel_Inputs!B121 -> 2022 | C121: =IF(AND(ISNUMBER(Panel_Inputs!F121),ISNUMBER(Panel_Inputs!J121)),IF(AND(Panel_Inputs!F121>0,Panel_Inputs!J121>0),(Panel_Inputs!F121+Panel_Inputs!J121)/2,""),"") -> 9221485 | D121: =IF(AND(ISNUMBER(Panel_Inputs!E121),ISNUMBER(C121)),IF(C121>0,100*Panel_Inputs!E121/C121,""),"") -> 2.5439829 | E121: =IF(AND(ISNUMBER(Panel_Inputs!H121),ISNUMBER(Panel_Inputs!F121)),IF(Panel_Inputs!F121>0,100*Panel_Inputs!H121/Panel_Inputs!F121,""),"") -> 11.306247 | F121: =IF(AND(ISNUMBER(Panel_Inputs!I121),ISNUMBER(C121)),IF(C121>0,100*Panel_Inputs!I121/C121,""),"") -> 13.878003 | G121: =IF(AND(ISNUMBER(Panel_Inputs!L121),ISNUMBER(Panel_Inputs!K121)),IF(Panel_Inputs!K121>0,100*Panel_Inputs!L121/Panel_Inputs!K121,""),"") -> 2.6864871 | H121: =IF(AND(ISNUMBER(Panel_Inputs!P121),ISNUMBER(Panel_Inputs!Q121)),IF(Panel_Inputs!Q121>0,100*Panel_Inputs!P121/Panel_Inputs!Q121,""),"") -> 18.996445 | I121: =IF(AND(ISNUMBER(Panel_Inputs!N121),ISNUMBER(C121)),IF(C121>0,100*Panel_Inputs!N121/C121,""),"") -> 0.6712151 | J121: =IF(AND(ISNUMBER(Panel_Inputs!L121),ISNUMBER(Panel_Inputs!O121)),IF(Panel_Inputs!O121>0,100*Panel_Inputs!L121/Panel_Inputs!O121,""),"") | K121: =IF(AND(ISNUMBER(Panel_Inputs!O121),ISNUMBER(Panel_Inputs!K121)),IF(Panel_Inputs!K121>0,100*Panel_Inputs!O121/Panel_Inputs!K121,""),"") | L121: =IF(AND(ISNUMBER(Panel_Inputs!R121),ISNUMBER(Panel_Inputs!K121)),IF(Panel_Inputs!K121>0,100*Panel_Inputs!R121/Panel_Inputs!K121,""),"") | M121: =IF(AND(ISNUMBER(Panel_Inputs!S121),ISNUMBER(Panel_Inputs!R121)),IF(Panel_Inputs!R121>0,100*Panel_Inputs!S121/Panel_Inputs!R121,""),"") | N121: =IF(AND(ISNUMBER(Panel_Inputs!E121),ISNUMBER(Panel_Inputs!F121)),IF(Panel_Inputs!F121>0,100*Panel_Inputs!E121/Panel_Inputs!F121,""),"") -> 2.2192805 | O121: =IF(AND(ISNUMBER(Panel_Inputs!G121),ISNUMBER(Panel_Inputs!F121)),IF(Panel_Inputs!F121>0,100*Panel_Inputs!G121/Panel_Inputs!F121,""),"") -> 88.693753 | P121: =IF(ISNUMBER(Panel_Inputs!F121),IF(Panel_Inputs!F121>0,LN(Panel_Inputs!F121),""),"") -> 16.173594 | Q121: =IF(AND(ISNUMBER(Panel_Inputs!F121),ISNUMBER(Panel_Inputs!G121),ISNUMBER(Panel_Inputs!H121)),Panel_Inputs!F121-Panel_Inputs!G121-Panel_Inputs!H121,"") -> 0 | R121: =IF(AND(ISNUMBER(Panel_Inputs!K121),ISNUMBER(Panel_Inputs!L121),ISNUMBER(Panel_Inputs!M121)),Panel_Inputs!K121-Panel_Inputs!L121-Panel_Inputs!M121,"") -> 0 | S121: =IF(AND(ISNUMBER(Panel_Inputs!V121),Panel_Inputs!W121=1),Panel_Inputs!V121,"") | T121: =IF(AND(ISNUMBER(Panel_Inputs!T121),ISNUMBER(Panel_Inputs!U121)),Panel_Inputs!T121-Panel_Inputs!U121,"")

Sheet Formula_Check
A1: Python value (from verified_panel.csv) and difference against the workbook formula.
A3: bank | B3: year | C3: average_assets_py | D3: roa_py | E3: eqta_py | F3: ocf_ratio_py | G3: allr_py | H3: car_computed_py | I3: impairment_assets_py | J3: broad_coverage_py | K3: npl_calc_py | L3: stage3_ratio_py | M3: stage3_coverage_py | N3: roa_closing_py | O3: leverage_py | P3: ln_assets_py | Q3: balance_residual_py | R3: loan_residual_py | S3: liquidity_used_py | T3: average_assets_diff | U3: roa_diff | V3: eqta_diff | W3: ocf_ratio_diff | X3: allr_diff | Y3: car_computed_diff | Z3: impairment_assets_diff | AA3: broad_coverage_diff | AB3: npl_calc_diff | AC3: stage3_ratio_diff | AD3: stage3_coverage_diff | AE3: roa_closing_diff | AF3: leverage_diff | AG3: ln_assets_diff | AH3: balance_residual_diff | AI3: loan_residual_diff | AJ3: liquidity_used_diff
A4: Access | B4: 2013 | E4: 14.387821 | N4: 1.5381689 | O4: 85.612179 | P4: 14.348544 | Q4: 1.4551915e-10 | T4: =IF(AND(ISNUMBER(Calculated_Ratios!C4),ISNUMBER(C4)),Calculated_Ratios!C4-C4,IF(AND(Calculated_Ratios!C4="",ISBLANK(C4)),0,"MISMATCH")) -> 0 | U4: =IF(AND(ISNUMBER(Calculated_Ratios!D4),ISNUMBER(D4)),Calculated_Ratios!D4-D4,IF(AND(Calculated_Ratios!D4="",ISBLANK(D4)),0,"MISMATCH")) -> 0 | V4: =IF(AND(ISNUMBER(Calculated_Ratios!E4),ISNUMBER(E4)),Calculated_Ratios!E4-E4,IF(AND(Calculated_Ratios!E4="",ISBLANK(E4)),0,"MISMATCH")) -> 0 | W4: =IF(AND(ISNUMBER(Calculated_Ratios!F4),ISNUMBER(F4)),Calculated_Ratios!F4-F4,IF(AND(Calculated_Ratios!F4="",ISBLANK(F4)),0,"MISMATCH")) -> 0 | X4: =IF(AND(ISNUMBER(Calculated_Ratios!G4),ISNUMBER(G4)),Calculated_Ratios!G4-G4,IF(AND(Calculated_Ratios!G4="",ISBLANK(G4)),0,"MISMATCH")) -> 0 | Y4: =IF(AND(ISNUMBER(Calculated_Ratios!H4),ISNUMBER(H4)),Calculated_Ratios!H4-H4,IF(AND(Calculated_Ratios!H4="",ISBLANK(H4)),0,"MISMATCH")) -> 0 | Z4: =IF(AND(ISNUMBER(Calculated_Ratios!I4),ISNUMBER(I4)),Calculated_Ratios!I4-I4,IF(AND(Calculated_Ratios!I4="",ISBLANK(I4)),0,"MISMATCH")) -> 0 | AA4: =IF(AND(ISNUMBER(Calculated_Ratios!J4),ISNUMBER(J4)),Calculated_Ratios!J4-J4,IF(AND(Calculated_Ratios!J4="",ISBLANK(J4)),0,"MISMATCH")) -> 0 | ... AJ4: =IF(AND(ISNUMBER(Calculated_Ratios!S4),ISNUMBER(S4)),Calculated_Ratios!S4-S4,IF(AND(Calculated_Ratios!S4="",ISBLANK(S4)),0,"MISMATCH")) -> 0
A5: Access | B5: 2014 | C5: 1843024.9 | D5: 2.1671507 | E5: 13.832589 | I5: 0.57564606 | N5: 2.015238 | O5: 86.167411 | P5: 14.499595 | Q5: 0.0010000001 | T5: =IF(AND(ISNUMBER(Calculated_Ratios!C5),ISNUMBER(C5)),Calculated_Ratios!C5-C5,IF(AND(Calculated_Ratios!C5="",ISBLANK(C5)),0,"MISMATCH")) -> 0 | U5: =IF(AND(ISNUMBER(Calculated_Ratios!D5),ISNUMBER(D5)),Calculated_Ratios!D5-D5,IF(AND(Calculated_Ratios!D5="",ISBLANK(D5)),0,"MISMATCH")) -> 0 | V5: =IF(AND(ISNUMBER(Calculated_Ratios!E5),ISNUMBER(E5)),Calculated_Ratios!E5-E5,IF(AND(Calculated_Ratios!E5="",ISBLANK(E5)),0,"MISMATCH")) -> 0 | W5: =IF(AND(ISNUMBER(Calculated_Ratios!F5),ISNUMBER(F5)),Calculated_Ratios!F5-F5,IF(AND(Calculated_Ratios!F5="",ISBLANK(F5)),0,"MISMATCH")) -> 0 | X5: =IF(AND(ISNUMBER(Calculated_Ratios!G5),ISNUMBER(G5)),Calculated_Ratios!G5-G5,IF(AND(Calculated_Ratios!G5="",ISBLANK(G5)),0,"MISMATCH")) -> 0 | Y5: =IF(AND(ISNUMBER(Calculated_Ratios!H5),ISNUMBER(H5)),Calculated_Ratios!H5-H5,IF(AND(Calculated_Ratios!H5="",ISBLANK(H5)),0,"MISMATCH")) -> 0 | Z5: =IF(AND(ISNUMBER(Calculated_Ratios!I5),ISNUMBER(I5)),Calculated_Ratios!I5-I5,IF(AND(Calculated_Ratios!I5="",ISBLANK(I5)),0,"MISMATCH")) -> 0 | AA5: =IF(AND(ISNUMBER(Calculated_Ratios!J5),ISNUMBER(J5)),Calculated_Ratios!J5-J5,IF(AND(Calculated_Ratios!J5="",ISBLANK(J5)),0,"MISMATCH")) -> 0 | ... AJ5: =IF(AND(ISNUMBER(Calculated_Ratios!S5),ISNUMBER(S5)),Calculated_Ratios!S5-S5,IF(AND(Calculated_Ratios!S5="",ISBLANK(S5)),0,"MISMATCH")) -> 0
A6: Access | B6: 2015 | C6: 2196949.9 | D6: 2.682116 | E6: 14.943502 | F6: -8.2499202 | G6: 2.1183867 | H6: 18.039786 | I6: 0.60482094 | N6: 2.4430395 | O6: 85.056498 | P6: 14.695944 | Q6: 3.4924597e-10 | R6: 0 | T6: =IF(AND(ISNUMBER(Calculated_Ratios!C6),ISNUMBER(C6)),Calculated_Ratios!C6-C6,IF(AND(Calculated_Ratios!C6="",ISBLANK(C6)),0,"MISMATCH")) -> 0 | U6: =IF(AND(ISNUMBER(Calculated_Ratios!D6),ISNUMBER(D6)),Calculated_Ratios!D6-D6,IF(AND(Calculated_Ratios!D6="",ISBLANK(D6)),0,"MISMATCH")) -> 0 | V6: =IF(AND(ISNUMBER(Calculated_Ratios!E6),ISNUMBER(E6)),Calculated_Ratios!E6-E6,IF(AND(Calculated_Ratios!E6="",ISBLANK(E6)),0,"MISMATCH")) -> 0 | W6: =IF(AND(ISNUMBER(Calculated_Ratios!F6),ISNUMBER(F6)),Calculated_Ratios!F6-F6,IF(AND(Calculated_Ratios!F6="",ISBLANK(F6)),0,"MISMATCH")) -> 0 | X6: =IF(AND(ISNUMBER(Calculated_Ratios!G6),ISNUMBER(G6)),Calculated_Ratios!G6-G6,IF(AND(Calculated_Ratios!G6="",ISBLANK(G6)),0,"MISMATCH")) -> 0 | Y6: =IF(AND(ISNUMBER(Calculated_Ratios!H6),ISNUMBER(H6)),Calculated_Ratios!H6-H6,IF(AND(Calculated_Ratios!H6="",ISBLANK(H6)),0,"MISMATCH")) -> 0 | Z6: =IF(AND(ISNUMBER(Calculated_Ratios!I6),ISNUMBER(I6)),Calculated_Ratios!I6-I6,IF(AND(Calculated_Ratios!I6="",ISBLANK(I6)),0,"MISMATCH")) -> 0 | AA6: =IF(AND(ISNUMBER(Calculated_Ratios!J6),ISNUMBER(J6)),Calculated_Ratios!J6-J6,IF(AND(Calculated_Ratios!J6="",ISBLANK(J6)),0,"MISMATCH")) -> 0 | ... AJ6: =IF(AND(ISNUMBER(Calculated_Ratios!S6),ISNUMBER(S6)),Calculated_Ratios!S6-S6,IF(AND(Calculated_Ratios!S6="",ISBLANK(S6)),0,"MISMATCH")) -> 0
A7: Access | B7: 2016 | C7: 2753452.3 | D7: 2.325304 | E7: 13.624685 | F7: -4.5083614 | G7: 1.8632945 | H7: 19.554571 | I7: 0.64069122 | N7: 2.0687222 | O7: 86.375315 | P7: 14.945286 | Q7: 1.1641532e-10 | R7: 0 | T7: =IF(AND(ISNUMBER(Calculated_Ratios!C7),ISNUMBER(C7)),Calculated_Ratios!C7-C7,IF(AND(Calculated_Ratios!C7="",ISBLANK(C7)),0,"MISMATCH")) -> 0 | U7: =IF(AND(ISNUMBER(Calculated_Ratios!D7),ISNUMBER(D7)),Calculated_Ratios!D7-D7,IF(AND(Calculated_Ratios!D7="",ISBLANK(D7)),0,"MISMATCH")) -> 0 | V7: =IF(AND(ISNUMBER(Calculated_Ratios!E7),ISNUMBER(E7)),Calculated_Ratios!E7-E7,IF(AND(Calculated_Ratios!E7="",ISBLANK(E7)),0,"MISMATCH")) -> 0 | W7: =IF(AND(ISNUMBER(Calculated_Ratios!F7),ISNUMBER(F7)),Calculated_Ratios!F7-F7,IF(AND(Calculated_Ratios!F7="",ISBLANK(F7)),0,"MISMATCH")) -> 0 | X7: =IF(AND(ISNUMBER(Calculated_Ratios!G7),ISNUMBER(G7)),Calculated_Ratios!G7-G7,IF(AND(Calculated_Ratios!G7="",ISBLANK(G7)),0,"MISMATCH")) -> 0 | Y7: =IF(AND(ISNUMBER(Calculated_Ratios!H7),ISNUMBER(H7)),Calculated_Ratios!H7-H7,IF(AND(Calculated_Ratios!H7="",ISBLANK(H7)),0,"MISMATCH")) -> 0 | Z7: =IF(AND(ISNUMBER(Calculated_Ratios!I7),ISNUMBER(I7)),Calculated_Ratios!I7-I7,IF(AND(Calculated_Ratios!I7="",ISBLANK(I7)),0,"MISMATCH")) -> 0 | AA7: =IF(AND(ISNUMBER(Calculated_Ratios!J7),ISNUMBER(J7)),Calculated_Ratios!J7-J7,IF(AND(Calculated_Ratios!J7="",ISBLANK(J7)),0,"MISMATCH")) -> 0 | ... AJ7: =IF(AND(ISNUMBER(Calculated_Ratios!S7),ISNUMBER(S7)),Calculated_Ratios!S7-S7,IF(AND(Calculated_Ratios!S7="",ISBLANK(S7)),0,"MISMATCH")) -> 0
A8: Access | B8: 2017 | C8: 3297322.2 | D8: 1.6146078 | E8: 13.415243 | F8: 3.1650131 | G8: 3.0800099 | H8: 18.175202 | I8: 0.88404611 | N8: 1.5212466 | O8: 86.584757 | P8: 15.068183 | Q8: -4.0745363e-10 | R8: -0.0010000002 | T8: =IF(AND(ISNUMBER(Calculated_Ratios!C8),ISNUMBER(C8)),Calculated_Ratios!C8-C8,IF(AND(Calculated_Ratios!C8="",ISBLANK(C8)),0,"MISMATCH")) -> 0 | U8: =IF(AND(ISNUMBER(Calculated_Ratios!D8),ISNUMBER(D8)),Calculated_Ratios!D8-D8,IF(AND(Calculated_Ratios!D8="",ISBLANK(D8)),0,"MISMATCH")) -> 0 | V8: =IF(AND(ISNUMBER(Calculated_Ratios!E8),ISNUMBER(E8)),Calculated_Ratios!E8-E8,IF(AND(Calculated_Ratios!E8="",ISBLANK(E8)),0,"MISMATCH")) -> 0 | W8: =IF(AND(ISNUMBER(Calculated_Ratios!F8),ISNUMBER(F8)),Calculated_Ratios!F8-F8,IF(AND(Calculated_Ratios!F8="",ISBLANK(F8)),0,"MISMATCH")) -> 0 | X8: =IF(AND(ISNUMBER(Calculated_Ratios!G8),ISNUMBER(G8)),Calculated_Ratios!G8-G8,IF(AND(Calculated_Ratios!G8="",ISBLANK(G8)),0,"MISMATCH")) -> 0 | Y8: =IF(AND(ISNUMBER(Calculated_Ratios!H8),ISNUMBER(H8)),Calculated_Ratios!H8-H8,IF(AND(Calculated_Ratios!H8="",ISBLANK(H8)),0,"MISMATCH")) -> 0 | Z8: =IF(AND(ISNUMBER(Calculated_Ratios!I8),ISNUMBER(I8)),Calculated_Ratios!I8-I8,IF(AND(Calculated_Ratios!I8="",ISBLANK(I8)),0,"MISMATCH")) -> 0 | AA8: =IF(AND(ISNUMBER(Calculated_Ratios!J8),ISNUMBER(J8)),Calculated_Ratios!J8-J8,IF(AND(Calculated_Ratios!J8="",ISBLANK(J8)),0,"MISMATCH")) -> 0 | ... AJ8: =IF(AND(ISNUMBER(Calculated_Ratios!S8),ISNUMBER(S8)),Calculated_Ratios!S8-S8,IF(AND(Calculated_Ratios!S8="",ISBLANK(S8)),0,"MISMATCH")) -> 0
A9: Access | B9: 2018 | E9: 11.108544 | N9: 1.8546918 | O9: 88.891456 | P9: 15.193802 | Q9: 2.3283064e-10 | T9: =IF(AND(ISNUMBER(Calculated_Ratios!C9),ISNUMBER(C9)),Calculated_Ratios!C9-C9,IF(AND(Calculated_Ratios!C9="",ISBLANK(C9)),0,"MISMATCH")) -> 0 | U9: =IF(AND(ISNUMBER(Calculated_Ratios!D9),ISNUMBER(D9)),Calculated_Ratios!D9-D9,IF(AND(Calculated_Ratios!D9="",ISBLANK(D9)),0,"MISMATCH")) -> 0 | V9: =IF(AND(ISNUMBER(Calculated_Ratios!E9),ISNUMBER(E9)),Calculated_Ratios!E9-E9,IF(AND(Calculated_Ratios!E9="",ISBLANK(E9)),0,"MISMATCH")) -> 0 | W9: =IF(AND(ISNUMBER(Calculated_Ratios!F9),ISNUMBER(F9)),Calculated_Ratios!F9-F9,IF(AND(Calculated_Ratios!F9="",ISBLANK(F9)),0,"MISMATCH")) -> 0 | X9: =IF(AND(ISNUMBER(Calculated_Ratios!G9),ISNUMBER(G9)),Calculated_Ratios!G9-G9,IF(AND(Calculated_Ratios!G9="",ISBLANK(G9)),0,"MISMATCH")) -> 0 | Y9: =IF(AND(ISNUMBER(Calculated_Ratios!H9),ISNUMBER(H9)),Calculated_Ratios!H9-H9,IF(AND(Calculated_Ratios!H9="",ISBLANK(H9)),0,"MISMATCH")) -> 0 | Z9: =IF(AND(ISNUMBER(Calculated_Ratios!I9),ISNUMBER(I9)),Calculated_Ratios!I9-I9,IF(AND(Calculated_Ratios!I9="",ISBLANK(I9)),0,"MISMATCH")) -> 0 | AA9: =IF(AND(ISNUMBER(Calculated_Ratios!J9),ISNUMBER(J9)),Calculated_Ratios!J9-J9,IF(AND(Calculated_Ratios!J9="",ISBLANK(J9)),0,"MISMATCH")) -> 0 | ... AJ9: =IF(AND(ISNUMBER(Calculated_Ratios!S9),ISNUMBER(S9)),Calculated_Ratios!S9-S9,IF(AND(Calculated_Ratios!S9="",ISBLANK(S9)),0,"MISMATCH")) -> 0
A10: Access | B10: 2019 | C10: 5139577.9 | D10: 1.4314221 | E10: 8.6030352 | F10: 21.296948 | G10: 6.797786 | I10: 0.40967331 | N10: 1.1657197 | O10: 91.396965 | P10: 15.657811 | Q10: -3.4924597e-10 | R10: -0.0010000002 | T10: =IF(AND(ISNUMBER(Calculated_Ratios!C10),ISNUMBER(C10)),Calculated_Ratios!C10-C10,IF(AND(Calculated_Ratios!C10="",ISBLANK(C10)),0,"MISMATCH")) -> 0 | U10: =IF(AND(ISNUMBER(Calculated_Ratios!D10),ISNUMBER(D10)),Calculated_Ratios!D10-D10,IF(AND(Calculated_Ratios!D10="",ISBLANK(D10)),0,"MISMATCH")) -> 0 | V10: =IF(AND(ISNUMBER(Calculated_Ratios!E10),ISNUMBER(E10)),Calculated_Ratios!E10-E10,IF(AND(Calculated_Ratios!E10="",ISBLANK(E10)),0,"MISMATCH")) -> 0 | W10: =IF(AND(ISNUMBER(Calculated_Ratios!F10),ISNUMBER(F10)),Calculated_Ratios!F10-F10,IF(AND(Calculated_Ratios!F10="",ISBLANK(F10)),0,"MISMATCH")) -> 0 | X10: =IF(AND(ISNUMBER(Calculated_Ratios!G10),ISNUMBER(G10)),Calculated_Ratios!G10-G10,IF(AND(Calculated_Ratios!G10="",ISBLANK(G10)),0,"MISMATCH")) -> 0 | Y10: =IF(AND(ISNUMBER(Calculated_Ratios!H10),ISNUMBER(H10)),Calculated_Ratios!H10-H10,IF(AND(Calculated_Ratios!H10="",ISBLANK(H10)),0,"MISMATCH")) -> 0 | Z10: =IF(AND(ISNUMBER(Calculated_Ratios!I10),ISNUMBER(I10)),Calculated_Ratios!I10-I10,IF(AND(Calculated_Ratios!I10="",ISBLANK(I10)),0,"MISMATCH")) -> 0 | AA10: =IF(AND(ISNUMBER(Calculated_Ratios!J10),ISNUMBER(J10)),Calculated_Ratios!J10-J10,IF(AND(Calculated_Ratios!J10="",ISBLANK(J10)),0,"MISMATCH")) -> 0 | ... AJ10: =IF(AND(ISNUMBER(Calculated_Ratios!S10),ISNUMBER(S10)),Calculated_Ratios!S10-S10,IF(AND(Calculated_Ratios!S10="",ISBLANK(S10)),0,"MISMATCH")) -> 0
A11: Access | B11: 2020 | C11: 6966284 | D11: 1.148953 | E11: 8.5757036 | F11: -0.93891214 | G11: 4.051935 | H11: 15.87392 | I11: 0.56917835 | N11: 1.0496989 | O11: 91.424296 | P11: 15.84694 | Q11: 3.4924597e-10 | R11: 0 | T11: =IF(AND(ISNUMBER(Calculated_Ratios!C11),ISNUMBER(C11)),Calculated_Ratios!C11-C11,IF(AND(Calculated_Ratios!C11="",ISBLANK(C11)),0,"MISMATCH")) -> 0 | U11: =IF(AND(ISNUMBER(Calculated_Ratios!D11),ISNUMBER(D11)),Calculated_Ratios!D11-D11,IF(AND(Calculated_Ratios!D11="",ISBLANK(D11)),0,"MISMATCH")) -> 0 | V11: =IF(AND(ISNUMBER(Calculated_Ratios!E11),ISNUMBER(E11)),Calculated_Ratios!E11-E11,IF(AND(Calculated_Ratios!E11="",ISBLANK(E11)),0,"MISMATCH")) -> 0 | W11: =IF(AND(ISNUMBER(Calculated_Ratios!F11),ISNUMBER(F11)),Calculated_Ratios!F11-F11,IF(AND(Calculated_Ratios!F11="",ISBLANK(F11)),0,"MISMATCH")) -> 0 | X11: =IF(AND(ISNUMBER(Calculated_Ratios!G11),ISNUMBER(G11)),Calculated_Ratios!G11-G11,IF(AND(Calculated_Ratios!G11="",ISBLANK(G11)),0,"MISMATCH")) -> 0 | Y11: =IF(AND(ISNUMBER(Calculated_Ratios!H11),ISNUMBER(H11)),Calculated_Ratios!H11-H11,IF(AND(Calculated_Ratios!H11="",ISBLANK(H11)),0,"MISMATCH")) -> 0 | Z11: =IF(AND(ISNUMBER(Calculated_Ratios!I11),ISNUMBER(I11)),Calculated_Ratios!I11-I11,IF(AND(Calculated_Ratios!I11="",ISBLANK(I11)),0,"MISMATCH")) -> 0 | AA11: =IF(AND(ISNUMBER(Calculated_Ratios!J11),ISNUMBER(J11)),Calculated_Ratios!J11-J11,IF(AND(Calculated_Ratios!J11="",ISBLANK(J11)),0,"MISMATCH")) -> 0 | ... AJ11: =IF(AND(ISNUMBER(Calculated_Ratios!S11),ISNUMBER(S11)),Calculated_Ratios!S11-S11,IF(AND(Calculated_Ratios!S11="",ISBLANK(S11)),0,"MISMATCH")) -> 0
A12: Access | B12: 2021 | C12: 8642870.1 | D12: 1.2880731 | E12: 9.0205125 | F12: 5.7947742 | G12: 2.6213171 | H12: 20.930667 | I12: 0.62248922 | N12: 1.1523574 | O12: 90.979487 | P12: 16.083583 | Q12: 1.1641532e-10 | R12: -0.0010000002 | T12: =IF(AND(ISNUMBER(Calculated_Ratios!C12),ISNUMBER(C12)),Calculated_Ratios!C12-C12,IF(AND(Calculated_Ratios!C12="",ISBLANK(C12)),0,"MISMATCH")) -> 0 | U12: =IF(AND(ISNUMBER(Calculated_Ratios!D12),ISNUMBER(D12)),Calculated_Ratios!D12-D12,IF(AND(Calculated_Ratios!D12="",ISBLANK(D12)),0,"MISMATCH")) -> 0 | V12: =IF(AND(ISNUMBER(Calculated_Ratios!E12),ISNUMBER(E12)),Calculated_Ratios!E12-E12,IF(AND(Calculated_Ratios!E12="",ISBLANK(E12)),0,"MISMATCH")) -> 0 | W12: =IF(AND(ISNUMBER(Calculated_Ratios!F12),ISNUMBER(F12)),Calculated_Ratios!F12-F12,IF(AND(Calculated_Ratios!F12="",ISBLANK(F12)),0,"MISMATCH")) -> 0 | X12: =IF(AND(ISNUMBER(Calculated_Ratios!G12),ISNUMBER(G12)),Calculated_Ratios!G12-G12,IF(AND(Calculated_Ratios!G12="",ISBLANK(G12)),0,"MISMATCH")) -> 0 | Y12: =IF(AND(ISNUMBER(Calculated_Ratios!H12),ISNUMBER(H12)),Calculated_Ratios!H12-H12,IF(AND(Calculated_Ratios!H12="",ISBLANK(H12)),0,"MISMATCH")) -> 0 | Z12: =IF(AND(ISNUMBER(Calculated_Ratios!I12),ISNUMBER(I12)),Calculated_Ratios!I12-I12,IF(AND(Calculated_Ratios!I12="",ISBLANK(I12)),0,"MISMATCH")) -> 0 | AA12: =IF(AND(ISNUMBER(Calculated_Ratios!J12),ISNUMBER(J12)),Calculated_Ratios!J12-J12,IF(AND(Calculated_Ratios!J12="",ISBLANK(J12)),0,"MISMATCH")) -> 0 | ... AJ12: =IF(AND(ISNUMBER(Calculated_Ratios!S12),ISNUMBER(S12)),Calculated_Ratios!S12-S12,IF(AND(Calculated_Ratios!S12="",ISBLANK(S12)),0,"MISMATCH")) -> 0
A13: Access | B13: 2022 | C13: 11098020 | D13: 1.5017092 | E13: 8.5252743 | F13: 6.2941675 | G13: 1.5679567 | H13: 17.845932 | I13: 1.0693889 | N13: 1.3295275 | O13: 91.474726 | P13: 16.344058 | Q13: 0 | R13: 0 | T13: =IF(AND(ISNUMBER(Calculated_Ratios!C13),ISNUMBER(C13)),Calculated_Ratios!C13-C13,IF(AND(Calculated_Ratios!C13="",ISBLANK(C13)),0,"MISMATCH")) -> 0 | U13: =IF(AND(ISNUMBER(Calculated_Ratios!D13),ISNUMBER(D13)),Calculated_Ratios!D13-D13,IF(AND(Calculated_Ratios!D13="",ISBLANK(D13)),0,"MISMATCH")) -> 0 | V13: =IF(AND(ISNUMBER(Calculated_Ratios!E13),ISNUMBER(E13)),Calculated_Ratios!E13-E13,IF(AND(Calculated_Ratios!E13="",ISBLANK(E13)),0,"MISMATCH")) -> 0 | W13: =IF(AND(ISNUMBER(Calculated_Ratios!F13),ISNUMBER(F13)),Calculated_Ratios!F13-F13,IF(AND(Calculated_Ratios!F13="",ISBLANK(F13)),0,"MISMATCH")) -> 0 | X13: =IF(AND(ISNUMBER(Calculated_Ratios!G13),ISNUMBER(G13)),Calculated_Ratios!G13-G13,IF(AND(Calculated_Ratios!G13="",ISBLANK(G13)),0,"MISMATCH")) -> 0 | Y13: =IF(AND(ISNUMBER(Calculated_Ratios!H13),ISNUMBER(H13)),Calculated_Ratios!H13-H13,IF(AND(Calculated_Ratios!H13="",ISBLANK(H13)),0,"MISMATCH")) -> 0 | Z13: =IF(AND(ISNUMBER(Calculated_Ratios!I13),ISNUMBER(I13)),Calculated_Ratios!I13-I13,IF(AND(Calculated_Ratios!I13="",ISBLANK(I13)),0,"MISMATCH")) -> 0 | AA13: =IF(AND(ISNUMBER(Calculated_Ratios!J13),ISNUMBER(J13)),Calculated_Ratios!J13-J13,IF(AND(Calculated_Ratios!J13="",ISBLANK(J13)),0,"MISMATCH")) -> 0 | ... AJ13: =IF(AND(ISNUMBER(Calculated_Ratios!S13),ISNUMBER(S13)),Calculated_Ratios!S13-S13,IF(AND(Calculated_Ratios!S13="",ISBLANK(S13)),0,"MISMATCH")) -> 0
A14: Ecobank Nigeria | B14: 2013 | C14: 1393063 | D14: 0.83686093 | E14: 10.721989 | F14: 0.33063831 | G14: 5.2703828 | H14: 17.385859 | I14: 2.3405977 | N14: 0.79804985 | O14: 89.278011 | P14: 14.194502 | Q14: 0 | R14: 0 | T14: =IF(AND(ISNUMBER(Calculated_Ratios!C14),ISNUMBER(C14)),Calculated_Ratios!C14-C14,IF(AND(Calculated_Ratios!C14="",ISBLANK(C14)),0,"MISMATCH")) -> 0 | U14: =IF(AND(ISNUMBER(Calculated_Ratios!D14),ISNUMBER(D14)),Calculated_Ratios!D14-D14,IF(AND(Calculated_Ratios!D14="",ISBLANK(D14)),0,"MISMATCH")) -> 0 | V14: =IF(AND(ISNUMBER(Calculated_Ratios!E14),ISNUMBER(E14)),Calculated_Ratios!E14-E14,IF(AND(Calculated_Ratios!E14="",ISBLANK(E14)),0,"MISMATCH")) -> 0 | W14: =IF(AND(ISNUMBER(Calculated_Ratios!F14),ISNUMBER(F14)),Calculated_Ratios!F14-F14,IF(AND(Calculated_Ratios!F14="",ISBLANK(F14)),0,"MISMATCH")) -> 0 | X14: =IF(AND(ISNUMBER(Calculated_Ratios!G14),ISNUMBER(G14)),Calculated_Ratios!G14-G14,IF(AND(Calculated_Ratios!G14="",ISBLANK(G14)),0,"MISMATCH")) -> 0 | Y14: =IF(AND(ISNUMBER(Calculated_Ratios!H14),ISNUMBER(H14)),Calculated_Ratios!H14-H14,IF(AND(Calculated_Ratios!H14="",ISBLANK(H14)),0,"MISMATCH")) -> 0 | Z14: =IF(AND(ISNUMBER(Calculated_Ratios!I14),ISNUMBER(I14)),Calculated_Ratios!I14-I14,IF(AND(Calculated_Ratios!I14="",ISBLANK(I14)),0,"MISMATCH")) -> 0 | AA14: =IF(AND(ISNUMBER(Calculated_Ratios!J14),ISNUMBER(J14)),Calculated_Ratios!J14-J14,IF(AND(Calculated_Ratios!J14="",ISBLANK(J14)),0,"MISMATCH")) -> 0 | ... AJ14: =IF(AND(ISNUMBER(Calculated_Ratios!S14),ISNUMBER(S14)),Calculated_Ratios!S14-S14,IF(AND(Calculated_Ratios!S14="",ISBLANK(S14)),0,"MISMATCH")) -> 0
A15: Ecobank Nigeria | B15: 2014 | C15: 1616866.5 | D15: 1.8389273 | E15: 11.190227 | F15: -6.8466382 | G15: 4.1070684 | H15: 16.033592 | I15: 2.0406137 | N15: 1.6770619 | O15: 88.809773 | P15: 14.38814 | Q15: 0 | R15: 0 | T15: =IF(AND(ISNUMBER(Calculated_Ratios!C15),ISNUMBER(C15)),Calculated_Ratios!C15-C15,IF(AND(Calculated_Ratios!C15="",ISBLANK(C15)),0,"MISMATCH")) -> 0 | U15: =IF(AND(ISNUMBER(Calculated_Ratios!D15),ISNUMBER(D15)),Calculated_Ratios!D15-D15,IF(AND(Calculated_Ratios!D15="",ISBLANK(D15)),0,"MISMATCH")) -> 0 | V15: =IF(AND(ISNUMBER(Calculated_Ratios!E15),ISNUMBER(E15)),Calculated_Ratios!E15-E15,IF(AND(Calculated_Ratios!E15="",ISBLANK(E15)),0,"MISMATCH")) -> 0 | W15: =IF(AND(ISNUMBER(Calculated_Ratios!F15),ISNUMBER(F15)),Calculated_Ratios!F15-F15,IF(AND(Calculated_Ratios!F15="",ISBLANK(F15)),0,"MISMATCH")) -> 0 | X15: =IF(AND(ISNUMBER(Calculated_Ratios!G15),ISNUMBER(G15)),Calculated_Ratios!G15-G15,IF(AND(Calculated_Ratios!G15="",ISBLANK(G15)),0,"MISMATCH")) -> 0 | Y15: =IF(AND(ISNUMBER(Calculated_Ratios!H15),ISNUMBER(H15)),Calculated_Ratios!H15-H15,IF(AND(Calculated_Ratios!H15="",ISBLANK(H15)),0,"MISMATCH")) -> 0 | Z15: =IF(AND(ISNUMBER(Calculated_Ratios!I15),ISNUMBER(I15)),Calculated_Ratios!I15-I15,IF(AND(Calculated_Ratios!I15="",ISBLANK(I15)),0,"MISMATCH")) -> 0 | AA15: =IF(AND(ISNUMBER(Calculated_Ratios!J15),ISNUMBER(J15)),Calculated_Ratios!J15-J15,IF(AND(Calculated_Ratios!J15="",ISBLANK(J15)),0,"MISMATCH")) -> 0 | ... AJ15: =IF(AND(ISNUMBER(Calculated_Ratios!S15),ISNUMBER(S15)),Calculated_Ratios!S15-S15,IF(AND(Calculated_Ratios!S15="",ISBLANK(S15)),0,"MISMATCH")) -> 0
A16: Ecobank Nigeria | B16: 2015 | C16: 1783635 | D16: 0.63376195 | E16: 12.694695 | F16: 1.3584057 | G16: 7.71739 | H16: 18.72444 | I16: 3.1250788 | N16: 0.62997813 | O16: 87.305305 | P16: 14.400152 | Q16: 0 | R16: 0 | T16: =IF(AND(ISNUMBER(Calculated_Ratios!C16),ISNUMBER(C16)),Calculated_Ratios!C16-C16,IF(AND(Calculated_Ratios!C16="",ISBLANK(C16)),0,"MISMATCH")) -> 0 | U16: =IF(AND(ISNUMBER(Calculated_Ratios!D16),ISNUMBER(D16)),Calculated_Ratios!D16-D16,IF(AND(Calculated_Ratios!D16="",ISBLANK(D16)),0,"MISMATCH")) -> 0 | V16: =IF(AND(ISNUMBER(Calculated_Ratios!E16),ISNUMBER(E16)),Calculated_Ratios!E16-E16,IF(AND(Calculated_Ratios!E16="",ISBLANK(E16)),0,"MISMATCH")) -> 0 | W16: =IF(AND(ISNUMBER(Calculated_Ratios!F16),ISNUMBER(F16)),Calculated_Ratios!F16-F16,IF(AND(Calculated_Ratios!F16="",ISBLANK(F16)),0,"MISMATCH")) -> 0 | X16: =IF(AND(ISNUMBER(Calculated_Ratios!G16),ISNUMBER(G16)),Calculated_Ratios!G16-G16,IF(AND(Calculated_Ratios!G16="",ISBLANK(G16)),0,"MISMATCH")) -> 0 | Y16: =IF(AND(ISNUMBER(Calculated_Ratios!H16),ISNUMBER(H16)),Calculated_Ratios!H16-H16,IF(AND(Calculated_Ratios!H16="",ISBLANK(H16)),0,"MISMATCH")) -> 0 | Z16: =IF(AND(ISNUMBER(Calculated_Ratios!I16),ISNUMBER(I16)),Calculated_Ratios!I16-I16,IF(AND(Calculated_Ratios!I16="",ISBLANK(I16)),0,"MISMATCH")) -> 0 | AA16: =IF(AND(ISNUMBER(Calculated_Ratios!J16),ISNUMBER(J16)),Calculated_Ratios!J16-J16,IF(AND(Calculated_Ratios!J16="",ISBLANK(J16)),0,"MISMATCH")) -> 0 | ... AJ16: =IF(AND(ISNUMBER(Calculated_Ratios!S16),ISNUMBER(S16)),Calculated_Ratios!S16-S16,IF(AND(Calculated_Ratios!S16="",ISBLANK(S16)),0,"MISMATCH")) -> 0
A17: Ecobank Nigeria | B17: 2016 | E17: 12.20761 | N17: 0.31960135 | O17: 87.79239 | P17: 14.40801 | Q17: 0 | T17: =IF(AND(ISNUMBER(Calculated_Ratios!C17),ISNUMBER(C17)),Calculated_Ratios!C17-C17,IF(AND(Calculated_Ratios!C17="",ISBLANK(C17)),0,"MISMATCH")) -> 0 | U17: =IF(AND(ISNUMBER(Calculated_Ratios!D17),ISNUMBER(D17)),Calculated_Ratios!D17-D17,IF(AND(Calculated_Ratios!D17="",ISBLANK(D17)),0,"MISMATCH")) -> 0 | V17: =IF(AND(ISNUMBER(Calculated_Ratios!E17),ISNUMBER(E17)),Calculated_Ratios!E17-E17,IF(AND(Calculated_Ratios!E17="",ISBLANK(E17)),0,"MISMATCH")) -> 0 | W17: =IF(AND(ISNUMBER(Calculated_Ratios!F17),ISNUMBER(F17)),Calculated_Ratios!F17-F17,IF(AND(Calculated_Ratios!F17="",ISBLANK(F17)),0,"MISMATCH")) -> 0 | X17: =IF(AND(ISNUMBER(Calculated_Ratios!G17),ISNUMBER(G17)),Calculated_Ratios!G17-G17,IF(AND(Calculated_Ratios!G17="",ISBLANK(G17)),0,"MISMATCH")) -> 0 | Y17: =IF(AND(ISNUMBER(Calculated_Ratios!H17),ISNUMBER(H17)),Calculated_Ratios!H17-H17,IF(AND(Calculated_Ratios!H17="",ISBLANK(H17)),0,"MISMATCH")) -> 0 | Z17: =IF(AND(ISNUMBER(Calculated_Ratios!I17),ISNUMBER(I17)),Calculated_Ratios!I17-I17,IF(AND(Calculated_Ratios!I17="",ISBLANK(I17)),0,"MISMATCH")) -> 0 | AA17: =IF(AND(ISNUMBER(Calculated_Ratios!J17),ISNUMBER(J17)),Calculated_Ratios!J17-J17,IF(AND(Calculated_Ratios!J17="",ISBLANK(J17)),0,"MISMATCH")) -> 0 | ... AJ17: =IF(AND(ISNUMBER(Calculated_Ratios!S17),ISNUMBER(S17)),Calculated_Ratios!S17-S17,IF(AND(Calculated_Ratios!S17="",ISBLANK(S17)),0,"MISMATCH")) -> 0
A18: Ecobank Nigeria | B18: 2017 | C18: 1819132 | D18: 1.1106396 | E18: 14.61005 | I18: 3.2928342 | N18: 1.1041879 | O18: 85.38995 | P18: 14.419696 | Q18: 0 | T18: =IF(AND(ISNUMBER(Calculated_Ratios!C18),ISNUMBER(C18)),Calculated_Ratios!C18-C18,IF(AND(Calculated_Ratios!C18="",ISBLANK(C18)),0,"MISMATCH")) -> 0 | U18: =IF(AND(ISNUMBER(Calculated_Ratios!D18),ISNUMBER(D18)),Calculated_Ratios!D18-D18,IF(AND(Calculated_Ratios!D18="",ISBLANK(D18)),0,"MISMATCH")) -> 0 | V18: =IF(AND(ISNUMBER(Calculated_Ratios!E18),ISNUMBER(E18)),Calculated_Ratios!E18-E18,IF(AND(Calculated_Ratios!E18="",ISBLANK(E18)),0,"MISMATCH")) -> 0 | W18: =IF(AND(ISNUMBER(Calculated_Ratios!F18),ISNUMBER(F18)),Calculated_Ratios!F18-F18,IF(AND(Calculated_Ratios!F18="",ISBLANK(F18)),0,"MISMATCH")) -> 0 | X18: =IF(AND(ISNUMBER(Calculated_Ratios!G18),ISNUMBER(G18)),Calculated_Ratios!G18-G18,IF(AND(Calculated_Ratios!G18="",ISBLANK(G18)),0,"MISMATCH")) -> 0 | Y18: =IF(AND(ISNUMBER(Calculated_Ratios!H18),ISNUMBER(H18)),Calculated_Ratios!H18-H18,IF(AND(Calculated_Ratios!H18="",ISBLANK(H18)),0,"MISMATCH")) -> 0 | Z18: =IF(AND(ISNUMBER(Calculated_Ratios!I18),ISNUMBER(I18)),Calculated_Ratios!I18-I18,IF(AND(Calculated_Ratios!I18="",ISBLANK(I18)),0,"MISMATCH")) -> 0 | AA18: =IF(AND(ISNUMBER(Calculated_Ratios!J18),ISNUMBER(J18)),Calculated_Ratios!J18-J18,IF(AND(Calculated_Ratios!J18="",ISBLANK(J18)),0,"MISMATCH")) -> 0 | ... AJ18: =IF(AND(ISNUMBER(Calculated_Ratios!S18),ISNUMBER(S18)),Calculated_Ratios!S18-S18,IF(AND(Calculated_Ratios!S18="",ISBLANK(S18)),0,"MISMATCH")) -> 0
A19: Ecobank Nigeria | B19: 2018 | C19: 1893295.5 | D19: 1.4342716 | E19: 12.647087 | F19: 1.6498217 | G19: 9.0735916 | H19: 14.321978 | I19: 1.4450993 | J19: 66.279051 | K19: 13.689984 | N19: 1.3877036 | O19: 87.352913 | P19: 14.486836 | Q19: 0 | R19: 0 | T19: =IF(AND(ISNUMBER(Calculated_Ratios!C19),ISNUMBER(C19)),Calculated_Ratios!C19-C19,IF(AND(Calculated_Ratios!C19="",ISBLANK(C19)),0,"MISMATCH")) -> 0 | U19: =IF(AND(ISNUMBER(Calculated_Ratios!D19),ISNUMBER(D19)),Calculated_Ratios!D19-D19,IF(AND(Calculated_Ratios!D19="",ISBLANK(D19)),0,"MISMATCH")) -> 0 | V19: =IF(AND(ISNUMBER(Calculated_Ratios!E19),ISNUMBER(E19)),Calculated_Ratios!E19-E19,IF(AND(Calculated_Ratios!E19="",ISBLANK(E19)),0,"MISMATCH")) -> 0 | W19: =IF(AND(ISNUMBER(Calculated_Ratios!F19),ISNUMBER(F19)),Calculated_Ratios!F19-F19,IF(AND(Calculated_Ratios!F19="",ISBLANK(F19)),0,"MISMATCH")) -> 0 | X19: =IF(AND(ISNUMBER(Calculated_Ratios!G19),ISNUMBER(G19)),Calculated_Ratios!G19-G19,IF(AND(Calculated_Ratios!G19="",ISBLANK(G19)),0,"MISMATCH")) -> 0 | Y19: =IF(AND(ISNUMBER(Calculated_Ratios!H19),ISNUMBER(H19)),Calculated_Ratios!H19-H19,IF(AND(Calculated_Ratios!H19="",ISBLANK(H19)),0,"MISMATCH")) -> 0 | Z19: =IF(AND(ISNUMBER(Calculated_Ratios!I19),ISNUMBER(I19)),Calculated_Ratios!I19-I19,IF(AND(Calculated_Ratios!I19="",ISBLANK(I19)),0,"MISMATCH")) -> 0 | AA19: =IF(AND(ISNUMBER(Calculated_Ratios!J19),ISNUMBER(J19)),Calculated_Ratios!J19-J19,IF(AND(Calculated_Ratios!J19="",ISBLANK(J19)),0,"MISMATCH")) -> 0 | ... AJ19: =IF(AND(ISNUMBER(Calculated_Ratios!S19),ISNUMBER(S19)),Calculated_Ratios!S19-S19,IF(AND(Calculated_Ratios!S19="",ISBLANK(S19)),0,"MISMATCH")) -> 0
A20: Ecobank Nigeria | B20: 2019 | C20: 1959464.5 | D20: 0.064099145 | E20: 13.272963 | F20: 2.503337 | G20: 11.113569 | H20: 16.313794 | I20: 0.13799689 | J20: 46.438917 | K20: 23.931586 | N20: 0.06308261 | O20: 86.727037 | P20: 14.504168 | Q20: 0 | R20: 0 | T20: =IF(AND(ISNUMBER(Calculated_Ratios!C20),ISNUMBER(C20)),Calculated_Ratios!C20-C20,IF(AND(Calculated_Ratios!C20="",ISBLANK(C20)),0,"MISMATCH")) -> 0 | U20: =IF(AND(ISNUMBER(Calculated_Ratios!D20),ISNUMBER(D20)),Calculated_Ratios!D20-D20,IF(AND(Calculated_Ratios!D20="",ISBLANK(D20)),0,"MISMATCH")) -> 0 | V20: =IF(AND(ISNUMBER(Calculated_Ratios!E20),ISNUMBER(E20)),Calculated_Ratios!E20-E20,IF(AND(Calculated_Ratios!E20="",ISBLANK(E20)),0,"MISMATCH")) -> 0 | W20: =IF(AND(ISNUMBER(Calculated_Ratios!F20),ISNUMBER(F20)),Calculated_Ratios!F20-F20,IF(AND(Calculated_Ratios!F20="",ISBLANK(F20)),0,"MISMATCH")) -> 0 | X20: =IF(AND(ISNUMBER(Calculated_Ratios!G20),ISNUMBER(G20)),Calculated_Ratios!G20-G20,IF(AND(Calculated_Ratios!G20="",ISBLANK(G20)),0,"MISMATCH")) -> 0 | Y20: =IF(AND(ISNUMBER(Calculated_Ratios!H20),ISNUMBER(H20)),Calculated_Ratios!H20-H20,IF(AND(Calculated_Ratios!H20="",ISBLANK(H20)),0,"MISMATCH")) -> 0 | Z20: =IF(AND(ISNUMBER(Calculated_Ratios!I20),ISNUMBER(I20)),Calculated_Ratios!I20-I20,IF(AND(Calculated_Ratios!I20="",ISBLANK(I20)),0,"MISMATCH")) -> 0 | AA20: =IF(AND(ISNUMBER(Calculated_Ratios!J20),ISNUMBER(J20)),Calculated_Ratios!J20-J20,IF(AND(Calculated_Ratios!J20="",ISBLANK(J20)),0,"MISMATCH")) -> 0 | ... AJ20: =IF(AND(ISNUMBER(Calculated_Ratios!S20),ISNUMBER(S20)),Calculated_Ratios!S20-S20,IF(AND(Calculated_Ratios!S20="",ISBLANK(S20)),0,"MISMATCH")) -> 0
A21: Ecobank Nigeria | B21: 2020 | C21: 2088876 | D21: 0.38714601 | E21: 13.660738 | F21: -0.63531775 | G21: 11.237416 | H21: 21.43908 | I21: 0.43870483 | J21: 56.595708 | K21: 19.855597 | N21: 0.36982465 | O21: 86.339262 | P21: 14.59791 | Q21: 0 | R21: 0 | T21: =IF(AND(ISNUMBER(Calculated_Ratios!C21),ISNUMBER(C21)),Calculated_Ratios!C21-C21,IF(AND(Calculated_Ratios!C21="",ISBLANK(C21)),0,"MISMATCH")) -> 0 | U21: =IF(AND(ISNUMBER(Calculated_Ratios!D21),ISNUMBER(D21)),Calculated_Ratios!D21-D21,IF(AND(Calculated_Ratios!D21="",ISBLANK(D21)),0,"MISMATCH")) -> 0 | V21: =IF(AND(ISNUMBER(Calculated_Ratios!E21),ISNUMBER(E21)),Calculated_Ratios!E21-E21,IF(AND(Calculated_Ratios!E21="",ISBLANK(E21)),0,"MISMATCH")) -> 0 | W21: =IF(AND(ISNUMBER(Calculated_Ratios!F21),ISNUMBER(F21)),Calculated_Ratios!F21-F21,IF(AND(Calculated_Ratios!F21="",ISBLANK(F21)),0,"MISMATCH")) -> 0 | X21: =IF(AND(ISNUMBER(Calculated_Ratios!G21),ISNUMBER(G21)),Calculated_Ratios!G21-G21,IF(AND(Calculated_Ratios!G21="",ISBLANK(G21)),0,"MISMATCH")) -> 0 | Y21: =IF(AND(ISNUMBER(Calculated_Ratios!H21),ISNUMBER(H21)),Calculated_Ratios!H21-H21,IF(AND(Calculated_Ratios!H21="",ISBLANK(H21)),0,"MISMATCH")) -> 0 | Z21: =IF(AND(ISNUMBER(Calculated_Ratios!I21),ISNUMBER(I21)),Calculated_Ratios!I21-I21,IF(AND(Calculated_Ratios!I21="",ISBLANK(I21)),0,"MISMATCH")) -> 0 | AA21: =IF(AND(ISNUMBER(Calculated_Ratios!J21),ISNUMBER(J21)),Calculated_Ratios!J21-J21,IF(AND(Calculated_Ratios!J21="",ISBLANK(J21)),0,"MISMATCH")) -> 0 | ... AJ21: =IF(AND(ISNUMBER(Calculated_Ratios!S21),ISNUMBER(S21)),Calculated_Ratios!S21-S21,IF(AND(Calculated_Ratios!S21="",ISBLANK(S21)),0,"MISMATCH")) -> 0
A22: Ecobank Nigeria | B22: 2021 | C22: 2330895 | D22: 0.41898069 | E22: 11.263358 | F22: -3.7213173 | G22: 8.7526572 | H22: 11.480052 | I22: 0.30207281 | J22: 53.540455 | K22: 16.347745 | N22: 0.39457326 | O22: 88.736642 | P22: 14.721783 | Q22: 0 | R22: 0 | T22: =IF(AND(ISNUMBER(Calculated_Ratios!C22),ISNUMBER(C22)),Calculated_Ratios!C22-C22,IF(AND(Calculated_Ratios!C22="",ISBLANK(C22)),0,"MISMATCH")) -> 0 | U22: =IF(AND(ISNUMBER(Calculated_Ratios!D22),ISNUMBER(D22)),Calculated_Ratios!D22-D22,IF(AND(Calculated_Ratios!D22="",ISBLANK(D22)),0,"MISMATCH")) -> 0 | V22: =IF(AND(ISNUMBER(Calculated_Ratios!E22),ISNUMBER(E22)),Calculated_Ratios!E22-E22,IF(AND(Calculated_Ratios!E22="",ISBLANK(E22)),0,"MISMATCH")) -> 0 | W22: =IF(AND(ISNUMBER(Calculated_Ratios!F22),ISNUMBER(F22)),Calculated_Ratios!F22-F22,IF(AND(Calculated_Ratios!F22="",ISBLANK(F22)),0,"MISMATCH")) -> 0 | X22: =IF(AND(ISNUMBER(Calculated_Ratios!G22),ISNUMBER(G22)),Calculated_Ratios!G22-G22,IF(AND(Calculated_Ratios!G22="",ISBLANK(G22)),0,"MISMATCH")) -> 0 | Y22: =IF(AND(ISNUMBER(Calculated_Ratios!H22),ISNUMBER(H22)),Calculated_Ratios!H22-H22,IF(AND(Calculated_Ratios!H22="",ISBLANK(H22)),0,"MISMATCH")) -> 0 | Z22: =IF(AND(ISNUMBER(Calculated_Ratios!I22),ISNUMBER(I22)),Calculated_Ratios!I22-I22,IF(AND(Calculated_Ratios!I22="",ISBLANK(I22)),0,"MISMATCH")) -> 0 | AA22: =IF(AND(ISNUMBER(Calculated_Ratios!J22),ISNUMBER(J22)),Calculated_Ratios!J22-J22,IF(AND(Calculated_Ratios!J22="",ISBLANK(J22)),0,"MISMATCH")) -> 0 | ... AJ22: =IF(AND(ISNUMBER(Calculated_Ratios!S22),ISNUMBER(S22)),Calculated_Ratios!S22-S22,IF(AND(Calculated_Ratios!S22="",ISBLANK(S22)),0,"MISMATCH")) -> 0
A23: Ecobank Nigeria | B23: 2022 | C23: 2696384 | D23: 0.38555339 | E23: 10.097478 | F23: -2.8053126 | G23: 5.2826752 | H23: 13.272064 | I23: 0.45902216 | J23: 76.358867 | K23: 6.918221 | N23: 0.35630939 | O23: 89.902522 | P23: 14.886302 | Q23: 0 | R23: 0 | T23: =IF(AND(ISNUMBER(Calculated_Ratios!C23),ISNUMBER(C23)),Calculated_Ratios!C23-C23,IF(AND(Calculated_Ratios!C23="",ISBLANK(C23)),0,"MISMATCH")) -> 0 | U23: =IF(AND(ISNUMBER(Calculated_Ratios!D23),ISNUMBER(D23)),Calculated_Ratios!D23-D23,IF(AND(Calculated_Ratios!D23="",ISBLANK(D23)),0,"MISMATCH")) -> 0 | V23: =IF(AND(ISNUMBER(Calculated_Ratios!E23),ISNUMBER(E23)),Calculated_Ratios!E23-E23,IF(AND(Calculated_Ratios!E23="",ISBLANK(E23)),0,"MISMATCH")) -> 0 | W23: =IF(AND(ISNUMBER(Calculated_Ratios!F23),ISNUMBER(F23)),Calculated_Ratios!F23-F23,IF(AND(Calculated_Ratios!F23="",ISBLANK(F23)),0,"MISMATCH")) -> 0 | X23: =IF(AND(ISNUMBER(Calculated_Ratios!G23),ISNUMBER(G23)),Calculated_Ratios!G23-G23,IF(AND(Calculated_Ratios!G23="",ISBLANK(G23)),0,"MISMATCH")) -> 0 | Y23: =IF(AND(ISNUMBER(Calculated_Ratios!H23),ISNUMBER(H23)),Calculated_Ratios!H23-H23,IF(AND(Calculated_Ratios!H23="",ISBLANK(H23)),0,"MISMATCH")) -> 0 | Z23: =IF(AND(ISNUMBER(Calculated_Ratios!I23),ISNUMBER(I23)),Calculated_Ratios!I23-I23,IF(AND(Calculated_Ratios!I23="",ISBLANK(I23)),0,"MISMATCH")) -> 0 | AA23: =IF(AND(ISNUMBER(Calculated_Ratios!J23),ISNUMBER(J23)),Calculated_Ratios!J23-J23,IF(AND(Calculated_Ratios!J23="",ISBLANK(J23)),0,"MISMATCH")) -> 0 | ... AJ23: =IF(AND(ISNUMBER(Calculated_Ratios!S23),ISNUMBER(S23)),Calculated_Ratios!S23-S23,IF(AND(Calculated_Ratios!S23="",ISBLANK(S23)),0,"MISMATCH")) -> 0
A24: Fidelity | B24: 2013 | C24: 997788.5 | D24: 0.77381128 | E24: 15.117687 | F24: 1.5081352 | G24: 3.74405 | I24: 0.76469111 | N24: 0.71410272 | O24: 84.882313 | P24: 13.893598 | Q24: 0 | T24: =IF(AND(ISNUMBER(Calculated_Ratios!C24),ISNUMBER(C24)),Calculated_Ratios!C24-C24,IF(AND(Calculated_Ratios!C24="",ISBLANK(C24)),0,"MISMATCH")) -> 0 | U24: =IF(AND(ISNUMBER(Calculated_Ratios!D24),ISNUMBER(D24)),Calculated_Ratios!D24-D24,IF(AND(Calculated_Ratios!D24="",ISBLANK(D24)),0,"MISMATCH")) -> 0 | V24: =IF(AND(ISNUMBER(Calculated_Ratios!E24),ISNUMBER(E24)),Calculated_Ratios!E24-E24,IF(AND(Calculated_Ratios!E24="",ISBLANK(E24)),0,"MISMATCH")) -> 0 | W24: =IF(AND(ISNUMBER(Calculated_Ratios!F24),ISNUMBER(F24)),Calculated_Ratios!F24-F24,IF(AND(Calculated_Ratios!F24="",ISBLANK(F24)),0,"MISMATCH")) -> 0 | X24: =IF(AND(ISNUMBER(Calculated_Ratios!G24),ISNUMBER(G24)),Calculated_Ratios!G24-G24,IF(AND(Calculated_Ratios!G24="",ISBLANK(G24)),0,"MISMATCH")) -> 0 | Y24: =IF(AND(ISNUMBER(Calculated_Ratios!H24),ISNUMBER(H24)),Calculated_Ratios!H24-H24,IF(AND(Calculated_Ratios!H24="",ISBLANK(H24)),0,"MISMATCH")) -> 0 | Z24: =IF(AND(ISNUMBER(Calculated_Ratios!I24),ISNUMBER(I24)),Calculated_Ratios!I24-I24,IF(AND(Calculated_Ratios!I24="",ISBLANK(I24)),0,"MISMATCH")) -> 0 | AA24: =IF(AND(ISNUMBER(Calculated_Ratios!J24),ISNUMBER(J24)),Calculated_Ratios!J24-J24,IF(AND(Calculated_Ratios!J24="",ISBLANK(J24)),0,"MISMATCH")) -> 0 | ... AJ24: =IF(AND(ISNUMBER(Calculated_Ratios!S24),ISNUMBER(S24)),Calculated_Ratios!S24-S24,IF(AND(Calculated_Ratios!S24="",ISBLANK(S24)),0,"MISMATCH")) -> 0
A25: Fidelity | B25: 2014 | C25: 1134121 | D25: 1.2164487 | E25: 14.583602 | F25: 4.723041 | G25: 3.1210598 | H25: 24.209308 | I25: 0.3796773 | N25: 1.1622333 | O25: 85.416398 | P25: 13.986961 | Q25: 0 | R25: 0 | T25: =IF(AND(ISNUMBER(Calculated_Ratios!C25),ISNUMBER(C25)),Calculated_Ratios!C25-C25,IF(AND(Calculated_Ratios!C25="",ISBLANK(C25)),0,"MISMATCH")) -> 0 | U25: =IF(AND(ISNUMBER(Calculated_Ratios!D25),ISNUMBER(D25)),Calculated_Ratios!D25-D25,IF(AND(Calculated_Ratios!D25="",ISBLANK(D25)),0,"MISMATCH")) -> 0 | V25: =IF(AND(ISNUMBER(Calculated_Ratios!E25),ISNUMBER(E25)),Calculated_Ratios!E25-E25,IF(AND(Calculated_Ratios!E25="",ISBLANK(E25)),0,"MISMATCH")) -> 0 | W25: =IF(AND(ISNUMBER(Calculated_Ratios!F25),ISNUMBER(F25)),Calculated_Ratios!F25-F25,IF(AND(Calculated_Ratios!F25="",ISBLANK(F25)),0,"MISMATCH")) -> 0 | X25: =IF(AND(ISNUMBER(Calculated_Ratios!G25),ISNUMBER(G25)),Calculated_Ratios!G25-G25,IF(AND(Calculated_Ratios!G25="",ISBLANK(G25)),0,"MISMATCH")) -> 0 | Y25: =IF(AND(ISNUMBER(Calculated_Ratios!H25),ISNUMBER(H25)),Calculated_Ratios!H25-H25,IF(AND(Calculated_Ratios!H25="",ISBLANK(H25)),0,"MISMATCH")) -> 0 | Z25: =IF(AND(ISNUMBER(Calculated_Ratios!I25),ISNUMBER(I25)),Calculated_Ratios!I25-I25,IF(AND(Calculated_Ratios!I25="",ISBLANK(I25)),0,"MISMATCH")) -> 0 | AA25: =IF(AND(ISNUMBER(Calculated_Ratios!J25),ISNUMBER(J25)),Calculated_Ratios!J25-J25,IF(AND(Calculated_Ratios!J25="",ISBLANK(J25)),0,"MISMATCH")) -> 0 | ... AJ25: =IF(AND(ISNUMBER(Calculated_Ratios!S25),ISNUMBER(S25)),Calculated_Ratios!S25-S25,IF(AND(Calculated_Ratios!S25="",ISBLANK(S25)),0,"MISMATCH")) -> 0
A26: Fidelity | B26: 2015 | C26: 1209373.5 | D26: 1.1496862 | E26: 14.899141 | F26: 8.8584709 | G26: 3.4685748 | H26: 18.931152 | I26: 0.47661041 | N26: 1.1288261 | O26: 85.100859 | P26: 14.023924 | Q26: 0 | R26: -1 | T26: =IF(AND(ISNUMBER(Calculated_Ratios!C26),ISNUMBER(C26)),Calculated_Ratios!C26-C26,IF(AND(Calculated_Ratios!C26="",ISBLANK(C26)),0,"MISMATCH")) -> 0 | U26: =IF(AND(ISNUMBER(Calculated_Ratios!D26),ISNUMBER(D26)),Calculated_Ratios!D26-D26,IF(AND(Calculated_Ratios!D26="",ISBLANK(D26)),0,"MISMATCH")) -> 0 | V26: =IF(AND(ISNUMBER(Calculated_Ratios!E26),ISNUMBER(E26)),Calculated_Ratios!E26-E26,IF(AND(Calculated_Ratios!E26="",ISBLANK(E26)),0,"MISMATCH")) -> 0 | W26: =IF(AND(ISNUMBER(Calculated_Ratios!F26),ISNUMBER(F26)),Calculated_Ratios!F26-F26,IF(AND(Calculated_Ratios!F26="",ISBLANK(F26)),0,"MISMATCH")) -> 0 | X26: =IF(AND(ISNUMBER(Calculated_Ratios!G26),ISNUMBER(G26)),Calculated_Ratios!G26-G26,IF(AND(Calculated_Ratios!G26="",ISBLANK(G26)),0,"MISMATCH")) -> 0 | Y26: =IF(AND(ISNUMBER(Calculated_Ratios!H26),ISNUMBER(H26)),Calculated_Ratios!H26-H26,IF(AND(Calculated_Ratios!H26="",ISBLANK(H26)),0,"MISMATCH")) -> 0 | Z26: =IF(AND(ISNUMBER(Calculated_Ratios!I26),ISNUMBER(I26)),Calculated_Ratios!I26-I26,IF(AND(Calculated_Ratios!I26="",ISBLANK(I26)),0,"MISMATCH")) -> 0 | AA26: =IF(AND(ISNUMBER(Calculated_Ratios!J26),ISNUMBER(J26)),Calculated_Ratios!J26-J26,IF(AND(Calculated_Ratios!J26="",ISBLANK(J26)),0,"MISMATCH")) -> 0 | ... AJ26: =IF(AND(ISNUMBER(Calculated_Ratios!S26),ISNUMBER(S26)),Calculated_Ratios!S26-S26,IF(AND(Calculated_Ratios!S26="",ISBLANK(S26)),0,"MISMATCH")) -> 0
A27: Fidelity | B27: 2016 | C27: 1264931.5 | D27: 0.76952784 | E27: 14.282116 | F27: -4.4988207 | G27: 3.3263807 | H27: 17.299505 | I27: 0.68549166 | N27: 0.7498415 | O27: 85.717884 | P27: 14.076444 | Q27: 0 | R27: 0 | T27: =IF(AND(ISNUMBER(Calculated_Ratios!C27),ISNUMBER(C27)),Calculated_Ratios!C27-C27,IF(AND(Calculated_Ratios!C27="",ISBLANK(C27)),0,"MISMATCH")) -> 0 | U27: =IF(AND(ISNUMBER(Calculated_Ratios!D27),ISNUMBER(D27)),Calculated_Ratios!D27-D27,IF(AND(Calculated_Ratios!D27="",ISBLANK(D27)),0,"MISMATCH")) -> 0 | V27: =IF(AND(ISNUMBER(Calculated_Ratios!E27),ISNUMBER(E27)),Calculated_Ratios!E27-E27,IF(AND(Calculated_Ratios!E27="",ISBLANK(E27)),0,"MISMATCH")) -> 0 | W27: =IF(AND(ISNUMBER(Calculated_Ratios!F27),ISNUMBER(F27)),Calculated_Ratios!F27-F27,IF(AND(Calculated_Ratios!F27="",ISBLANK(F27)),0,"MISMATCH")) -> 0 | X27: =IF(AND(ISNUMBER(Calculated_Ratios!G27),ISNUMBER(G27)),Calculated_Ratios!G27-G27,IF(AND(Calculated_Ratios!G27="",ISBLANK(G27)),0,"MISMATCH")) -> 0 | Y27: =IF(AND(ISNUMBER(Calculated_Ratios!H27),ISNUMBER(H27)),Calculated_Ratios!H27-H27,IF(AND(Calculated_Ratios!H27="",ISBLANK(H27)),0,"MISMATCH")) -> 0 | Z27: =IF(AND(ISNUMBER(Calculated_Ratios!I27),ISNUMBER(I27)),Calculated_Ratios!I27-I27,IF(AND(Calculated_Ratios!I27="",ISBLANK(I27)),0,"MISMATCH")) -> 0 | AA27: =IF(AND(ISNUMBER(Calculated_Ratios!J27),ISNUMBER(J27)),Calculated_Ratios!J27-J27,IF(AND(Calculated_Ratios!J27="",ISBLANK(J27)),0,"MISMATCH")) -> 0 | ... AJ27: =IF(AND(ISNUMBER(Calculated_Ratios!S27),ISNUMBER(S27)),Calculated_Ratios!S27-S27,IF(AND(Calculated_Ratios!S27="",ISBLANK(S27)),0,"MISMATCH")) -> 0
A28: Fidelity | B28: 2017 | C28: 1338677.5 | D28: 1.408629 | E28: 14.741367 | F28: -2.8405647 | G28: 3.3418205 | H28: 16.029965 | I28: 0.84523718 | N28: 1.367228 | O28: 85.258633 | P28: 14.137024 | Q28: 0 | R28: 0 | T28: =IF(AND(ISNUMBER(Calculated_Ratios!C28),ISNUMBER(C28)),Calculated_Ratios!C28-C28,IF(AND(Calculated_Ratios!C28="",ISBLANK(C28)),0,"MISMATCH")) -> 0 | U28: =IF(AND(ISNUMBER(Calculated_Ratios!D28),ISNUMBER(D28)),Calculated_Ratios!D28-D28,IF(AND(Calculated_Ratios!D28="",ISBLANK(D28)),0,"MISMATCH")) -> 0 | V28: =IF(AND(ISNUMBER(Calculated_Ratios!E28),ISNUMBER(E28)),Calculated_Ratios!E28-E28,IF(AND(Calculated_Ratios!E28="",ISBLANK(E28)),0,"MISMATCH")) -> 0 | W28: =IF(AND(ISNUMBER(Calculated_Ratios!F28),ISNUMBER(F28)),Calculated_Ratios!F28-F28,IF(AND(Calculated_Ratios!F28="",ISBLANK(F28)),0,"MISMATCH")) -> 0 | X28: =IF(AND(ISNUMBER(Calculated_Ratios!G28),ISNUMBER(G28)),Calculated_Ratios!G28-G28,IF(AND(Calculated_Ratios!G28="",ISBLANK(G28)),0,"MISMATCH")) -> 0 | Y28: =IF(AND(ISNUMBER(Calculated_Ratios!H28),ISNUMBER(H28)),Calculated_Ratios!H28-H28,IF(AND(Calculated_Ratios!H28="",ISBLANK(H28)),0,"MISMATCH")) -> 0 | Z28: =IF(AND(ISNUMBER(Calculated_Ratios!I28),ISNUMBER(I28)),Calculated_Ratios!I28-I28,IF(AND(Calculated_Ratios!I28="",ISBLANK(I28)),0,"MISMATCH")) -> 0 | AA28: =IF(AND(ISNUMBER(Calculated_Ratios!J28),ISNUMBER(J28)),Calculated_Ratios!J28-J28,IF(AND(Calculated_Ratios!J28="",ISBLANK(J28)),0,"MISMATCH")) -> 0 | ... AJ28: =IF(AND(ISNUMBER(Calculated_Ratios!S28),ISNUMBER(S28)),Calculated_Ratios!S28-S28,IF(AND(Calculated_Ratios!S28="",ISBLANK(S28)),0,"MISMATCH")) -> 0
A29: Fidelity | B29: 2018 | E29: 11.304025 | N29: 1.3329977 | O29: 88.695975 | P29: 14.357767 | Q29: 0 | T29: =IF(AND(ISNUMBER(Calculated_Ratios!C29),ISNUMBER(C29)),Calculated_Ratios!C29-C29,IF(AND(Calculated_Ratios!C29="",ISBLANK(C29)),0,"MISMATCH")) -> 0 | U29: =IF(AND(ISNUMBER(Calculated_Ratios!D29),ISNUMBER(D29)),Calculated_Ratios!D29-D29,IF(AND(Calculated_Ratios!D29="",ISBLANK(D29)),0,"MISMATCH")) -> 0 | V29: =IF(AND(ISNUMBER(Calculated_Ratios!E29),ISNUMBER(E29)),Calculated_Ratios!E29-E29,IF(AND(Calculated_Ratios!E29="",ISBLANK(E29)),0,"MISMATCH")) -> 0 | W29: =IF(AND(ISNUMBER(Calculated_Ratios!F29),ISNUMBER(F29)),Calculated_Ratios!F29-F29,IF(AND(Calculated_Ratios!F29="",ISBLANK(F29)),0,"MISMATCH")) -> 0 | X29: =IF(AND(ISNUMBER(Calculated_Ratios!G29),ISNUMBER(G29)),Calculated_Ratios!G29-G29,IF(AND(Calculated_Ratios!G29="",ISBLANK(G29)),0,"MISMATCH")) -> 0 | Y29: =IF(AND(ISNUMBER(Calculated_Ratios!H29),ISNUMBER(H29)),Calculated_Ratios!H29-H29,IF(AND(Calculated_Ratios!H29="",ISBLANK(H29)),0,"MISMATCH")) -> 0 | Z29: =IF(AND(ISNUMBER(Calculated_Ratios!I29),ISNUMBER(I29)),Calculated_Ratios!I29-I29,IF(AND(Calculated_Ratios!I29="",ISBLANK(I29)),0,"MISMATCH")) -> 0 | AA29: =IF(AND(ISNUMBER(Calculated_Ratios!J29),ISNUMBER(J29)),Calculated_Ratios!J29-J29,IF(AND(Calculated_Ratios!J29="",ISBLANK(J29)),0,"MISMATCH")) -> 0 | ... AJ29: =IF(AND(ISNUMBER(Calculated_Ratios!S29),ISNUMBER(S29)),Calculated_Ratios!S29-S29,IF(AND(Calculated_Ratios!S29="",ISBLANK(S29)),0,"MISMATCH")) -> 0
A30: Fidelity | B30: 2019 | C30: 1916960 | D30: 1.4828165 | E30: 11.070289 | I30: -0.2760621 | N30: 1.3445838 | O30: 88.929711 | P30: 14.56411 | Q30: 0 | T30: =IF(AND(ISNUMBER(Calculated_Ratios!C30),ISNUMBER(C30)),Calculated_Ratios!C30-C30,IF(AND(Calculated_Ratios!C30="",ISBLANK(C30)),0,"MISMATCH")) -> 0 | U30: =IF(AND(ISNUMBER(Calculated_Ratios!D30),ISNUMBER(D30)),Calculated_Ratios!D30-D30,IF(AND(Calculated_Ratios!D30="",ISBLANK(D30)),0,"MISMATCH")) -> 0 | V30: =IF(AND(ISNUMBER(Calculated_Ratios!E30),ISNUMBER(E30)),Calculated_Ratios!E30-E30,IF(AND(Calculated_Ratios!E30="",ISBLANK(E30)),0,"MISMATCH")) -> 0 | W30: =IF(AND(ISNUMBER(Calculated_Ratios!F30),ISNUMBER(F30)),Calculated_Ratios!F30-F30,IF(AND(Calculated_Ratios!F30="",ISBLANK(F30)),0,"MISMATCH")) -> 0 | X30: =IF(AND(ISNUMBER(Calculated_Ratios!G30),ISNUMBER(G30)),Calculated_Ratios!G30-G30,IF(AND(Calculated_Ratios!G30="",ISBLANK(G30)),0,"MISMATCH")) -> 0 | Y30: =IF(AND(ISNUMBER(Calculated_Ratios!H30),ISNUMBER(H30)),Calculated_Ratios!H30-H30,IF(AND(Calculated_Ratios!H30="",ISBLANK(H30)),0,"MISMATCH")) -> 0 | Z30: =IF(AND(ISNUMBER(Calculated_Ratios!I30),ISNUMBER(I30)),Calculated_Ratios!I30-I30,IF(AND(Calculated_Ratios!I30="",ISBLANK(I30)),0,"MISMATCH")) -> 0 | AA30: =IF(AND(ISNUMBER(Calculated_Ratios!J30),ISNUMBER(J30)),Calculated_Ratios!J30-J30,IF(AND(Calculated_Ratios!J30="",ISBLANK(J30)),0,"MISMATCH")) -> 0 | ... AJ30: =IF(AND(ISNUMBER(Calculated_Ratios!S30),ISNUMBER(S30)),Calculated_Ratios!S30-S30,IF(AND(Calculated_Ratios!S30="",ISBLANK(S30)),0,"MISMATCH")) -> 0
A31: Fidelity | B31: 2020 | C31: 2436092.5 | D31: 1.093965 | E31: 9.9172706 | F31: 9.9593509 | G31: 4.8447788 | H31: 18.182958 | I31: 0.69200985 | N31: 0.96622806 | O31: 90.082729 | P31: 14.83007 | Q31: 0 | R31: 0 | T31: =IF(AND(ISNUMBER(Calculated_Ratios!C31),ISNUMBER(C31)),Calculated_Ratios!C31-C31,IF(AND(Calculated_Ratios!C31="",ISBLANK(C31)),0,"MISMATCH")) -> 0 | U31: =IF(AND(ISNUMBER(Calculated_Ratios!D31),ISNUMBER(D31)),Calculated_Ratios!D31-D31,IF(AND(Calculated_Ratios!D31="",ISBLANK(D31)),0,"MISMATCH")) -> 0 | V31: =IF(AND(ISNUMBER(Calculated_Ratios!E31),ISNUMBER(E31)),Calculated_Ratios!E31-E31,IF(AND(Calculated_Ratios!E31="",ISBLANK(E31)),0,"MISMATCH")) -> 0 | W31: =IF(AND(ISNUMBER(Calculated_Ratios!F31),ISNUMBER(F31)),Calculated_Ratios!F31-F31,IF(AND(Calculated_Ratios!F31="",ISBLANK(F31)),0,"MISMATCH")) -> 0 | X31: =IF(AND(ISNUMBER(Calculated_Ratios!G31),ISNUMBER(G31)),Calculated_Ratios!G31-G31,IF(AND(Calculated_Ratios!G31="",ISBLANK(G31)),0,"MISMATCH")) -> 0 | Y31: =IF(AND(ISNUMBER(Calculated_Ratios!H31),ISNUMBER(H31)),Calculated_Ratios!H31-H31,IF(AND(Calculated_Ratios!H31="",ISBLANK(H31)),0,"MISMATCH")) -> 0 | Z31: =IF(AND(ISNUMBER(Calculated_Ratios!I31),ISNUMBER(I31)),Calculated_Ratios!I31-I31,IF(AND(Calculated_Ratios!I31="",ISBLANK(I31)),0,"MISMATCH")) -> 0 | AA31: =IF(AND(ISNUMBER(Calculated_Ratios!J31),ISNUMBER(J31)),Calculated_Ratios!J31-J31,IF(AND(Calculated_Ratios!J31="",ISBLANK(J31)),0,"MISMATCH")) -> 0 | ... AJ31: =IF(AND(ISNUMBER(Calculated_Ratios!S31),ISNUMBER(S31)),Calculated_Ratios!S31-S31,IF(AND(Calculated_Ratios!S31="",ISBLANK(S31)),0,"MISMATCH")) -> 0
A32: Fidelity | B32: 2021 | E32: 8.696784 | G32: 4.2787394 | H32: 19.147101 | N32: 0.70429276 | O32: 91.303216 | P32: 15.003492 | Q32: 0 | R32: 0 | T32: =IF(AND(ISNUMBER(Calculated_Ratios!C32),ISNUMBER(C32)),Calculated_Ratios!C32-C32,IF(AND(Calculated_Ratios!C32="",ISBLANK(C32)),0,"MISMATCH")) -> 0 | U32: =IF(AND(ISNUMBER(Calculated_Ratios!D32),ISNUMBER(D32)),Calculated_Ratios!D32-D32,IF(AND(Calculated_Ratios!D32="",ISBLANK(D32)),0,"MISMATCH")) -> 0 | V32: =IF(AND(ISNUMBER(Calculated_Ratios!E32),ISNUMBER(E32)),Calculated_Ratios!E32-E32,IF(AND(Calculated_Ratios!E32="",ISBLANK(E32)),0,"MISMATCH")) -> 0 | W32: =IF(AND(ISNUMBER(Calculated_Ratios!F32),ISNUMBER(F32)),Calculated_Ratios!F32-F32,IF(AND(Calculated_Ratios!F32="",ISBLANK(F32)),0,"MISMATCH")) -> 0 | X32: =IF(AND(ISNUMBER(Calculated_Ratios!G32),ISNUMBER(G32)),Calculated_Ratios!G32-G32,IF(AND(Calculated_Ratios!G32="",ISBLANK(G32)),0,"MISMATCH")) -> 0 | Y32: =IF(AND(ISNUMBER(Calculated_Ratios!H32),ISNUMBER(H32)),Calculated_Ratios!H32-H32,IF(AND(Calculated_Ratios!H32="",ISBLANK(H32)),0,"MISMATCH")) -> 0 | Z32: =IF(AND(ISNUMBER(Calculated_Ratios!I32),ISNUMBER(I32)),Calculated_Ratios!I32-I32,IF(AND(Calculated_Ratios!I32="",ISBLANK(I32)),0,"MISMATCH")) -> 0 | AA32: =IF(AND(ISNUMBER(Calculated_Ratios!J32),ISNUMBER(J32)),Calculated_Ratios!J32-J32,IF(AND(Calculated_Ratios!J32="",ISBLANK(J32)),0,"MISMATCH")) -> 0 | ... AJ32: =IF(AND(ISNUMBER(Calculated_Ratios!S32),ISNUMBER(S32)),Calculated_Ratios!S32-S32,IF(AND(Calculated_Ratios!S32="",ISBLANK(S32)),0,"MISMATCH")) -> 0
A33: Fidelity | B33: 2022 | C33: 3634731.5 | D33: 1.285487 | E33: 7.8806541 | F33: 8.1874548 | G33: 3.6666727 | H33: 18.142178 | I33: 0.14974971 | N33: 1.1713185 | O33: 92.119346 | P33: 15.199053 | Q33: 0 | R33: 0 | T33: =IF(AND(ISNUMBER(Calculated_Ratios!C33),ISNUMBER(C33)),Calculated_Ratios!C33-C33,IF(AND(Calculated_Ratios!C33="",ISBLANK(C33)),0,"MISMATCH")) -> 0 | U33: =IF(AND(ISNUMBER(Calculated_Ratios!D33),ISNUMBER(D33)),Calculated_Ratios!D33-D33,IF(AND(Calculated_Ratios!D33="",ISBLANK(D33)),0,"MISMATCH")) -> 0 | V33: =IF(AND(ISNUMBER(Calculated_Ratios!E33),ISNUMBER(E33)),Calculated_Ratios!E33-E33,IF(AND(Calculated_Ratios!E33="",ISBLANK(E33)),0,"MISMATCH")) -> 0 | W33: =IF(AND(ISNUMBER(Calculated_Ratios!F33),ISNUMBER(F33)),Calculated_Ratios!F33-F33,IF(AND(Calculated_Ratios!F33="",ISBLANK(F33)),0,"MISMATCH")) -> 0 | X33: =IF(AND(ISNUMBER(Calculated_Ratios!G33),ISNUMBER(G33)),Calculated_Ratios!G33-G33,IF(AND(Calculated_Ratios!G33="",ISBLANK(G33)),0,"MISMATCH")) -> 0 | Y33: =IF(AND(ISNUMBER(Calculated_Ratios!H33),ISNUMBER(H33)),Calculated_Ratios!H33-H33,IF(AND(Calculated_Ratios!H33="",ISBLANK(H33)),0,"MISMATCH")) -> 0 | Z33: =IF(AND(ISNUMBER(Calculated_Ratios!I33),ISNUMBER(I33)),Calculated_Ratios!I33-I33,IF(AND(Calculated_Ratios!I33="",ISBLANK(I33)),0,"MISMATCH")) -> 0 | AA33: =IF(AND(ISNUMBER(Calculated_Ratios!J33),ISNUMBER(J33)),Calculated_Ratios!J33-J33,IF(AND(Calculated_Ratios!J33="",ISBLANK(J33)),0,"MISMATCH")) -> 0 | ... AJ33: =IF(AND(ISNUMBER(Calculated_Ratios!S33),ISNUMBER(S33)),Calculated_Ratios!S33-S33,IF(AND(Calculated_Ratios!S33="",ISBLANK(S33)),0,"MISMATCH")) -> 0
A34: First Bank | B34: 2013 | E34: 10.802417 | G34: 2.7353876 | N34: 1.8285401 | O34: 89.197583 | P34: 14.993112 | Q34: 0 | T34: =IF(AND(ISNUMBER(Calculated_Ratios!C34),ISNUMBER(C34)),Calculated_Ratios!C34-C34,IF(AND(Calculated_Ratios!C34="",ISBLANK(C34)),0,"MISMATCH")) -> 0 | U34: =IF(AND(ISNUMBER(Calculated_Ratios!D34),ISNUMBER(D34)),Calculated_Ratios!D34-D34,IF(AND(Calculated_Ratios!D34="",ISBLANK(D34)),0,"MISMATCH")) -> 0 | V34: =IF(AND(ISNUMBER(Calculated_Ratios!E34),ISNUMBER(E34)),Calculated_Ratios!E34-E34,IF(AND(Calculated_Ratios!E34="",ISBLANK(E34)),0,"MISMATCH")) -> 0 | W34: =IF(AND(ISNUMBER(Calculated_Ratios!F34),ISNUMBER(F34)),Calculated_Ratios!F34-F34,IF(AND(Calculated_Ratios!F34="",ISBLANK(F34)),0,"MISMATCH")) -> 0 | X34: =IF(AND(ISNUMBER(Calculated_Ratios!G34),ISNUMBER(G34)),Calculated_Ratios!G34-G34,IF(AND(Calculated_Ratios!G34="",ISBLANK(G34)),0,"MISMATCH")) -> 0 | Y34: =IF(AND(ISNUMBER(Calculated_Ratios!H34),ISNUMBER(H34)),Calculated_Ratios!H34-H34,IF(AND(Calculated_Ratios!H34="",ISBLANK(H34)),0,"MISMATCH")) -> 0 | Z34: =IF(AND(ISNUMBER(Calculated_Ratios!I34),ISNUMBER(I34)),Calculated_Ratios!I34-I34,IF(AND(Calculated_Ratios!I34="",ISBLANK(I34)),0,"MISMATCH")) -> 0 | AA34: =IF(AND(ISNUMBER(Calculated_Ratios!J34),ISNUMBER(J34)),Calculated_Ratios!J34-J34,IF(AND(Calculated_Ratios!J34="",ISBLANK(J34)),0,"MISMATCH")) -> 0 | ... AJ34: =IF(AND(ISNUMBER(Calculated_Ratios!S34),ISNUMBER(S34)),Calculated_Ratios!S34-S34,IF(AND(Calculated_Ratios!S34="",ISBLANK(S34)),0,"MISMATCH")) -> 0
A35: First Bank | B35: 2014 | C35: 3368725 | D35: 2.3555203 | E35: 12.118666 | F35: -15.04026 | G35: 2.0779354 | I35: 0.6211252 | N35: 2.2731003 | O35: 87.881334 | P35: 15.065662 | Q35: 0 | T35: =IF(AND(ISNUMBER(Calculated_Ratios!C35),ISNUMBER(C35)),Calculated_Ratios!C35-C35,IF(AND(Calculated_Ratios!C35="",ISBLANK(C35)),0,"MISMATCH")) -> 0 | U35: =IF(AND(ISNUMBER(Calculated_Ratios!D35),ISNUMBER(D35)),Calculated_Ratios!D35-D35,IF(AND(Calculated_Ratios!D35="",ISBLANK(D35)),0,"MISMATCH")) -> 0 | V35: =IF(AND(ISNUMBER(Calculated_Ratios!E35),ISNUMBER(E35)),Calculated_Ratios!E35-E35,IF(AND(Calculated_Ratios!E35="",ISBLANK(E35)),0,"MISMATCH")) -> 0 | W35: =IF(AND(ISNUMBER(Calculated_Ratios!F35),ISNUMBER(F35)),Calculated_Ratios!F35-F35,IF(AND(Calculated_Ratios!F35="",ISBLANK(F35)),0,"MISMATCH")) -> 0 | X35: =IF(AND(ISNUMBER(Calculated_Ratios!G35),ISNUMBER(G35)),Calculated_Ratios!G35-G35,IF(AND(Calculated_Ratios!G35="",ISBLANK(G35)),0,"MISMATCH")) -> 0 | Y35: =IF(AND(ISNUMBER(Calculated_Ratios!H35),ISNUMBER(H35)),Calculated_Ratios!H35-H35,IF(AND(Calculated_Ratios!H35="",ISBLANK(H35)),0,"MISMATCH")) -> 0 | Z35: =IF(AND(ISNUMBER(Calculated_Ratios!I35),ISNUMBER(I35)),Calculated_Ratios!I35-I35,IF(AND(Calculated_Ratios!I35="",ISBLANK(I35)),0,"MISMATCH")) -> 0 | AA35: =IF(AND(ISNUMBER(Calculated_Ratios!J35),ISNUMBER(J35)),Calculated_Ratios!J35-J35,IF(AND(Calculated_Ratios!J35="",ISBLANK(J35)),0,"MISMATCH")) -> 0 | ... AJ35: =IF(AND(ISNUMBER(Calculated_Ratios!S35),ISNUMBER(S35)),Calculated_Ratios!S35-S35,IF(AND(Calculated_Ratios!S35="",ISBLANK(S35)),0,"MISMATCH")) -> 0
A36: First Bank | B36: 2015 | C36: 3411623 | D36: 0.0010845278 | E36: 13.796376 | F36: 8.9679311 | G36: 8.630503 | H36: 17.079044 | I36: 3.5187358 | N36: 0.0011103192 | O36: 86.203624 | P36: 15.019196 | Q36: 0 | R36: 0 | T36: =IF(AND(ISNUMBER(Calculated_Ratios!C36),ISNUMBER(C36)),Calculated_Ratios!C36-C36,IF(AND(Calculated_Ratios!C36="",ISBLANK(C36)),0,"MISMATCH")) -> 0 | U36: =IF(AND(ISNUMBER(Calculated_Ratios!D36),ISNUMBER(D36)),Calculated_Ratios!D36-D36,IF(AND(Calculated_Ratios!D36="",ISBLANK(D36)),0,"MISMATCH")) -> 0 | V36: =IF(AND(ISNUMBER(Calculated_Ratios!E36),ISNUMBER(E36)),Calculated_Ratios!E36-E36,IF(AND(Calculated_Ratios!E36="",ISBLANK(E36)),0,"MISMATCH")) -> 0 | W36: =IF(AND(ISNUMBER(Calculated_Ratios!F36),ISNUMBER(F36)),Calculated_Ratios!F36-F36,IF(AND(Calculated_Ratios!F36="",ISBLANK(F36)),0,"MISMATCH")) -> 0 | X36: =IF(AND(ISNUMBER(Calculated_Ratios!G36),ISNUMBER(G36)),Calculated_Ratios!G36-G36,IF(AND(Calculated_Ratios!G36="",ISBLANK(G36)),0,"MISMATCH")) -> 0 | Y36: =IF(AND(ISNUMBER(Calculated_Ratios!H36),ISNUMBER(H36)),Calculated_Ratios!H36-H36,IF(AND(Calculated_Ratios!H36="",ISBLANK(H36)),0,"MISMATCH")) -> 0 | Z36: =IF(AND(ISNUMBER(Calculated_Ratios!I36),ISNUMBER(I36)),Calculated_Ratios!I36-I36,IF(AND(Calculated_Ratios!I36="",ISBLANK(I36)),0,"MISMATCH")) -> 0 | AA36: =IF(AND(ISNUMBER(Calculated_Ratios!J36),ISNUMBER(J36)),Calculated_Ratios!J36-J36,IF(AND(Calculated_Ratios!J36="",ISBLANK(J36)),0,"MISMATCH")) -> 0 | ... AJ36: =IF(AND(ISNUMBER(Calculated_Ratios!S36),ISNUMBER(S36)),Calculated_Ratios!S36-S36,IF(AND(Calculated_Ratios!S36="",ISBLANK(S36)),0,"MISMATCH")) -> 0
A37: First Bank | B37: 2016 | E37: 13.662641 | G37: 12.449267 | H37: 17.786654 | N37: 1.4073937 | O37: 86.337359 | P37: 15.084648 | Q37: 0 | R37: 0 | T37: =IF(AND(ISNUMBER(Calculated_Ratios!C37),ISNUMBER(C37)),Calculated_Ratios!C37-C37,IF(AND(Calculated_Ratios!C37="",ISBLANK(C37)),0,"MISMATCH")) -> 0 | U37: =IF(AND(ISNUMBER(Calculated_Ratios!D37),ISNUMBER(D37)),Calculated_Ratios!D37-D37,IF(AND(Calculated_Ratios!D37="",ISBLANK(D37)),0,"MISMATCH")) -> 0 | V37: =IF(AND(ISNUMBER(Calculated_Ratios!E37),ISNUMBER(E37)),Calculated_Ratios!E37-E37,IF(AND(Calculated_Ratios!E37="",ISBLANK(E37)),0,"MISMATCH")) -> 0 | W37: =IF(AND(ISNUMBER(Calculated_Ratios!F37),ISNUMBER(F37)),Calculated_Ratios!F37-F37,IF(AND(Calculated_Ratios!F37="",ISBLANK(F37)),0,"MISMATCH")) -> 0 | X37: =IF(AND(ISNUMBER(Calculated_Ratios!G37),ISNUMBER(G37)),Calculated_Ratios!G37-G37,IF(AND(Calculated_Ratios!G37="",ISBLANK(G37)),0,"MISMATCH")) -> 0 | Y37: =IF(AND(ISNUMBER(Calculated_Ratios!H37),ISNUMBER(H37)),Calculated_Ratios!H37-H37,IF(AND(Calculated_Ratios!H37="",ISBLANK(H37)),0,"MISMATCH")) -> 0 | Z37: =IF(AND(ISNUMBER(Calculated_Ratios!I37),ISNUMBER(I37)),Calculated_Ratios!I37-I37,IF(AND(Calculated_Ratios!I37="",ISBLANK(I37)),0,"MISMATCH")) -> 0 | AA37: =IF(AND(ISNUMBER(Calculated_Ratios!J37),ISNUMBER(J37)),Calculated_Ratios!J37-J37,IF(AND(Calculated_Ratios!J37="",ISBLANK(J37)),0,"MISMATCH")) -> 0 | ... AJ37: =IF(AND(ISNUMBER(Calculated_Ratios!S37),ISNUMBER(S37)),Calculated_Ratios!S37-S37,IF(AND(Calculated_Ratios!S37="",ISBLANK(S37)),0,"MISMATCH")) -> 0
A38: First Bank | B38: 2017 | C38: 3667410.5 | D38: 1.2793223 | E38: 15.351787 | F38: 3.0869738 | G38: 9.7261247 | H38: 17.738851 | N38: 1.24219 | O38: 84.648213 | P38: 15.144451 | Q38: 0 | R38: 0 | T38: =IF(AND(ISNUMBER(Calculated_Ratios!C38),ISNUMBER(C38)),Calculated_Ratios!C38-C38,IF(AND(Calculated_Ratios!C38="",ISBLANK(C38)),0,"MISMATCH")) -> 0 | U38: =IF(AND(ISNUMBER(Calculated_Ratios!D38),ISNUMBER(D38)),Calculated_Ratios!D38-D38,IF(AND(Calculated_Ratios!D38="",ISBLANK(D38)),0,"MISMATCH")) -> 0 | V38: =IF(AND(ISNUMBER(Calculated_Ratios!E38),ISNUMBER(E38)),Calculated_Ratios!E38-E38,IF(AND(Calculated_Ratios!E38="",ISBLANK(E38)),0,"MISMATCH")) -> 0 | W38: =IF(AND(ISNUMBER(Calculated_Ratios!F38),ISNUMBER(F38)),Calculated_Ratios!F38-F38,IF(AND(Calculated_Ratios!F38="",ISBLANK(F38)),0,"MISMATCH")) -> 0 | X38: =IF(AND(ISNUMBER(Calculated_Ratios!G38),ISNUMBER(G38)),Calculated_Ratios!G38-G38,IF(AND(Calculated_Ratios!G38="",ISBLANK(G38)),0,"MISMATCH")) -> 0 | Y38: =IF(AND(ISNUMBER(Calculated_Ratios!H38),ISNUMBER(H38)),Calculated_Ratios!H38-H38,IF(AND(Calculated_Ratios!H38="",ISBLANK(H38)),0,"MISMATCH")) -> 0 | Z38: =IF(AND(ISNUMBER(Calculated_Ratios!I38),ISNUMBER(I38)),Calculated_Ratios!I38-I38,IF(AND(Calculated_Ratios!I38="",ISBLANK(I38)),0,"MISMATCH")) -> 0 | AA38: =IF(AND(ISNUMBER(Calculated_Ratios!J38),ISNUMBER(J38)),Calculated_Ratios!J38-J38,IF(AND(Calculated_Ratios!J38="",ISBLANK(J38)),0,"MISMATCH")) -> 0 | ... AJ38: =IF(AND(ISNUMBER(Calculated_Ratios!S38),ISNUMBER(S38)),Calculated_Ratios!S38-S38,IF(AND(Calculated_Ratios!S38="",ISBLANK(S38)),0,"MISMATCH")) -> 0
A39: First Bank | B39: 2018 | C39: 3881473 | D39: 1.467278 | E39: 11.10623 | F39: 8.4374411 | G39: 16.052908 | H39: 10.657651 | I39: 1.5938537 | N39: 1.4288341 | O39: 88.89377 | P39: 15.198275 | Q39: 0 | R39: 0 | T39: =IF(AND(ISNUMBER(Calculated_Ratios!C39),ISNUMBER(C39)),Calculated_Ratios!C39-C39,IF(AND(Calculated_Ratios!C39="",ISBLANK(C39)),0,"MISMATCH")) -> 0 | U39: =IF(AND(ISNUMBER(Calculated_Ratios!D39),ISNUMBER(D39)),Calculated_Ratios!D39-D39,IF(AND(Calculated_Ratios!D39="",ISBLANK(D39)),0,"MISMATCH")) -> 0 | V39: =IF(AND(ISNUMBER(Calculated_Ratios!E39),ISNUMBER(E39)),Calculated_Ratios!E39-E39,IF(AND(Calculated_Ratios!E39="",ISBLANK(E39)),0,"MISMATCH")) -> 0 | W39: =IF(AND(ISNUMBER(Calculated_Ratios!F39),ISNUMBER(F39)),Calculated_Ratios!F39-F39,IF(AND(Calculated_Ratios!F39="",ISBLANK(F39)),0,"MISMATCH")) -> 0 | X39: =IF(AND(ISNUMBER(Calculated_Ratios!G39),ISNUMBER(G39)),Calculated_Ratios!G39-G39,IF(AND(Calculated_Ratios!G39="",ISBLANK(G39)),0,"MISMATCH")) -> 0 | Y39: =IF(AND(ISNUMBER(Calculated_Ratios!H39),ISNUMBER(H39)),Calculated_Ratios!H39-H39,IF(AND(Calculated_Ratios!H39="",ISBLANK(H39)),0,"MISMATCH")) -> 0 | Z39: =IF(AND(ISNUMBER(Calculated_Ratios!I39),ISNUMBER(I39)),Calculated_Ratios!I39-I39,IF(AND(Calculated_Ratios!I39="",ISBLANK(I39)),0,"MISMATCH")) -> 0 | AA39: =IF(AND(ISNUMBER(Calculated_Ratios!J39),ISNUMBER(J39)),Calculated_Ratios!J39-J39,IF(AND(Calculated_Ratios!J39="",ISBLANK(J39)),0,"MISMATCH")) -> 0 | ... AJ39: =IF(AND(ISNUMBER(Calculated_Ratios!S39),ISNUMBER(S39)),Calculated_Ratios!S39-S39,IF(AND(Calculated_Ratios!S39="",ISBLANK(S39)),0,"MISMATCH")) -> 0
A40: First Bank | B40: 2019 | C40: 4327093 | D40: 1.0149308 | E40: 11.555972 | F40: -5.0554032 | G40: 3.6640337 | H40: 11.156867 | I40: 1.0778599 | N40: 0.94075354 | O40: 88.444028 | P40: 15.356301 | Q40: 0 | R40: -1 | T40: =IF(AND(ISNUMBER(Calculated_Ratios!C40),ISNUMBER(C40)),Calculated_Ratios!C40-C40,IF(AND(Calculated_Ratios!C40="",ISBLANK(C40)),0,"MISMATCH")) -> 0 | U40: =IF(AND(ISNUMBER(Calculated_Ratios!D40),ISNUMBER(D40)),Calculated_Ratios!D40-D40,IF(AND(Calculated_Ratios!D40="",ISBLANK(D40)),0,"MISMATCH")) -> 0 | V40: =IF(AND(ISNUMBER(Calculated_Ratios!E40),ISNUMBER(E40)),Calculated_Ratios!E40-E40,IF(AND(Calculated_Ratios!E40="",ISBLANK(E40)),0,"MISMATCH")) -> 0 | W40: =IF(AND(ISNUMBER(Calculated_Ratios!F40),ISNUMBER(F40)),Calculated_Ratios!F40-F40,IF(AND(Calculated_Ratios!F40="",ISBLANK(F40)),0,"MISMATCH")) -> 0 | X40: =IF(AND(ISNUMBER(Calculated_Ratios!G40),ISNUMBER(G40)),Calculated_Ratios!G40-G40,IF(AND(Calculated_Ratios!G40="",ISBLANK(G40)),0,"MISMATCH")) -> 0 | Y40: =IF(AND(ISNUMBER(Calculated_Ratios!H40),ISNUMBER(H40)),Calculated_Ratios!H40-H40,IF(AND(Calculated_Ratios!H40="",ISBLANK(H40)),0,"MISMATCH")) -> 0 | Z40: =IF(AND(ISNUMBER(Calculated_Ratios!I40),ISNUMBER(I40)),Calculated_Ratios!I40-I40,IF(AND(Calculated_Ratios!I40="",ISBLANK(I40)),0,"MISMATCH")) -> 0 | AA40: =IF(AND(ISNUMBER(Calculated_Ratios!J40),ISNUMBER(J40)),Calculated_Ratios!J40-J40,IF(AND(Calculated_Ratios!J40="",ISBLANK(J40)),0,"MISMATCH")) -> 0 | ... AJ40: =IF(AND(ISNUMBER(Calculated_Ratios!S40),ISNUMBER(S40)),Calculated_Ratios!S40-S40,IF(AND(Calculated_Ratios!S40="",ISBLANK(S40)),0,"MISMATCH")) -> 0
A41: First Bank | B41: 2022 | E41: 9.2662208 | N41: 1.1250994 | O41: 90.733779 | P41: 15.910464 | Q41: 0 | T41: =IF(AND(ISNUMBER(Calculated_Ratios!C41),ISNUMBER(C41)),Calculated_Ratios!C41-C41,IF(AND(Calculated_Ratios!C41="",ISBLANK(C41)),0,"MISMATCH")) -> 0 | U41: =IF(AND(ISNUMBER(Calculated_Ratios!D41),ISNUMBER(D41)),Calculated_Ratios!D41-D41,IF(AND(Calculated_Ratios!D41="",ISBLANK(D41)),0,"MISMATCH")) -> 0 | V41: =IF(AND(ISNUMBER(Calculated_Ratios!E41),ISNUMBER(E41)),Calculated_Ratios!E41-E41,IF(AND(Calculated_Ratios!E41="",ISBLANK(E41)),0,"MISMATCH")) -> 0 | W41: =IF(AND(ISNUMBER(Calculated_Ratios!F41),ISNUMBER(F41)),Calculated_Ratios!F41-F41,IF(AND(Calculated_Ratios!F41="",ISBLANK(F41)),0,"MISMATCH")) -> 0 | X41: =IF(AND(ISNUMBER(Calculated_Ratios!G41),ISNUMBER(G41)),Calculated_Ratios!G41-G41,IF(AND(Calculated_Ratios!G41="",ISBLANK(G41)),0,"MISMATCH")) -> 0 | Y41: =IF(AND(ISNUMBER(Calculated_Ratios!H41),ISNUMBER(H41)),Calculated_Ratios!H41-H41,IF(AND(Calculated_Ratios!H41="",ISBLANK(H41)),0,"MISMATCH")) -> 0 | Z41: =IF(AND(ISNUMBER(Calculated_Ratios!I41),ISNUMBER(I41)),Calculated_Ratios!I41-I41,IF(AND(Calculated_Ratios!I41="",ISBLANK(I41)),0,"MISMATCH")) -> 0 | AA41: =IF(AND(ISNUMBER(Calculated_Ratios!J41),ISNUMBER(J41)),Calculated_Ratios!J41-J41,IF(AND(Calculated_Ratios!J41="",ISBLANK(J41)),0,"MISMATCH")) -> 0 | ... AJ41: =IF(AND(ISNUMBER(Calculated_Ratios!S41),ISNUMBER(S41)),Calculated_Ratios!S41-S41,IF(AND(Calculated_Ratios!S41="",ISBLANK(S41)),0,"MISMATCH")) -> 0
A42: GTBank | B42: 2013 | E42: 17.310065 | N42: 4.4920987 | O42: 82.689935 | P42: 14.45966 | Q42: 0 | T42: =IF(AND(ISNUMBER(Calculated_Ratios!C42),ISNUMBER(C42)),Calculated_Ratios!C42-C42,IF(AND(Calculated_Ratios!C42="",ISBLANK(C42)),0,"MISMATCH")) -> 0 | U42: =IF(AND(ISNUMBER(Calculated_Ratios!D42),ISNUMBER(D42)),Calculated_Ratios!D42-D42,IF(AND(Calculated_Ratios!D42="",ISBLANK(D42)),0,"MISMATCH")) -> 0 | V42: =IF(AND(ISNUMBER(Calculated_Ratios!E42),ISNUMBER(E42)),Calculated_Ratios!E42-E42,IF(AND(Calculated_Ratios!E42="",ISBLANK(E42)),0,"MISMATCH")) -> 0 | W42: =IF(AND(ISNUMBER(Calculated_Ratios!F42),ISNUMBER(F42)),Calculated_Ratios!F42-F42,IF(AND(Calculated_Ratios!F42="",ISBLANK(F42)),0,"MISMATCH")) -> 0 | X42: =IF(AND(ISNUMBER(Calculated_Ratios!G42),ISNUMBER(G42)),Calculated_Ratios!G42-G42,IF(AND(Calculated_Ratios!G42="",ISBLANK(G42)),0,"MISMATCH")) -> 0 | Y42: =IF(AND(ISNUMBER(Calculated_Ratios!H42),ISNUMBER(H42)),Calculated_Ratios!H42-H42,IF(AND(Calculated_Ratios!H42="",ISBLANK(H42)),0,"MISMATCH")) -> 0 | Z42: =IF(AND(ISNUMBER(Calculated_Ratios!I42),ISNUMBER(I42)),Calculated_Ratios!I42-I42,IF(AND(Calculated_Ratios!I42="",ISBLANK(I42)),0,"MISMATCH")) -> 0 | AA42: =IF(AND(ISNUMBER(Calculated_Ratios!J42),ISNUMBER(J42)),Calculated_Ratios!J42-J42,IF(AND(Calculated_Ratios!J42="",ISBLANK(J42)),0,"MISMATCH")) -> 0 | ... AJ42: =IF(AND(ISNUMBER(Calculated_Ratios!S42),ISNUMBER(S42)),Calculated_Ratios!S42-S42,IF(AND(Calculated_Ratios!S42="",ISBLANK(S42)),0,"MISMATCH")) -> 0
A43: GTBank | B43: 2014 | C43: 2015487 | D43: 4.6357034 | E43: 17.376498 | N43: 4.3934754 | O43: 82.623502 | P43: 14.570039 | Q43: 0 | T43: =IF(AND(ISNUMBER(Calculated_Ratios!C43),ISNUMBER(C43)),Calculated_Ratios!C43-C43,IF(AND(Calculated_Ratios!C43="",ISBLANK(C43)),0,"MISMATCH")) -> 0 | U43: =IF(AND(ISNUMBER(Calculated_Ratios!D43),ISNUMBER(D43)),Calculated_Ratios!D43-D43,IF(AND(Calculated_Ratios!D43="",ISBLANK(D43)),0,"MISMATCH")) -> 0 | V43: =IF(AND(ISNUMBER(Calculated_Ratios!E43),ISNUMBER(E43)),Calculated_Ratios!E43-E43,IF(AND(Calculated_Ratios!E43="",ISBLANK(E43)),0,"MISMATCH")) -> 0 | W43: =IF(AND(ISNUMBER(Calculated_Ratios!F43),ISNUMBER(F43)),Calculated_Ratios!F43-F43,IF(AND(Calculated_Ratios!F43="",ISBLANK(F43)),0,"MISMATCH")) -> 0 | X43: =IF(AND(ISNUMBER(Calculated_Ratios!G43),ISNUMBER(G43)),Calculated_Ratios!G43-G43,IF(AND(Calculated_Ratios!G43="",ISBLANK(G43)),0,"MISMATCH")) -> 0 | Y43: =IF(AND(ISNUMBER(Calculated_Ratios!H43),ISNUMBER(H43)),Calculated_Ratios!H43-H43,IF(AND(Calculated_Ratios!H43="",ISBLANK(H43)),0,"MISMATCH")) -> 0 | Z43: =IF(AND(ISNUMBER(Calculated_Ratios!I43),ISNUMBER(I43)),Calculated_Ratios!I43-I43,IF(AND(Calculated_Ratios!I43="",ISBLANK(I43)),0,"MISMATCH")) -> 0 | AA43: =IF(AND(ISNUMBER(Calculated_Ratios!J43),ISNUMBER(J43)),Calculated_Ratios!J43-J43,IF(AND(Calculated_Ratios!J43="",ISBLANK(J43)),0,"MISMATCH")) -> 0 | ... AJ43: =IF(AND(ISNUMBER(Calculated_Ratios!S43),ISNUMBER(S43)),Calculated_Ratios!S43-S43,IF(AND(Calculated_Ratios!S43="",ISBLANK(S43)),0,"MISMATCH")) -> 0
A44: GTBank | B44: 2015 | C44: 2202118.8 | D44: 4.2826084 | E44: 17.808357 | F44: 0.47359607 | G44: 2.0370464 | H44: 18.169648 | I44: 0.53445682 | N44: 4.1406267 | O44: 82.191643 | P44: 14.638646 | Q44: 0 | R44: 0 | T44: =IF(AND(ISNUMBER(Calculated_Ratios!C44),ISNUMBER(C44)),Calculated_Ratios!C44-C44,IF(AND(Calculated_Ratios!C44="",ISBLANK(C44)),0,"MISMATCH")) -> 0 | U44: =IF(AND(ISNUMBER(Calculated_Ratios!D44),ISNUMBER(D44)),Calculated_Ratios!D44-D44,IF(AND(Calculated_Ratios!D44="",ISBLANK(D44)),0,"MISMATCH")) -> 0 | V44: =IF(AND(ISNUMBER(Calculated_Ratios!E44),ISNUMBER(E44)),Calculated_Ratios!E44-E44,IF(AND(Calculated_Ratios!E44="",ISBLANK(E44)),0,"MISMATCH")) -> 0 | W44: =IF(AND(ISNUMBER(Calculated_Ratios!F44),ISNUMBER(F44)),Calculated_Ratios!F44-F44,IF(AND(Calculated_Ratios!F44="",ISBLANK(F44)),0,"MISMATCH")) -> 0 | X44: =IF(AND(ISNUMBER(Calculated_Ratios!G44),ISNUMBER(G44)),Calculated_Ratios!G44-G44,IF(AND(Calculated_Ratios!G44="",ISBLANK(G44)),0,"MISMATCH")) -> 0 | Y44: =IF(AND(ISNUMBER(Calculated_Ratios!H44),ISNUMBER(H44)),Calculated_Ratios!H44-H44,IF(AND(Calculated_Ratios!H44="",ISBLANK(H44)),0,"MISMATCH")) -> 0 | Z44: =IF(AND(ISNUMBER(Calculated_Ratios!I44),ISNUMBER(I44)),Calculated_Ratios!I44-I44,IF(AND(Calculated_Ratios!I44="",ISBLANK(I44)),0,"MISMATCH")) -> 0 | AA44: =IF(AND(ISNUMBER(Calculated_Ratios!J44),ISNUMBER(J44)),Calculated_Ratios!J44-J44,IF(AND(Calculated_Ratios!J44="",ISBLANK(J44)),0,"MISMATCH")) -> 0 | ... AJ44: =IF(AND(ISNUMBER(Calculated_Ratios!S44),ISNUMBER(S44)),Calculated_Ratios!S44-S44,IF(AND(Calculated_Ratios!S44="",ISBLANK(S44)),0,"MISMATCH")) -> 0
A45: GTBank | B45: 2016 | C45: 2445484.6 | D45: 5.1865708 | E45: 18.249361 | F45: 11.731177 | G45: 4.955998 | H45: 19.790595 | I45: 2.5983659 | N45: 4.8534362 | O45: 81.750639 | P45: 14.77614 | Q45: 1.1641532e-10 | R45: 0 | T45: =IF(AND(ISNUMBER(Calculated_Ratios!C45),ISNUMBER(C45)),Calculated_Ratios!C45-C45,IF(AND(Calculated_Ratios!C45="",ISBLANK(C45)),0,"MISMATCH")) -> 0 | U45: =IF(AND(ISNUMBER(Calculated_Ratios!D45),ISNUMBER(D45)),Calculated_Ratios!D45-D45,IF(AND(Calculated_Ratios!D45="",ISBLANK(D45)),0,"MISMATCH")) -> 0 | V45: =IF(AND(ISNUMBER(Calculated_Ratios!E45),ISNUMBER(E45)),Calculated_Ratios!E45-E45,IF(AND(Calculated_Ratios!E45="",ISBLANK(E45)),0,"MISMATCH")) -> 0 | W45: =IF(AND(ISNUMBER(Calculated_Ratios!F45),ISNUMBER(F45)),Calculated_Ratios!F45-F45,IF(AND(Calculated_Ratios!F45="",ISBLANK(F45)),0,"MISMATCH")) -> 0 | X45: =IF(AND(ISNUMBER(Calculated_Ratios!G45),ISNUMBER(G45)),Calculated_Ratios!G45-G45,IF(AND(Calculated_Ratios!G45="",ISBLANK(G45)),0,"MISMATCH")) -> 0 | Y45: =IF(AND(ISNUMBER(Calculated_Ratios!H45),ISNUMBER(H45)),Calculated_Ratios!H45-H45,IF(AND(Calculated_Ratios!H45="",ISBLANK(H45)),0,"MISMATCH")) -> 0 | Z45: =IF(AND(ISNUMBER(Calculated_Ratios!I45),ISNUMBER(I45)),Calculated_Ratios!I45-I45,IF(AND(Calculated_Ratios!I45="",ISBLANK(I45)),0,"MISMATCH")) -> 0 | AA45: =IF(AND(ISNUMBER(Calculated_Ratios!J45),ISNUMBER(J45)),Calculated_Ratios!J45-J45,IF(AND(Calculated_Ratios!J45="",ISBLANK(J45)),0,"MISMATCH")) -> 0 | ... AJ45: =IF(AND(ISNUMBER(Calculated_Ratios!S45),ISNUMBER(S45)),Calculated_Ratios!S45-S45,IF(AND(Calculated_Ratios!S45="",ISBLANK(S45)),0,"MISMATCH")) -> 0
A46: GTBank | B46: 2017 | C46: 2719134.5 | D46: 5.8374348 | E46: 20.481109 | F46: 12.996684 | G46: 4.5450472 | I46: 0.4240795 | N46: 5.6188211 | O46: 79.518891 | P46: 14.853994 | Q46: 1.1641532e-10 | R46: 0 | T46: =IF(AND(ISNUMBER(Calculated_Ratios!C46),ISNUMBER(C46)),Calculated_Ratios!C46-C46,IF(AND(Calculated_Ratios!C46="",ISBLANK(C46)),0,"MISMATCH")) -> 0 | U46: =IF(AND(ISNUMBER(Calculated_Ratios!D46),ISNUMBER(D46)),Calculated_Ratios!D46-D46,IF(AND(Calculated_Ratios!D46="",ISBLANK(D46)),0,"MISMATCH")) -> 0 | V46: =IF(AND(ISNUMBER(Calculated_Ratios!E46),ISNUMBER(E46)),Calculated_Ratios!E46-E46,IF(AND(Calculated_Ratios!E46="",ISBLANK(E46)),0,"MISMATCH")) -> 0 | W46: =IF(AND(ISNUMBER(Calculated_Ratios!F46),ISNUMBER(F46)),Calculated_Ratios!F46-F46,IF(AND(Calculated_Ratios!F46="",ISBLANK(F46)),0,"MISMATCH")) -> 0 | X46: =IF(AND(ISNUMBER(Calculated_Ratios!G46),ISNUMBER(G46)),Calculated_Ratios!G46-G46,IF(AND(Calculated_Ratios!G46="",ISBLANK(G46)),0,"MISMATCH")) -> 0 | Y46: =IF(AND(ISNUMBER(Calculated_Ratios!H46),ISNUMBER(H46)),Calculated_Ratios!H46-H46,IF(AND(Calculated_Ratios!H46="",ISBLANK(H46)),0,"MISMATCH")) -> 0 | Z46: =IF(AND(ISNUMBER(Calculated_Ratios!I46),ISNUMBER(I46)),Calculated_Ratios!I46-I46,IF(AND(Calculated_Ratios!I46="",ISBLANK(I46)),0,"MISMATCH")) -> 0 | AA46: =IF(AND(ISNUMBER(Calculated_Ratios!J46),ISNUMBER(J46)),Calculated_Ratios!J46-J46,IF(AND(Calculated_Ratios!J46="",ISBLANK(J46)),0,"MISMATCH")) -> 0 | ... AJ46: =IF(AND(ISNUMBER(Calculated_Ratios!S46),ISNUMBER(S46)),Calculated_Ratios!S46-S46,IF(AND(Calculated_Ratios!S46="",ISBLANK(S46)),0,"MISMATCH")) -> 0
A47: GTBank | B47: 2018 | C47: 2768725.2 | D47: 6.0287587 | E47: 18.869611 | F47: 8.1129634 | G47: 7.8501545 | I47: 0.049987047 | N47: 6.1536753 | O47: 81.130389 | P47: 14.813389 | Q47: 5.8207661e-11 | R47: 0 | T47: =IF(AND(ISNUMBER(Calculated_Ratios!C47),ISNUMBER(C47)),Calculated_Ratios!C47-C47,IF(AND(Calculated_Ratios!C47="",ISBLANK(C47)),0,"MISMATCH")) -> 0 | U47: =IF(AND(ISNUMBER(Calculated_Ratios!D47),ISNUMBER(D47)),Calculated_Ratios!D47-D47,IF(AND(Calculated_Ratios!D47="",ISBLANK(D47)),0,"MISMATCH")) -> 0 | V47: =IF(AND(ISNUMBER(Calculated_Ratios!E47),ISNUMBER(E47)),Calculated_Ratios!E47-E47,IF(AND(Calculated_Ratios!E47="",ISBLANK(E47)),0,"MISMATCH")) -> 0 | W47: =IF(AND(ISNUMBER(Calculated_Ratios!F47),ISNUMBER(F47)),Calculated_Ratios!F47-F47,IF(AND(Calculated_Ratios!F47="",ISBLANK(F47)),0,"MISMATCH")) -> 0 | X47: =IF(AND(ISNUMBER(Calculated_Ratios!G47),ISNUMBER(G47)),Calculated_Ratios!G47-G47,IF(AND(Calculated_Ratios!G47="",ISBLANK(G47)),0,"MISMATCH")) -> 0 | Y47: =IF(AND(ISNUMBER(Calculated_Ratios!H47),ISNUMBER(H47)),Calculated_Ratios!H47-H47,IF(AND(Calculated_Ratios!H47="",ISBLANK(H47)),0,"MISMATCH")) -> 0 | Z47: =IF(AND(ISNUMBER(Calculated_Ratios!I47),ISNUMBER(I47)),Calculated_Ratios!I47-I47,IF(AND(Calculated_Ratios!I47="",ISBLANK(I47)),0,"MISMATCH")) -> 0 | AA47: =IF(AND(ISNUMBER(Calculated_Ratios!J47),ISNUMBER(J47)),Calculated_Ratios!J47-J47,IF(AND(Calculated_Ratios!J47="",ISBLANK(J47)),0,"MISMATCH")) -> 0 | ... AJ47: =IF(AND(ISNUMBER(Calculated_Ratios!S47),ISNUMBER(S47)),Calculated_Ratios!S47-S47,IF(AND(Calculated_Ratios!S47="",ISBLANK(S47)),0,"MISMATCH")) -> 0
A48: GTBank | B48: 2019 | C48: 2904885 | D48: 6.0286477 | E48: 19.562189 | F48: 6.8110671 | G48: 4.1446465 | H48: 20.659872 | I48: 0.064004152 | N48: 5.6542212 | O48: 80.437811 | P48: 14.946025 | Q48: -1.1641532e-10 | R48: 0 | T48: =IF(AND(ISNUMBER(Calculated_Ratios!C48),ISNUMBER(C48)),Calculated_Ratios!C48-C48,IF(AND(Calculated_Ratios!C48="",ISBLANK(C48)),0,"MISMATCH")) -> 0 | U48: =IF(AND(ISNUMBER(Calculated_Ratios!D48),ISNUMBER(D48)),Calculated_Ratios!D48-D48,IF(AND(Calculated_Ratios!D48="",ISBLANK(D48)),0,"MISMATCH")) -> 0 | V48: =IF(AND(ISNUMBER(Calculated_Ratios!E48),ISNUMBER(E48)),Calculated_Ratios!E48-E48,IF(AND(Calculated_Ratios!E48="",ISBLANK(E48)),0,"MISMATCH")) -> 0 | W48: =IF(AND(ISNUMBER(Calculated_Ratios!F48),ISNUMBER(F48)),Calculated_Ratios!F48-F48,IF(AND(Calculated_Ratios!F48="",ISBLANK(F48)),0,"MISMATCH")) -> 0 | X48: =IF(AND(ISNUMBER(Calculated_Ratios!G48),ISNUMBER(G48)),Calculated_Ratios!G48-G48,IF(AND(Calculated_Ratios!G48="",ISBLANK(G48)),0,"MISMATCH")) -> 0 | Y48: =IF(AND(ISNUMBER(Calculated_Ratios!H48),ISNUMBER(H48)),Calculated_Ratios!H48-H48,IF(AND(Calculated_Ratios!H48="",ISBLANK(H48)),0,"MISMATCH")) -> 0 | Z48: =IF(AND(ISNUMBER(Calculated_Ratios!I48),ISNUMBER(I48)),Calculated_Ratios!I48-I48,IF(AND(Calculated_Ratios!I48="",ISBLANK(I48)),0,"MISMATCH")) -> 0 | AA48: =IF(AND(ISNUMBER(Calculated_Ratios!J48),ISNUMBER(J48)),Calculated_Ratios!J48-J48,IF(AND(Calculated_Ratios!J48="",ISBLANK(J48)),0,"MISMATCH")) -> 0 | ... AJ48: =IF(AND(ISNUMBER(Calculated_Ratios!S48),ISNUMBER(S48)),Calculated_Ratios!S48-S48,IF(AND(Calculated_Ratios!S48="",ISBLANK(S48)),0,"MISMATCH")) -> 0
A49: GTBank | B49: 2020 | C49: 3579396 | D49: 4.9781694 | E49: 17.293906 | F49: 9.1577864 | G49: 4.2701522 | H49: 19.55 | I49: 0.2948952 | N49: 4.3872088 | O49: 82.706094 | P49: 15.217074 | Q49: -1.1641532e-10 | R49: 0 | T49: =IF(AND(ISNUMBER(Calculated_Ratios!C49),ISNUMBER(C49)),Calculated_Ratios!C49-C49,IF(AND(Calculated_Ratios!C49="",ISBLANK(C49)),0,"MISMATCH")) -> 0 | U49: =IF(AND(ISNUMBER(Calculated_Ratios!D49),ISNUMBER(D49)),Calculated_Ratios!D49-D49,IF(AND(Calculated_Ratios!D49="",ISBLANK(D49)),0,"MISMATCH")) -> 0 | V49: =IF(AND(ISNUMBER(Calculated_Ratios!E49),ISNUMBER(E49)),Calculated_Ratios!E49-E49,IF(AND(Calculated_Ratios!E49="",ISBLANK(E49)),0,"MISMATCH")) -> 0 | W49: =IF(AND(ISNUMBER(Calculated_Ratios!F49),ISNUMBER(F49)),Calculated_Ratios!F49-F49,IF(AND(Calculated_Ratios!F49="",ISBLANK(F49)),0,"MISMATCH")) -> 0 | X49: =IF(AND(ISNUMBER(Calculated_Ratios!G49),ISNUMBER(G49)),Calculated_Ratios!G49-G49,IF(AND(Calculated_Ratios!G49="",ISBLANK(G49)),0,"MISMATCH")) -> 0 | Y49: =IF(AND(ISNUMBER(Calculated_Ratios!H49),ISNUMBER(H49)),Calculated_Ratios!H49-H49,IF(AND(Calculated_Ratios!H49="",ISBLANK(H49)),0,"MISMATCH")) -> 0 | Z49: =IF(AND(ISNUMBER(Calculated_Ratios!I49),ISNUMBER(I49)),Calculated_Ratios!I49-I49,IF(AND(Calculated_Ratios!I49="",ISBLANK(I49)),0,"MISMATCH")) -> 0 | AA49: =IF(AND(ISNUMBER(Calculated_Ratios!J49),ISNUMBER(J49)),Calculated_Ratios!J49-J49,IF(AND(Calculated_Ratios!J49="",ISBLANK(J49)),0,"MISMATCH")) -> 0 | ... AJ49: =IF(AND(ISNUMBER(Calculated_Ratios!S49),ISNUMBER(S49)),Calculated_Ratios!S49-S49,IF(AND(Calculated_Ratios!S49="",ISBLANK(S49)),0,"MISMATCH")) -> 0
A50: GTBank | B50: 2021 | C50: 4209288.4 | D50: 3.4728927 | E50: 17.14092 | F50: 8.6634779 | N50: 3.3551287 | O50: 82.85908 | P50: 15.287302 | Q50: -3.4924597e-10 | T50: =IF(AND(ISNUMBER(Calculated_Ratios!C50),ISNUMBER(C50)),Calculated_Ratios!C50-C50,IF(AND(Calculated_Ratios!C50="",ISBLANK(C50)),0,"MISMATCH")) -> 0 | U50: =IF(AND(ISNUMBER(Calculated_Ratios!D50),ISNUMBER(D50)),Calculated_Ratios!D50-D50,IF(AND(Calculated_Ratios!D50="",ISBLANK(D50)),0,"MISMATCH")) -> 0 | V50: =IF(AND(ISNUMBER(Calculated_Ratios!E50),ISNUMBER(E50)),Calculated_Ratios!E50-E50,IF(AND(Calculated_Ratios!E50="",ISBLANK(E50)),0,"MISMATCH")) -> 0 | W50: =IF(AND(ISNUMBER(Calculated_Ratios!F50),ISNUMBER(F50)),Calculated_Ratios!F50-F50,IF(AND(Calculated_Ratios!F50="",ISBLANK(F50)),0,"MISMATCH")) -> 0 | X50: =IF(AND(ISNUMBER(Calculated_Ratios!G50),ISNUMBER(G50)),Calculated_Ratios!G50-G50,IF(AND(Calculated_Ratios!G50="",ISBLANK(G50)),0,"MISMATCH")) -> 0 | Y50: =IF(AND(ISNUMBER(Calculated_Ratios!H50),ISNUMBER(H50)),Calculated_Ratios!H50-H50,IF(AND(Calculated_Ratios!H50="",ISBLANK(H50)),0,"MISMATCH")) -> 0 | Z50: =IF(AND(ISNUMBER(Calculated_Ratios!I50),ISNUMBER(I50)),Calculated_Ratios!I50-I50,IF(AND(Calculated_Ratios!I50="",ISBLANK(I50)),0,"MISMATCH")) -> 0 | AA50: =IF(AND(ISNUMBER(Calculated_Ratios!J50),ISNUMBER(J50)),Calculated_Ratios!J50-J50,IF(AND(Calculated_Ratios!J50="",ISBLANK(J50)),0,"MISMATCH")) -> 0 | ... AJ50: =IF(AND(ISNUMBER(Calculated_Ratios!S50),ISNUMBER(S50)),Calculated_Ratios!S50-S50,IF(AND(Calculated_Ratios!S50="",ISBLANK(S50)),0,"MISMATCH")) -> 0
A51: GTBank | B51: 2022 | C51: 4782805 | D51: 3.037887 | E51: 15.281569 | F51: 14.036982 | N51: 2.7895568 | O51: 84.718431 | P51: 15.465817 | Q51: -4.6566129e-10 | T51: =IF(AND(ISNUMBER(Calculated_Ratios!C51),ISNUMBER(C51)),Calculated_Ratios!C51-C51,IF(AND(Calculated_Ratios!C51="",ISBLANK(C51)),0,"MISMATCH")) -> 0 | U51: =IF(AND(ISNUMBER(Calculated_Ratios!D51),ISNUMBER(D51)),Calculated_Ratios!D51-D51,IF(AND(Calculated_Ratios!D51="",ISBLANK(D51)),0,"MISMATCH")) -> 0 | V51: =IF(AND(ISNUMBER(Calculated_Ratios!E51),ISNUMBER(E51)),Calculated_Ratios!E51-E51,IF(AND(Calculated_Ratios!E51="",ISBLANK(E51)),0,"MISMATCH")) -> 0 | W51: =IF(AND(ISNUMBER(Calculated_Ratios!F51),ISNUMBER(F51)),Calculated_Ratios!F51-F51,IF(AND(Calculated_Ratios!F51="",ISBLANK(F51)),0,"MISMATCH")) -> 0 | X51: =IF(AND(ISNUMBER(Calculated_Ratios!G51),ISNUMBER(G51)),Calculated_Ratios!G51-G51,IF(AND(Calculated_Ratios!G51="",ISBLANK(G51)),0,"MISMATCH")) -> 0 | Y51: =IF(AND(ISNUMBER(Calculated_Ratios!H51),ISNUMBER(H51)),Calculated_Ratios!H51-H51,IF(AND(Calculated_Ratios!H51="",ISBLANK(H51)),0,"MISMATCH")) -> 0 | Z51: =IF(AND(ISNUMBER(Calculated_Ratios!I51),ISNUMBER(I51)),Calculated_Ratios!I51-I51,IF(AND(Calculated_Ratios!I51="",ISBLANK(I51)),0,"MISMATCH")) -> 0 | AA51: =IF(AND(ISNUMBER(Calculated_Ratios!J51),ISNUMBER(J51)),Calculated_Ratios!J51-J51,IF(AND(Calculated_Ratios!J51="",ISBLANK(J51)),0,"MISMATCH")) -> 0 | ... AJ51: =IF(AND(ISNUMBER(Calculated_Ratios!S51),ISNUMBER(S51)),Calculated_Ratios!S51-S51,IF(AND(Calculated_Ratios!S51="",ISBLANK(S51)),0,"MISMATCH")) -> 0
A52: Stanbic | B52: 2013 | C52: 687785 | D52: 1.4726986 | E52: 9.7338298 | I52: 0.38776653 | N52: 1.3969108 | O52: 90.26617 | P52: 13.494065 | Q52: 0 | T52: =IF(AND(ISNUMBER(Calculated_Ratios!C52),ISNUMBER(C52)),Calculated_Ratios!C52-C52,IF(AND(Calculated_Ratios!C52="",ISBLANK(C52)),0,"MISMATCH")) -> 0 | U52: =IF(AND(ISNUMBER(Calculated_Ratios!D52),ISNUMBER(D52)),Calculated_Ratios!D52-D52,IF(AND(Calculated_Ratios!D52="",ISBLANK(D52)),0,"MISMATCH")) -> 0 | V52: =IF(AND(ISNUMBER(Calculated_Ratios!E52),ISNUMBER(E52)),Calculated_Ratios!E52-E52,IF(AND(Calculated_Ratios!E52="",ISBLANK(E52)),0,"MISMATCH")) -> 0 | W52: =IF(AND(ISNUMBER(Calculated_Ratios!F52),ISNUMBER(F52)),Calculated_Ratios!F52-F52,IF(AND(Calculated_Ratios!F52="",ISBLANK(F52)),0,"MISMATCH")) -> 0 | X52: =IF(AND(ISNUMBER(Calculated_Ratios!G52),ISNUMBER(G52)),Calculated_Ratios!G52-G52,IF(AND(Calculated_Ratios!G52="",ISBLANK(G52)),0,"MISMATCH")) -> 0 | Y52: =IF(AND(ISNUMBER(Calculated_Ratios!H52),ISNUMBER(H52)),Calculated_Ratios!H52-H52,IF(AND(Calculated_Ratios!H52="",ISBLANK(H52)),0,"MISMATCH")) -> 0 | Z52: =IF(AND(ISNUMBER(Calculated_Ratios!I52),ISNUMBER(I52)),Calculated_Ratios!I52-I52,IF(AND(Calculated_Ratios!I52="",ISBLANK(I52)),0,"MISMATCH")) -> 0 | AA52: =IF(AND(ISNUMBER(Calculated_Ratios!J52),ISNUMBER(J52)),Calculated_Ratios!J52-J52,IF(AND(Calculated_Ratios!J52="",ISBLANK(J52)),0,"MISMATCH")) -> 0 | ... AJ52: =IF(AND(ISNUMBER(Calculated_Ratios!S52),ISNUMBER(S52)),Calculated_Ratios!S52-S52,IF(AND(Calculated_Ratios!S52="",ISBLANK(S52)),0,"MISMATCH")) -> 0
A53: Stanbic | B53: 2014 | C53: 818076 | D53: 2.3782631 | E53: 8.9809363 | I53: 0.39323975 | N53: 2.1355532 | O53: 91.019064 | P53: 13.722355 | Q53: 0 | T53: =IF(AND(ISNUMBER(Calculated_Ratios!C53),ISNUMBER(C53)),Calculated_Ratios!C53-C53,IF(AND(Calculated_Ratios!C53="",ISBLANK(C53)),0,"MISMATCH")) -> 0 | U53: =IF(AND(ISNUMBER(Calculated_Ratios!D53),ISNUMBER(D53)),Calculated_Ratios!D53-D53,IF(AND(Calculated_Ratios!D53="",ISBLANK(D53)),0,"MISMATCH")) -> 0 | V53: =IF(AND(ISNUMBER(Calculated_Ratios!E53),ISNUMBER(E53)),Calculated_Ratios!E53-E53,IF(AND(Calculated_Ratios!E53="",ISBLANK(E53)),0,"MISMATCH")) -> 0 | W53: =IF(AND(ISNUMBER(Calculated_Ratios!F53),ISNUMBER(F53)),Calculated_Ratios!F53-F53,IF(AND(Calculated_Ratios!F53="",ISBLANK(F53)),0,"MISMATCH")) -> 0 | X53: =IF(AND(ISNUMBER(Calculated_Ratios!G53),ISNUMBER(G53)),Calculated_Ratios!G53-G53,IF(AND(Calculated_Ratios!G53="",ISBLANK(G53)),0,"MISMATCH")) -> 0 | Y53: =IF(AND(ISNUMBER(Calculated_Ratios!H53),ISNUMBER(H53)),Calculated_Ratios!H53-H53,IF(AND(Calculated_Ratios!H53="",ISBLANK(H53)),0,"MISMATCH")) -> 0 | Z53: =IF(AND(ISNUMBER(Calculated_Ratios!I53),ISNUMBER(I53)),Calculated_Ratios!I53-I53,IF(AND(Calculated_Ratios!I53="",ISBLANK(I53)),0,"MISMATCH")) -> 0 | AA53: =IF(AND(ISNUMBER(Calculated_Ratios!J53),ISNUMBER(J53)),Calculated_Ratios!J53-J53,IF(AND(Calculated_Ratios!J53="",ISBLANK(J53)),0,"MISMATCH")) -> 0 | ... AJ53: =IF(AND(ISNUMBER(Calculated_Ratios!S53),ISNUMBER(S53)),Calculated_Ratios!S53-S53,IF(AND(Calculated_Ratios!S53="",ISBLANK(S53)),0,"MISMATCH")) -> 0
A54: Stanbic | B54: 2015 | C54: 899504.5 | D54: 0.69282588 | E54: 10.657886 | I54: 1.6599139 | N54: 0.69976869 | O54: 89.342114 | P54: 13.699628 | Q54: 0 | T54: =IF(AND(ISNUMBER(Calculated_Ratios!C54),ISNUMBER(C54)),Calculated_Ratios!C54-C54,IF(AND(Calculated_Ratios!C54="",ISBLANK(C54)),0,"MISMATCH")) -> 0 | U54: =IF(AND(ISNUMBER(Calculated_Ratios!D54),ISNUMBER(D54)),Calculated_Ratios!D54-D54,IF(AND(Calculated_Ratios!D54="",ISBLANK(D54)),0,"MISMATCH")) -> 0 | V54: =IF(AND(ISNUMBER(Calculated_Ratios!E54),ISNUMBER(E54)),Calculated_Ratios!E54-E54,IF(AND(Calculated_Ratios!E54="",ISBLANK(E54)),0,"MISMATCH")) -> 0 | W54: =IF(AND(ISNUMBER(Calculated_Ratios!F54),ISNUMBER(F54)),Calculated_Ratios!F54-F54,IF(AND(Calculated_Ratios!F54="",ISBLANK(F54)),0,"MISMATCH")) -> 0 | X54: =IF(AND(ISNUMBER(Calculated_Ratios!G54),ISNUMBER(G54)),Calculated_Ratios!G54-G54,IF(AND(Calculated_Ratios!G54="",ISBLANK(G54)),0,"MISMATCH")) -> 0 | Y54: =IF(AND(ISNUMBER(Calculated_Ratios!H54),ISNUMBER(H54)),Calculated_Ratios!H54-H54,IF(AND(Calculated_Ratios!H54="",ISBLANK(H54)),0,"MISMATCH")) -> 0 | Z54: =IF(AND(ISNUMBER(Calculated_Ratios!I54),ISNUMBER(I54)),Calculated_Ratios!I54-I54,IF(AND(Calculated_Ratios!I54="",ISBLANK(I54)),0,"MISMATCH")) -> 0 | AA54: =IF(AND(ISNUMBER(Calculated_Ratios!J54),ISNUMBER(J54)),Calculated_Ratios!J54-J54,IF(AND(Calculated_Ratios!J54="",ISBLANK(J54)),0,"MISMATCH")) -> 0 | ... AJ54: =IF(AND(ISNUMBER(Calculated_Ratios!S54),ISNUMBER(S54)),Calculated_Ratios!S54-S54,IF(AND(Calculated_Ratios!S54="",ISBLANK(S54)),0,"MISMATCH")) -> 0
A55: Stanbic | B55: 2016 | C55: 942169.5 | D55: 1.5952544 | E55: 11.000253 | I55: 2.1018511 | N55: 1.5124391 | O55: 88.999747 | P55: 13.80925 | Q55: 0 | T55: =IF(AND(ISNUMBER(Calculated_Ratios!C55),ISNUMBER(C55)),Calculated_Ratios!C55-C55,IF(AND(Calculated_Ratios!C55="",ISBLANK(C55)),0,"MISMATCH")) -> 0 | U55: =IF(AND(ISNUMBER(Calculated_Ratios!D55),ISNUMBER(D55)),Calculated_Ratios!D55-D55,IF(AND(Calculated_Ratios!D55="",ISBLANK(D55)),0,"MISMATCH")) -> 0 | V55: =IF(AND(ISNUMBER(Calculated_Ratios!E55),ISNUMBER(E55)),Calculated_Ratios!E55-E55,IF(AND(Calculated_Ratios!E55="",ISBLANK(E55)),0,"MISMATCH")) -> 0 | W55: =IF(AND(ISNUMBER(Calculated_Ratios!F55),ISNUMBER(F55)),Calculated_Ratios!F55-F55,IF(AND(Calculated_Ratios!F55="",ISBLANK(F55)),0,"MISMATCH")) -> 0 | X55: =IF(AND(ISNUMBER(Calculated_Ratios!G55),ISNUMBER(G55)),Calculated_Ratios!G55-G55,IF(AND(Calculated_Ratios!G55="",ISBLANK(G55)),0,"MISMATCH")) -> 0 | Y55: =IF(AND(ISNUMBER(Calculated_Ratios!H55),ISNUMBER(H55)),Calculated_Ratios!H55-H55,IF(AND(Calculated_Ratios!H55="",ISBLANK(H55)),0,"MISMATCH")) -> 0 | Z55: =IF(AND(ISNUMBER(Calculated_Ratios!I55),ISNUMBER(I55)),Calculated_Ratios!I55-I55,IF(AND(Calculated_Ratios!I55="",ISBLANK(I55)),0,"MISMATCH")) -> 0 | AA55: =IF(AND(ISNUMBER(Calculated_Ratios!J55),ISNUMBER(J55)),Calculated_Ratios!J55-J55,IF(AND(Calculated_Ratios!J55="",ISBLANK(J55)),0,"MISMATCH")) -> 0 | ... AJ55: =IF(AND(ISNUMBER(Calculated_Ratios!S55),ISNUMBER(S55)),Calculated_Ratios!S55-S55,IF(AND(Calculated_Ratios!S55="",ISBLANK(S55)),0,"MISMATCH")) -> 0
A56: Stanbic | B56: 2017 | C56: 1163214 | D56: 2.4795094 | E56: 10.407686 | I56: 2.1988215 | N56: 2.1642283 | O56: 89.592314 | P56: 14.102694 | Q56: 0 | T56: =IF(AND(ISNUMBER(Calculated_Ratios!C56),ISNUMBER(C56)),Calculated_Ratios!C56-C56,IF(AND(Calculated_Ratios!C56="",ISBLANK(C56)),0,"MISMATCH")) -> 0 | U56: =IF(AND(ISNUMBER(Calculated_Ratios!D56),ISNUMBER(D56)),Calculated_Ratios!D56-D56,IF(AND(Calculated_Ratios!D56="",ISBLANK(D56)),0,"MISMATCH")) -> 0 | V56: =IF(AND(ISNUMBER(Calculated_Ratios!E56),ISNUMBER(E56)),Calculated_Ratios!E56-E56,IF(AND(Calculated_Ratios!E56="",ISBLANK(E56)),0,"MISMATCH")) -> 0 | W56: =IF(AND(ISNUMBER(Calculated_Ratios!F56),ISNUMBER(F56)),Calculated_Ratios!F56-F56,IF(AND(Calculated_Ratios!F56="",ISBLANK(F56)),0,"MISMATCH")) -> 0 | X56: =IF(AND(ISNUMBER(Calculated_Ratios!G56),ISNUMBER(G56)),Calculated_Ratios!G56-G56,IF(AND(Calculated_Ratios!G56="",ISBLANK(G56)),0,"MISMATCH")) -> 0 | Y56: =IF(AND(ISNUMBER(Calculated_Ratios!H56),ISNUMBER(H56)),Calculated_Ratios!H56-H56,IF(AND(Calculated_Ratios!H56="",ISBLANK(H56)),0,"MISMATCH")) -> 0 | Z56: =IF(AND(ISNUMBER(Calculated_Ratios!I56),ISNUMBER(I56)),Calculated_Ratios!I56-I56,IF(AND(Calculated_Ratios!I56="",ISBLANK(I56)),0,"MISMATCH")) -> 0 | AA56: =IF(AND(ISNUMBER(Calculated_Ratios!J56),ISNUMBER(J56)),Calculated_Ratios!J56-J56,IF(AND(Calculated_Ratios!J56="",ISBLANK(J56)),0,"MISMATCH")) -> 0 | ... AJ56: =IF(AND(ISNUMBER(Calculated_Ratios!S56),ISNUMBER(S56)),Calculated_Ratios!S56-S56,IF(AND(Calculated_Ratios!S56="",ISBLANK(S56)),0,"MISMATCH")) -> 0
A57: Stanbic | B57: 2018 | C57: 1465984 | D57: 3.4046756 | E57: 10.651339 | I57: -0.20382214 | N57: 3.1209727 | O57: 89.348661 | P57: 14.285042 | Q57: 0 | T57: =IF(AND(ISNUMBER(Calculated_Ratios!C57),ISNUMBER(C57)),Calculated_Ratios!C57-C57,IF(AND(Calculated_Ratios!C57="",ISBLANK(C57)),0,"MISMATCH")) -> 0 | U57: =IF(AND(ISNUMBER(Calculated_Ratios!D57),ISNUMBER(D57)),Calculated_Ratios!D57-D57,IF(AND(Calculated_Ratios!D57="",ISBLANK(D57)),0,"MISMATCH")) -> 0 | V57: =IF(AND(ISNUMBER(Calculated_Ratios!E57),ISNUMBER(E57)),Calculated_Ratios!E57-E57,IF(AND(Calculated_Ratios!E57="",ISBLANK(E57)),0,"MISMATCH")) -> 0 | W57: =IF(AND(ISNUMBER(Calculated_Ratios!F57),ISNUMBER(F57)),Calculated_Ratios!F57-F57,IF(AND(Calculated_Ratios!F57="",ISBLANK(F57)),0,"MISMATCH")) -> 0 | X57: =IF(AND(ISNUMBER(Calculated_Ratios!G57),ISNUMBER(G57)),Calculated_Ratios!G57-G57,IF(AND(Calculated_Ratios!G57="",ISBLANK(G57)),0,"MISMATCH")) -> 0 | Y57: =IF(AND(ISNUMBER(Calculated_Ratios!H57),ISNUMBER(H57)),Calculated_Ratios!H57-H57,IF(AND(Calculated_Ratios!H57="",ISBLANK(H57)),0,"MISMATCH")) -> 0 | Z57: =IF(AND(ISNUMBER(Calculated_Ratios!I57),ISNUMBER(I57)),Calculated_Ratios!I57-I57,IF(AND(Calculated_Ratios!I57="",ISBLANK(I57)),0,"MISMATCH")) -> 0 | AA57: =IF(AND(ISNUMBER(Calculated_Ratios!J57),ISNUMBER(J57)),Calculated_Ratios!J57-J57,IF(AND(Calculated_Ratios!J57="",ISBLANK(J57)),0,"MISMATCH")) -> 0 | ... AJ57: =IF(AND(ISNUMBER(Calculated_Ratios!S57),ISNUMBER(S57)),Calculated_Ratios!S57-S57,IF(AND(Calculated_Ratios!S57="",ISBLANK(S57)),0,"MISMATCH")) -> 0
A58: Stanbic | B58: 2019 | C58: 1695782.5 | D58: 3.0833553 | E58: 11.233485 | I58: 0.098125791 | N58: 2.9172804 | O58: 88.766515 | P58: 14.399021 | Q58: 0 | T58: =IF(AND(ISNUMBER(Calculated_Ratios!C58),ISNUMBER(C58)),Calculated_Ratios!C58-C58,IF(AND(Calculated_Ratios!C58="",ISBLANK(C58)),0,"MISMATCH")) -> 0 | U58: =IF(AND(ISNUMBER(Calculated_Ratios!D58),ISNUMBER(D58)),Calculated_Ratios!D58-D58,IF(AND(Calculated_Ratios!D58="",ISBLANK(D58)),0,"MISMATCH")) -> 0 | V58: =IF(AND(ISNUMBER(Calculated_Ratios!E58),ISNUMBER(E58)),Calculated_Ratios!E58-E58,IF(AND(Calculated_Ratios!E58="",ISBLANK(E58)),0,"MISMATCH")) -> 0 | W58: =IF(AND(ISNUMBER(Calculated_Ratios!F58),ISNUMBER(F58)),Calculated_Ratios!F58-F58,IF(AND(Calculated_Ratios!F58="",ISBLANK(F58)),0,"MISMATCH")) -> 0 | X58: =IF(AND(ISNUMBER(Calculated_Ratios!G58),ISNUMBER(G58)),Calculated_Ratios!G58-G58,IF(AND(Calculated_Ratios!G58="",ISBLANK(G58)),0,"MISMATCH")) -> 0 | Y58: =IF(AND(ISNUMBER(Calculated_Ratios!H58),ISNUMBER(H58)),Calculated_Ratios!H58-H58,IF(AND(Calculated_Ratios!H58="",ISBLANK(H58)),0,"MISMATCH")) -> 0 | Z58: =IF(AND(ISNUMBER(Calculated_Ratios!I58),ISNUMBER(I58)),Calculated_Ratios!I58-I58,IF(AND(Calculated_Ratios!I58="",ISBLANK(I58)),0,"MISMATCH")) -> 0 | AA58: =IF(AND(ISNUMBER(Calculated_Ratios!J58),ISNUMBER(J58)),Calculated_Ratios!J58-J58,IF(AND(Calculated_Ratios!J58="",ISBLANK(J58)),0,"MISMATCH")) -> 0 | ... AJ58: =IF(AND(ISNUMBER(Calculated_Ratios!S58),ISNUMBER(S58)),Calculated_Ratios!S58-S58,IF(AND(Calculated_Ratios!S58="",ISBLANK(S58)),0,"MISMATCH")) -> 0
A59: Stanbic | B59: 2020 | E59: 10.21458 | G59: 4.6014601 | H59: 19.41501 | N59: 2.5097169 | O59: 89.78542 | P59: 14.678547 | Q59: 0 | R59: 0 | T59: =IF(AND(ISNUMBER(Calculated_Ratios!C59),ISNUMBER(C59)),Calculated_Ratios!C59-C59,IF(AND(Calculated_Ratios!C59="",ISBLANK(C59)),0,"MISMATCH")) -> 0 | U59: =IF(AND(ISNUMBER(Calculated_Ratios!D59),ISNUMBER(D59)),Calculated_Ratios!D59-D59,IF(AND(Calculated_Ratios!D59="",ISBLANK(D59)),0,"MISMATCH")) -> 0 | V59: =IF(AND(ISNUMBER(Calculated_Ratios!E59),ISNUMBER(E59)),Calculated_Ratios!E59-E59,IF(AND(Calculated_Ratios!E59="",ISBLANK(E59)),0,"MISMATCH")) -> 0 | W59: =IF(AND(ISNUMBER(Calculated_Ratios!F59),ISNUMBER(F59)),Calculated_Ratios!F59-F59,IF(AND(Calculated_Ratios!F59="",ISBLANK(F59)),0,"MISMATCH")) -> 0 | X59: =IF(AND(ISNUMBER(Calculated_Ratios!G59),ISNUMBER(G59)),Calculated_Ratios!G59-G59,IF(AND(Calculated_Ratios!G59="",ISBLANK(G59)),0,"MISMATCH")) -> 0 | Y59: =IF(AND(ISNUMBER(Calculated_Ratios!H59),ISNUMBER(H59)),Calculated_Ratios!H59-H59,IF(AND(Calculated_Ratios!H59="",ISBLANK(H59)),0,"MISMATCH")) -> 0 | Z59: =IF(AND(ISNUMBER(Calculated_Ratios!I59),ISNUMBER(I59)),Calculated_Ratios!I59-I59,IF(AND(Calculated_Ratios!I59="",ISBLANK(I59)),0,"MISMATCH")) -> 0 | AA59: =IF(AND(ISNUMBER(Calculated_Ratios!J59),ISNUMBER(J59)),Calculated_Ratios!J59-J59,IF(AND(Calculated_Ratios!J59="",ISBLANK(J59)),0,"MISMATCH")) -> 0 | ... AJ59: =IF(AND(ISNUMBER(Calculated_Ratios!S59),ISNUMBER(S59)),Calculated_Ratios!S59-S59,IF(AND(Calculated_Ratios!S59="",ISBLANK(S59)),0,"MISMATCH")) -> 0
A60: Stanbic | B60: 2021 | C60: 2492217 | D60: 1.1864938 | E60: 9.6314698 | F60: 2.2378067 | G60: 2.6647038 | H60: 16.141502 | I60: -0.0484709 | N60: 1.1311789 | O60: 90.36853 | P60: 14.776425 | Q60: 0 | R60: 0 | T60: =IF(AND(ISNUMBER(Calculated_Ratios!C60),ISNUMBER(C60)),Calculated_Ratios!C60-C60,IF(AND(Calculated_Ratios!C60="",ISBLANK(C60)),0,"MISMATCH")) -> 0 | U60: =IF(AND(ISNUMBER(Calculated_Ratios!D60),ISNUMBER(D60)),Calculated_Ratios!D60-D60,IF(AND(Calculated_Ratios!D60="",ISBLANK(D60)),0,"MISMATCH")) -> 0 | V60: =IF(AND(ISNUMBER(Calculated_Ratios!E60),ISNUMBER(E60)),Calculated_Ratios!E60-E60,IF(AND(Calculated_Ratios!E60="",ISBLANK(E60)),0,"MISMATCH")) -> 0 | W60: =IF(AND(ISNUMBER(Calculated_Ratios!F60),ISNUMBER(F60)),Calculated_Ratios!F60-F60,IF(AND(Calculated_Ratios!F60="",ISBLANK(F60)),0,"MISMATCH")) -> 0 | X60: =IF(AND(ISNUMBER(Calculated_Ratios!G60),ISNUMBER(G60)),Calculated_Ratios!G60-G60,IF(AND(Calculated_Ratios!G60="",ISBLANK(G60)),0,"MISMATCH")) -> 0 | Y60: =IF(AND(ISNUMBER(Calculated_Ratios!H60),ISNUMBER(H60)),Calculated_Ratios!H60-H60,IF(AND(Calculated_Ratios!H60="",ISBLANK(H60)),0,"MISMATCH")) -> 0 | Z60: =IF(AND(ISNUMBER(Calculated_Ratios!I60),ISNUMBER(I60)),Calculated_Ratios!I60-I60,IF(AND(Calculated_Ratios!I60="",ISBLANK(I60)),0,"MISMATCH")) -> 0 | AA60: =IF(AND(ISNUMBER(Calculated_Ratios!J60),ISNUMBER(J60)),Calculated_Ratios!J60-J60,IF(AND(Calculated_Ratios!J60="",ISBLANK(J60)),0,"MISMATCH")) -> 0 | ... AJ60: =IF(AND(ISNUMBER(Calculated_Ratios!S60),ISNUMBER(S60)),Calculated_Ratios!S60-S60,IF(AND(Calculated_Ratios!S60="",ISBLANK(S60)),0,"MISMATCH")) -> 0
A61: Stanbic | B61: 2022 | C61: 2734298 | D61: 2.0169711 | E61: 9.7777586 | F61: -5.2807338 | G61: 2.6982826 | H61: 18.40935 | I61: 0.37110074 | N61: 1.932031 | O61: 90.222241 | P61: 14.86441 | Q61: 0 | R61: 0 | T61: =IF(AND(ISNUMBER(Calculated_Ratios!C61),ISNUMBER(C61)),Calculated_Ratios!C61-C61,IF(AND(Calculated_Ratios!C61="",ISBLANK(C61)),0,"MISMATCH")) -> 0 | U61: =IF(AND(ISNUMBER(Calculated_Ratios!D61),ISNUMBER(D61)),Calculated_Ratios!D61-D61,IF(AND(Calculated_Ratios!D61="",ISBLANK(D61)),0,"MISMATCH")) -> 0 | V61: =IF(AND(ISNUMBER(Calculated_Ratios!E61),ISNUMBER(E61)),Calculated_Ratios!E61-E61,IF(AND(Calculated_Ratios!E61="",ISBLANK(E61)),0,"MISMATCH")) -> 0 | W61: =IF(AND(ISNUMBER(Calculated_Ratios!F61),ISNUMBER(F61)),Calculated_Ratios!F61-F61,IF(AND(Calculated_Ratios!F61="",ISBLANK(F61)),0,"MISMATCH")) -> 0 | X61: =IF(AND(ISNUMBER(Calculated_Ratios!G61),ISNUMBER(G61)),Calculated_Ratios!G61-G61,IF(AND(Calculated_Ratios!G61="",ISBLANK(G61)),0,"MISMATCH")) -> 0 | Y61: =IF(AND(ISNUMBER(Calculated_Ratios!H61),ISNUMBER(H61)),Calculated_Ratios!H61-H61,IF(AND(Calculated_Ratios!H61="",ISBLANK(H61)),0,"MISMATCH")) -> 0 | Z61: =IF(AND(ISNUMBER(Calculated_Ratios!I61),ISNUMBER(I61)),Calculated_Ratios!I61-I61,IF(AND(Calculated_Ratios!I61="",ISBLANK(I61)),0,"MISMATCH")) -> 0 | AA61: =IF(AND(ISNUMBER(Calculated_Ratios!J61),ISNUMBER(J61)),Calculated_Ratios!J61-J61,IF(AND(Calculated_Ratios!J61="",ISBLANK(J61)),0,"MISMATCH")) -> 0 | ... AJ61: =IF(AND(ISNUMBER(Calculated_Ratios!S61),ISNUMBER(S61)),Calculated_Ratios!S61-S61,IF(AND(Calculated_Ratios!S61="",ISBLANK(S61)),0,"MISMATCH")) -> 0
A62: Sterling | B62: 2013 | E62: 8.965548 | G62: 2.1058397 | N62: 1.169101 | O62: 91.034452 | P62: 13.469913 | Q62: -5.0931703e-11 | T62: =IF(AND(ISNUMBER(Calculated_Ratios!C62),ISNUMBER(C62)),Calculated_Ratios!C62-C62,IF(AND(Calculated_Ratios!C62="",ISBLANK(C62)),0,"MISMATCH")) -> 0 | U62: =IF(AND(ISNUMBER(Calculated_Ratios!D62),ISNUMBER(D62)),Calculated_Ratios!D62-D62,IF(AND(Calculated_Ratios!D62="",ISBLANK(D62)),0,"MISMATCH")) -> 0 | V62: =IF(AND(ISNUMBER(Calculated_Ratios!E62),ISNUMBER(E62)),Calculated_Ratios!E62-E62,IF(AND(Calculated_Ratios!E62="",ISBLANK(E62)),0,"MISMATCH")) -> 0 | W62: =IF(AND(ISNUMBER(Calculated_Ratios!F62),ISNUMBER(F62)),Calculated_Ratios!F62-F62,IF(AND(Calculated_Ratios!F62="",ISBLANK(F62)),0,"MISMATCH")) -> 0 | X62: =IF(AND(ISNUMBER(Calculated_Ratios!G62),ISNUMBER(G62)),Calculated_Ratios!G62-G62,IF(AND(Calculated_Ratios!G62="",ISBLANK(G62)),0,"MISMATCH")) -> 0 | Y62: =IF(AND(ISNUMBER(Calculated_Ratios!H62),ISNUMBER(H62)),Calculated_Ratios!H62-H62,IF(AND(Calculated_Ratios!H62="",ISBLANK(H62)),0,"MISMATCH")) -> 0 | Z62: =IF(AND(ISNUMBER(Calculated_Ratios!I62),ISNUMBER(I62)),Calculated_Ratios!I62-I62,IF(AND(Calculated_Ratios!I62="",ISBLANK(I62)),0,"MISMATCH")) -> 0 | AA62: =IF(AND(ISNUMBER(Calculated_Ratios!J62),ISNUMBER(J62)),Calculated_Ratios!J62-J62,IF(AND(Calculated_Ratios!J62="",ISBLANK(J62)),0,"MISMATCH")) -> 0 | ... AJ62: =IF(AND(ISNUMBER(Calculated_Ratios!S62),ISNUMBER(S62)),Calculated_Ratios!S62-S62,IF(AND(Calculated_Ratios!S62="",ISBLANK(S62)),0,"MISMATCH")) -> 0
A63: Sterling | B63: 2014 | C63: 766168.3 | D63: 1.1753257 | E63: 10.274255 | F63: -0.0985431 | G63: 2.540695 | I63: 0.96443027 | N63: 1.0921216 | O63: 89.725745 | P63: 13.62258 | Q63: 2.910383e-11 | S63: 34 | T63: =IF(AND(ISNUMBER(Calculated_Ratios!C63),ISNUMBER(C63)),Calculated_Ratios!C63-C63,IF(AND(Calculated_Ratios!C63="",ISBLANK(C63)),0,"MISMATCH")) -> 0 | U63: =IF(AND(ISNUMBER(Calculated_Ratios!D63),ISNUMBER(D63)),Calculated_Ratios!D63-D63,IF(AND(Calculated_Ratios!D63="",ISBLANK(D63)),0,"MISMATCH")) -> 0 | V63: =IF(AND(ISNUMBER(Calculated_Ratios!E63),ISNUMBER(E63)),Calculated_Ratios!E63-E63,IF(AND(Calculated_Ratios!E63="",ISBLANK(E63)),0,"MISMATCH")) -> 0 | W63: =IF(AND(ISNUMBER(Calculated_Ratios!F63),ISNUMBER(F63)),Calculated_Ratios!F63-F63,IF(AND(Calculated_Ratios!F63="",ISBLANK(F63)),0,"MISMATCH")) -> 0 | X63: =IF(AND(ISNUMBER(Calculated_Ratios!G63),ISNUMBER(G63)),Calculated_Ratios!G63-G63,IF(AND(Calculated_Ratios!G63="",ISBLANK(G63)),0,"MISMATCH")) -> 0 | Y63: =IF(AND(ISNUMBER(Calculated_Ratios!H63),ISNUMBER(H63)),Calculated_Ratios!H63-H63,IF(AND(Calculated_Ratios!H63="",ISBLANK(H63)),0,"MISMATCH")) -> 0 | Z63: =IF(AND(ISNUMBER(Calculated_Ratios!I63),ISNUMBER(I63)),Calculated_Ratios!I63-I63,IF(AND(Calculated_Ratios!I63="",ISBLANK(I63)),0,"MISMATCH")) -> 0 | AA63: =IF(AND(ISNUMBER(Calculated_Ratios!J63),ISNUMBER(J63)),Calculated_Ratios!J63-J63,IF(AND(Calculated_Ratios!J63="",ISBLANK(J63)),0,"MISMATCH")) -> 0 | ... AJ63: =IF(AND(ISNUMBER(Calculated_Ratios!S63),ISNUMBER(S63)),Calculated_Ratios!S63-S63,IF(AND(Calculated_Ratios!S63="",ISBLANK(S63)),0,"MISMATCH")) -> 0
A64: Sterling | B64: 2015 | C64: 811995.42 | D64: 1.2675659 | E64: 11.953916 | F64: 6.7355053 | G64: 4.4427933 | H64: 17.49022 | I64: 1.003865 | N64: 1.287455 | O64: 88.046084 | P64: 13.591681 | Q64: -2.910383e-11 | R64: 0 | T64: =IF(AND(ISNUMBER(Calculated_Ratios!C64),ISNUMBER(C64)),Calculated_Ratios!C64-C64,IF(AND(Calculated_Ratios!C64="",ISBLANK(C64)),0,"MISMATCH")) -> 0 | U64: =IF(AND(ISNUMBER(Calculated_Ratios!D64),ISNUMBER(D64)),Calculated_Ratios!D64-D64,IF(AND(Calculated_Ratios!D64="",ISBLANK(D64)),0,"MISMATCH")) -> 0 | V64: =IF(AND(ISNUMBER(Calculated_Ratios!E64),ISNUMBER(E64)),Calculated_Ratios!E64-E64,IF(AND(Calculated_Ratios!E64="",ISBLANK(E64)),0,"MISMATCH")) -> 0 | W64: =IF(AND(ISNUMBER(Calculated_Ratios!F64),ISNUMBER(F64)),Calculated_Ratios!F64-F64,IF(AND(Calculated_Ratios!F64="",ISBLANK(F64)),0,"MISMATCH")) -> 0 | X64: =IF(AND(ISNUMBER(Calculated_Ratios!G64),ISNUMBER(G64)),Calculated_Ratios!G64-G64,IF(AND(Calculated_Ratios!G64="",ISBLANK(G64)),0,"MISMATCH")) -> 0 | Y64: =IF(AND(ISNUMBER(Calculated_Ratios!H64),ISNUMBER(H64)),Calculated_Ratios!H64-H64,IF(AND(Calculated_Ratios!H64="",ISBLANK(H64)),0,"MISMATCH")) -> 0 | Z64: =IF(AND(ISNUMBER(Calculated_Ratios!I64),ISNUMBER(I64)),Calculated_Ratios!I64-I64,IF(AND(Calculated_Ratios!I64="",ISBLANK(I64)),0,"MISMATCH")) -> 0 | AA64: =IF(AND(ISNUMBER(Calculated_Ratios!J64),ISNUMBER(J64)),Calculated_Ratios!J64-J64,IF(AND(Calculated_Ratios!J64="",ISBLANK(J64)),0,"MISMATCH")) -> 0 | ... AJ64: =IF(AND(ISNUMBER(Calculated_Ratios!S64),ISNUMBER(S64)),Calculated_Ratios!S64-S64,IF(AND(Calculated_Ratios!S64="",ISBLANK(S64)),0,"MISMATCH")) -> 0
A65: Sterling | B65: 2016 | C65: 815126.82 | D65: 0.6356022 | E65: 10.312758 | F65: -15.321847 | G65: 1.7753428 | H65: 10.659011 | I65: 1.4370731 | N65: 0.62360979 | O65: 89.687242 | P65: 13.630147 | Q65: 8.7311491e-11 | R65: 0 | T65: =IF(AND(ISNUMBER(Calculated_Ratios!C65),ISNUMBER(C65)),Calculated_Ratios!C65-C65,IF(AND(Calculated_Ratios!C65="",ISBLANK(C65)),0,"MISMATCH")) -> 0 | U65: =IF(AND(ISNUMBER(Calculated_Ratios!D65),ISNUMBER(D65)),Calculated_Ratios!D65-D65,IF(AND(Calculated_Ratios!D65="",ISBLANK(D65)),0,"MISMATCH")) -> 0 | V65: =IF(AND(ISNUMBER(Calculated_Ratios!E65),ISNUMBER(E65)),Calculated_Ratios!E65-E65,IF(AND(Calculated_Ratios!E65="",ISBLANK(E65)),0,"MISMATCH")) -> 0 | W65: =IF(AND(ISNUMBER(Calculated_Ratios!F65),ISNUMBER(F65)),Calculated_Ratios!F65-F65,IF(AND(Calculated_Ratios!F65="",ISBLANK(F65)),0,"MISMATCH")) -> 0 | X65: =IF(AND(ISNUMBER(Calculated_Ratios!G65),ISNUMBER(G65)),Calculated_Ratios!G65-G65,IF(AND(Calculated_Ratios!G65="",ISBLANK(G65)),0,"MISMATCH")) -> 0 | Y65: =IF(AND(ISNUMBER(Calculated_Ratios!H65),ISNUMBER(H65)),Calculated_Ratios!H65-H65,IF(AND(Calculated_Ratios!H65="",ISBLANK(H65)),0,"MISMATCH")) -> 0 | Z65: =IF(AND(ISNUMBER(Calculated_Ratios!I65),ISNUMBER(I65)),Calculated_Ratios!I65-I65,IF(AND(Calculated_Ratios!I65="",ISBLANK(I65)),0,"MISMATCH")) -> 0 | AA65: =IF(AND(ISNUMBER(Calculated_Ratios!J65),ISNUMBER(J65)),Calculated_Ratios!J65-J65,IF(AND(Calculated_Ratios!J65="",ISBLANK(J65)),0,"MISMATCH")) -> 0 | ... AJ65: =IF(AND(ISNUMBER(Calculated_Ratios!S65),ISNUMBER(S65)),Calculated_Ratios!S65-S65,IF(AND(Calculated_Ratios!S65="",ISBLANK(S65)),0,"MISMATCH")) -> 0
A66: Sterling | B66: 2017 | C66: 949801.5 | D66: 0.890186 | E66: 9.6269828 | F66: -4.9001818 | G66: 3.1581487 | H66: 11.732009 | I66: 1.291533 | N66: 0.79107558 | O66: 90.373017 | P66: 13.882045 | Q66: 0 | R66: 0 | T66: =IF(AND(ISNUMBER(Calculated_Ratios!C66),ISNUMBER(C66)),Calculated_Ratios!C66-C66,IF(AND(Calculated_Ratios!C66="",ISBLANK(C66)),0,"MISMATCH")) -> 0 | U66: =IF(AND(ISNUMBER(Calculated_Ratios!D66),ISNUMBER(D66)),Calculated_Ratios!D66-D66,IF(AND(Calculated_Ratios!D66="",ISBLANK(D66)),0,"MISMATCH")) -> 0 | V66: =IF(AND(ISNUMBER(Calculated_Ratios!E66),ISNUMBER(E66)),Calculated_Ratios!E66-E66,IF(AND(Calculated_Ratios!E66="",ISBLANK(E66)),0,"MISMATCH")) -> 0 | W66: =IF(AND(ISNUMBER(Calculated_Ratios!F66),ISNUMBER(F66)),Calculated_Ratios!F66-F66,IF(AND(Calculated_Ratios!F66="",ISBLANK(F66)),0,"MISMATCH")) -> 0 | X66: =IF(AND(ISNUMBER(Calculated_Ratios!G66),ISNUMBER(G66)),Calculated_Ratios!G66-G66,IF(AND(Calculated_Ratios!G66="",ISBLANK(G66)),0,"MISMATCH")) -> 0 | Y66: =IF(AND(ISNUMBER(Calculated_Ratios!H66),ISNUMBER(H66)),Calculated_Ratios!H66-H66,IF(AND(Calculated_Ratios!H66="",ISBLANK(H66)),0,"MISMATCH")) -> 0 | Z66: =IF(AND(ISNUMBER(Calculated_Ratios!I66),ISNUMBER(I66)),Calculated_Ratios!I66-I66,IF(AND(Calculated_Ratios!I66="",ISBLANK(I66)),0,"MISMATCH")) -> 0 | AA66: =IF(AND(ISNUMBER(Calculated_Ratios!J66),ISNUMBER(J66)),Calculated_Ratios!J66-J66,IF(AND(Calculated_Ratios!J66="",ISBLANK(J66)),0,"MISMATCH")) -> 0 | ... AJ66: =IF(AND(ISNUMBER(Calculated_Ratios!S66),ISNUMBER(S66)),Calculated_Ratios!S66-S66,IF(AND(Calculated_Ratios!S66="",ISBLANK(S66)),0,"MISMATCH")) -> 0
A67: Sterling | B67: 2018 | E67: 9.0258004 | G67: 3.0687803 | N67: 0.87192276 | O67: 90.9742 | P67: 13.897898 | Q67: 0 | T67: =IF(AND(ISNUMBER(Calculated_Ratios!C67),ISNUMBER(C67)),Calculated_Ratios!C67-C67,IF(AND(Calculated_Ratios!C67="",ISBLANK(C67)),0,"MISMATCH")) -> 0 | U67: =IF(AND(ISNUMBER(Calculated_Ratios!D67),ISNUMBER(D67)),Calculated_Ratios!D67-D67,IF(AND(Calculated_Ratios!D67="",ISBLANK(D67)),0,"MISMATCH")) -> 0 | V67: =IF(AND(ISNUMBER(Calculated_Ratios!E67),ISNUMBER(E67)),Calculated_Ratios!E67-E67,IF(AND(Calculated_Ratios!E67="",ISBLANK(E67)),0,"MISMATCH")) -> 0 | W67: =IF(AND(ISNUMBER(Calculated_Ratios!F67),ISNUMBER(F67)),Calculated_Ratios!F67-F67,IF(AND(Calculated_Ratios!F67="",ISBLANK(F67)),0,"MISMATCH")) -> 0 | X67: =IF(AND(ISNUMBER(Calculated_Ratios!G67),ISNUMBER(G67)),Calculated_Ratios!G67-G67,IF(AND(Calculated_Ratios!G67="",ISBLANK(G67)),0,"MISMATCH")) -> 0 | Y67: =IF(AND(ISNUMBER(Calculated_Ratios!H67),ISNUMBER(H67)),Calculated_Ratios!H67-H67,IF(AND(Calculated_Ratios!H67="",ISBLANK(H67)),0,"MISMATCH")) -> 0 | Z67: =IF(AND(ISNUMBER(Calculated_Ratios!I67),ISNUMBER(I67)),Calculated_Ratios!I67-I67,IF(AND(Calculated_Ratios!I67="",ISBLANK(I67)),0,"MISMATCH")) -> 0 | AA67: =IF(AND(ISNUMBER(Calculated_Ratios!J67),ISNUMBER(J67)),Calculated_Ratios!J67-J67,IF(AND(Calculated_Ratios!J67="",ISBLANK(J67)),0,"MISMATCH")) -> 0 | ... AJ67: =IF(AND(ISNUMBER(Calculated_Ratios!S67),ISNUMBER(S67)),Calculated_Ratios!S67-S67,IF(AND(Calculated_Ratios!S67="",ISBLANK(S67)),0,"MISMATCH")) -> 0
A68: Sterling | B68: 2019 | C68: 1125692.5 | D68: 0.90282204 | E68: 10.238274 | F68: 10.163877 | G68: 2.0525631 | I68: 0.51896943 | N68: 0.87197954 | O68: 89.761726 | P68: 13.968668 | Q68: 0 | T68: =IF(AND(ISNUMBER(Calculated_Ratios!C68),ISNUMBER(C68)),Calculated_Ratios!C68-C68,IF(AND(Calculated_Ratios!C68="",ISBLANK(C68)),0,"MISMATCH")) -> 0 | U68: =IF(AND(ISNUMBER(Calculated_Ratios!D68),ISNUMBER(D68)),Calculated_Ratios!D68-D68,IF(AND(Calculated_Ratios!D68="",ISBLANK(D68)),0,"MISMATCH")) -> 0 | V68: =IF(AND(ISNUMBER(Calculated_Ratios!E68),ISNUMBER(E68)),Calculated_Ratios!E68-E68,IF(AND(Calculated_Ratios!E68="",ISBLANK(E68)),0,"MISMATCH")) -> 0 | W68: =IF(AND(ISNUMBER(Calculated_Ratios!F68),ISNUMBER(F68)),Calculated_Ratios!F68-F68,IF(AND(Calculated_Ratios!F68="",ISBLANK(F68)),0,"MISMATCH")) -> 0 | X68: =IF(AND(ISNUMBER(Calculated_Ratios!G68),ISNUMBER(G68)),Calculated_Ratios!G68-G68,IF(AND(Calculated_Ratios!G68="",ISBLANK(G68)),0,"MISMATCH")) -> 0 | Y68: =IF(AND(ISNUMBER(Calculated_Ratios!H68),ISNUMBER(H68)),Calculated_Ratios!H68-H68,IF(AND(Calculated_Ratios!H68="",ISBLANK(H68)),0,"MISMATCH")) -> 0 | Z68: =IF(AND(ISNUMBER(Calculated_Ratios!I68),ISNUMBER(I68)),Calculated_Ratios!I68-I68,IF(AND(Calculated_Ratios!I68="",ISBLANK(I68)),0,"MISMATCH")) -> 0 | AA68: =IF(AND(ISNUMBER(Calculated_Ratios!J68),ISNUMBER(J68)),Calculated_Ratios!J68-J68,IF(AND(Calculated_Ratios!J68="",ISBLANK(J68)),0,"MISMATCH")) -> 0 | ... AJ68: =IF(AND(ISNUMBER(Calculated_Ratios!S68),ISNUMBER(S68)),Calculated_Ratios!S68-S68,IF(AND(Calculated_Ratios!S68="",ISBLANK(S68)),0,"MISMATCH")) -> 0
A69: Sterling | B69: 2020 | C69: 1223669.5 | D69: 0.90792489 | E69: 10.562243 | F69: 0.36006454 | G69: 2.695322 | H69: 17.976327 | I69: 0.64666154 | N69: 0.8667296 | O69: 89.437757 | P69: 14.063799 | Q69: 0 | R69: 0 | T69: =IF(AND(ISNUMBER(Calculated_Ratios!C69),ISNUMBER(C69)),Calculated_Ratios!C69-C69,IF(AND(Calculated_Ratios!C69="",ISBLANK(C69)),0,"MISMATCH")) -> 0 | U69: =IF(AND(ISNUMBER(Calculated_Ratios!D69),ISNUMBER(D69)),Calculated_Ratios!D69-D69,IF(AND(Calculated_Ratios!D69="",ISBLANK(D69)),0,"MISMATCH")) -> 0 | V69: =IF(AND(ISNUMBER(Calculated_Ratios!E69),ISNUMBER(E69)),Calculated_Ratios!E69-E69,IF(AND(Calculated_Ratios!E69="",ISBLANK(E69)),0,"MISMATCH")) -> 0 | W69: =IF(AND(ISNUMBER(Calculated_Ratios!F69),ISNUMBER(F69)),Calculated_Ratios!F69-F69,IF(AND(Calculated_Ratios!F69="",ISBLANK(F69)),0,"MISMATCH")) -> 0 | X69: =IF(AND(ISNUMBER(Calculated_Ratios!G69),ISNUMBER(G69)),Calculated_Ratios!G69-G69,IF(AND(Calculated_Ratios!G69="",ISBLANK(G69)),0,"MISMATCH")) -> 0 | Y69: =IF(AND(ISNUMBER(Calculated_Ratios!H69),ISNUMBER(H69)),Calculated_Ratios!H69-H69,IF(AND(Calculated_Ratios!H69="",ISBLANK(H69)),0,"MISMATCH")) -> 0 | Z69: =IF(AND(ISNUMBER(Calculated_Ratios!I69),ISNUMBER(I69)),Calculated_Ratios!I69-I69,IF(AND(Calculated_Ratios!I69="",ISBLANK(I69)),0,"MISMATCH")) -> 0 | AA69: =IF(AND(ISNUMBER(Calculated_Ratios!J69),ISNUMBER(J69)),Calculated_Ratios!J69-J69,IF(AND(Calculated_Ratios!J69="",ISBLANK(J69)),0,"MISMATCH")) -> 0 | ... AJ69: =IF(AND(ISNUMBER(Calculated_Ratios!S69),ISNUMBER(S69)),Calculated_Ratios!S69-S69,IF(AND(Calculated_Ratios!S69="",ISBLANK(S69)),0,"MISMATCH")) -> 0
A70: Sterling | B70: 2021 | C70: 1446789.5 | D70: 0.926396 | E70: 8.7492531 | F70: 10.024057 | G70: 1.9529528 | H70: 14.815547 | I70: 0.67888245 | N70: 0.8315811 | O70: 91.250747 | P70: 14.29283 | Q70: 0 | R70: 0 | T70: =IF(AND(ISNUMBER(Calculated_Ratios!C70),ISNUMBER(C70)),Calculated_Ratios!C70-C70,IF(AND(Calculated_Ratios!C70="",ISBLANK(C70)),0,"MISMATCH")) -> 0 | U70: =IF(AND(ISNUMBER(Calculated_Ratios!D70),ISNUMBER(D70)),Calculated_Ratios!D70-D70,IF(AND(Calculated_Ratios!D70="",ISBLANK(D70)),0,"MISMATCH")) -> 0 | V70: =IF(AND(ISNUMBER(Calculated_Ratios!E70),ISNUMBER(E70)),Calculated_Ratios!E70-E70,IF(AND(Calculated_Ratios!E70="",ISBLANK(E70)),0,"MISMATCH")) -> 0 | W70: =IF(AND(ISNUMBER(Calculated_Ratios!F70),ISNUMBER(F70)),Calculated_Ratios!F70-F70,IF(AND(Calculated_Ratios!F70="",ISBLANK(F70)),0,"MISMATCH")) -> 0 | X70: =IF(AND(ISNUMBER(Calculated_Ratios!G70),ISNUMBER(G70)),Calculated_Ratios!G70-G70,IF(AND(Calculated_Ratios!G70="",ISBLANK(G70)),0,"MISMATCH")) -> 0 | Y70: =IF(AND(ISNUMBER(Calculated_Ratios!H70),ISNUMBER(H70)),Calculated_Ratios!H70-H70,IF(AND(Calculated_Ratios!H70="",ISBLANK(H70)),0,"MISMATCH")) -> 0 | Z70: =IF(AND(ISNUMBER(Calculated_Ratios!I70),ISNUMBER(I70)),Calculated_Ratios!I70-I70,IF(AND(Calculated_Ratios!I70="",ISBLANK(I70)),0,"MISMATCH")) -> 0 | AA70: =IF(AND(ISNUMBER(Calculated_Ratios!J70),ISNUMBER(J70)),Calculated_Ratios!J70-J70,IF(AND(Calculated_Ratios!J70="",ISBLANK(J70)),0,"MISMATCH")) -> 0 | ... AJ70: =IF(AND(ISNUMBER(Calculated_Ratios!S70),ISNUMBER(S70)),Calculated_Ratios!S70-S70,IF(AND(Calculated_Ratios!S70="",ISBLANK(S70)),0,"MISMATCH")) -> 0
A71: Sterling | B71: 2022 | C71: 1723760 | D71: 1.1212118 | E71: 8.3423973 | F71: 4.1094468 | G71: 2.6969742 | H71: 14.67421 | I71: 0.52698752 | N71: 1.0500255 | O71: 91.657603 | P71: 14.425614 | Q71: 0 | R71: 0 | T71: =IF(AND(ISNUMBER(Calculated_Ratios!C71),ISNUMBER(C71)),Calculated_Ratios!C71-C71,IF(AND(Calculated_Ratios!C71="",ISBLANK(C71)),0,"MISMATCH")) -> 0 | U71: =IF(AND(ISNUMBER(Calculated_Ratios!D71),ISNUMBER(D71)),Calculated_Ratios!D71-D71,IF(AND(Calculated_Ratios!D71="",ISBLANK(D71)),0,"MISMATCH")) -> 0 | V71: =IF(AND(ISNUMBER(Calculated_Ratios!E71),ISNUMBER(E71)),Calculated_Ratios!E71-E71,IF(AND(Calculated_Ratios!E71="",ISBLANK(E71)),0,"MISMATCH")) -> 0 | W71: =IF(AND(ISNUMBER(Calculated_Ratios!F71),ISNUMBER(F71)),Calculated_Ratios!F71-F71,IF(AND(Calculated_Ratios!F71="",ISBLANK(F71)),0,"MISMATCH")) -> 0 | X71: =IF(AND(ISNUMBER(Calculated_Ratios!G71),ISNUMBER(G71)),Calculated_Ratios!G71-G71,IF(AND(Calculated_Ratios!G71="",ISBLANK(G71)),0,"MISMATCH")) -> 0 | Y71: =IF(AND(ISNUMBER(Calculated_Ratios!H71),ISNUMBER(H71)),Calculated_Ratios!H71-H71,IF(AND(Calculated_Ratios!H71="",ISBLANK(H71)),0,"MISMATCH")) -> 0 | Z71: =IF(AND(ISNUMBER(Calculated_Ratios!I71),ISNUMBER(I71)),Calculated_Ratios!I71-I71,IF(AND(Calculated_Ratios!I71="",ISBLANK(I71)),0,"MISMATCH")) -> 0 | AA71: =IF(AND(ISNUMBER(Calculated_Ratios!J71),ISNUMBER(J71)),Calculated_Ratios!J71-J71,IF(AND(Calculated_Ratios!J71="",ISBLANK(J71)),0,"MISMATCH")) -> 0 | ... AJ71: =IF(AND(ISNUMBER(Calculated_Ratios!S71),ISNUMBER(S71)),Calculated_Ratios!S71-S71,IF(AND(Calculated_Ratios!S71="",ISBLANK(S71)),0,"MISMATCH")) -> 0
A72: UBA | B72: 2013 | E72: 11.704519 | G72: 1.0328354 | N72: 2.0962679 | O72: 88.295481 | P72: 14.611854 | Q72: 0 | T72: =IF(AND(ISNUMBER(Calculated_Ratios!C72),ISNUMBER(C72)),Calculated_Ratios!C72-C72,IF(AND(Calculated_Ratios!C72="",ISBLANK(C72)),0,"MISMATCH")) -> 0 | U72: =IF(AND(ISNUMBER(Calculated_Ratios!D72),ISNUMBER(D72)),Calculated_Ratios!D72-D72,IF(AND(Calculated_Ratios!D72="",ISBLANK(D72)),0,"MISMATCH")) -> 0 | V72: =IF(AND(ISNUMBER(Calculated_Ratios!E72),ISNUMBER(E72)),Calculated_Ratios!E72-E72,IF(AND(Calculated_Ratios!E72="",ISBLANK(E72)),0,"MISMATCH")) -> 0 | W72: =IF(AND(ISNUMBER(Calculated_Ratios!F72),ISNUMBER(F72)),Calculated_Ratios!F72-F72,IF(AND(Calculated_Ratios!F72="",ISBLANK(F72)),0,"MISMATCH")) -> 0 | X72: =IF(AND(ISNUMBER(Calculated_Ratios!G72),ISNUMBER(G72)),Calculated_Ratios!G72-G72,IF(AND(Calculated_Ratios!G72="",ISBLANK(G72)),0,"MISMATCH")) -> 0 | Y72: =IF(AND(ISNUMBER(Calculated_Ratios!H72),ISNUMBER(H72)),Calculated_Ratios!H72-H72,IF(AND(Calculated_Ratios!H72="",ISBLANK(H72)),0,"MISMATCH")) -> 0 | Z72: =IF(AND(ISNUMBER(Calculated_Ratios!I72),ISNUMBER(I72)),Calculated_Ratios!I72-I72,IF(AND(Calculated_Ratios!I72="",ISBLANK(I72)),0,"MISMATCH")) -> 0 | AA72: =IF(AND(ISNUMBER(Calculated_Ratios!J72),ISNUMBER(J72)),Calculated_Ratios!J72-J72,IF(AND(Calculated_Ratios!J72="",ISBLANK(J72)),0,"MISMATCH")) -> 0 | ... AJ72: =IF(AND(ISNUMBER(Calculated_Ratios!S72),ISNUMBER(S72)),Calculated_Ratios!S72-S72,IF(AND(Calculated_Ratios!S72="",ISBLANK(S72)),0,"MISMATCH")) -> 0
A73: UBA | B73: 2014 | C73: 2278137.5 | D73: 1.7594636 | E73: 12.054302 | F73: -4.0655579 | G73: 1.1754993 | I73: 0.13489089 | N73: 1.7137851 | O73: 87.945698 | P73: 14.665173 | Q73: 0 | T73: =IF(AND(ISNUMBER(Calculated_Ratios!C73),ISNUMBER(C73)),Calculated_Ratios!C73-C73,IF(AND(Calculated_Ratios!C73="",ISBLANK(C73)),0,"MISMATCH")) -> 0 | U73: =IF(AND(ISNUMBER(Calculated_Ratios!D73),ISNUMBER(D73)),Calculated_Ratios!D73-D73,IF(AND(Calculated_Ratios!D73="",ISBLANK(D73)),0,"MISMATCH")) -> 0 | V73: =IF(AND(ISNUMBER(Calculated_Ratios!E73),ISNUMBER(E73)),Calculated_Ratios!E73-E73,IF(AND(Calculated_Ratios!E73="",ISBLANK(E73)),0,"MISMATCH")) -> 0 | W73: =IF(AND(ISNUMBER(Calculated_Ratios!F73),ISNUMBER(F73)),Calculated_Ratios!F73-F73,IF(AND(Calculated_Ratios!F73="",ISBLANK(F73)),0,"MISMATCH")) -> 0 | X73: =IF(AND(ISNUMBER(Calculated_Ratios!G73),ISNUMBER(G73)),Calculated_Ratios!G73-G73,IF(AND(Calculated_Ratios!G73="",ISBLANK(G73)),0,"MISMATCH")) -> 0 | Y73: =IF(AND(ISNUMBER(Calculated_Ratios!H73),ISNUMBER(H73)),Calculated_Ratios!H73-H73,IF(AND(Calculated_Ratios!H73="",ISBLANK(H73)),0,"MISMATCH")) -> 0 | Z73: =IF(AND(ISNUMBER(Calculated_Ratios!I73),ISNUMBER(I73)),Calculated_Ratios!I73-I73,IF(AND(Calculated_Ratios!I73="",ISBLANK(I73)),0,"MISMATCH")) -> 0 | AA73: =IF(AND(ISNUMBER(Calculated_Ratios!J73),ISNUMBER(J73)),Calculated_Ratios!J73-J73,IF(AND(Calculated_Ratios!J73="",ISBLANK(J73)),0,"MISMATCH")) -> 0 | ... AJ73: =IF(AND(ISNUMBER(Calculated_Ratios!S73),ISNUMBER(S73)),Calculated_Ratios!S73-S73,IF(AND(Calculated_Ratios!S73="",ISBLANK(S73)),0,"MISMATCH")) -> 0
A74: UBA | B74: 2015 | C74: 2277597.5 | D74: 2.0917656 | E74: 15.260811 | F74: 2.5644566 | G74: 1.5606584 | H74: 19.95172 | I74: 0.15327555 | N74: 2.1495828 | O74: 84.739189 | P74: 14.611366 | Q74: 0 | R74: 0 | S74: 52.57 | T74: =IF(AND(ISNUMBER(Calculated_Ratios!C74),ISNUMBER(C74)),Calculated_Ratios!C74-C74,IF(AND(Calculated_Ratios!C74="",ISBLANK(C74)),0,"MISMATCH")) -> 0 | U74: =IF(AND(ISNUMBER(Calculated_Ratios!D74),ISNUMBER(D74)),Calculated_Ratios!D74-D74,IF(AND(Calculated_Ratios!D74="",ISBLANK(D74)),0,"MISMATCH")) -> 0 | V74: =IF(AND(ISNUMBER(Calculated_Ratios!E74),ISNUMBER(E74)),Calculated_Ratios!E74-E74,IF(AND(Calculated_Ratios!E74="",ISBLANK(E74)),0,"MISMATCH")) -> 0 | W74: =IF(AND(ISNUMBER(Calculated_Ratios!F74),ISNUMBER(F74)),Calculated_Ratios!F74-F74,IF(AND(Calculated_Ratios!F74="",ISBLANK(F74)),0,"MISMATCH")) -> 0 | X74: =IF(AND(ISNUMBER(Calculated_Ratios!G74),ISNUMBER(G74)),Calculated_Ratios!G74-G74,IF(AND(Calculated_Ratios!G74="",ISBLANK(G74)),0,"MISMATCH")) -> 0 | Y74: =IF(AND(ISNUMBER(Calculated_Ratios!H74),ISNUMBER(H74)),Calculated_Ratios!H74-H74,IF(AND(Calculated_Ratios!H74="",ISBLANK(H74)),0,"MISMATCH")) -> 0 | Z74: =IF(AND(ISNUMBER(Calculated_Ratios!I74),ISNUMBER(I74)),Calculated_Ratios!I74-I74,IF(AND(Calculated_Ratios!I74="",ISBLANK(I74)),0,"MISMATCH")) -> 0 | AA74: =IF(AND(ISNUMBER(Calculated_Ratios!J74),ISNUMBER(J74)),Calculated_Ratios!J74-J74,IF(AND(Calculated_Ratios!J74="",ISBLANK(J74)),0,"MISMATCH")) -> 0 | ... AJ74: =IF(AND(ISNUMBER(Calculated_Ratios!S74),ISNUMBER(S74)),Calculated_Ratios!S74-S74,IF(AND(Calculated_Ratios!S74="",ISBLANK(S74)),0,"MISMATCH")) -> 0
A75: UBA | B75: 2016 | C75: 2377961 | D75: 1.9992338 | E75: 15.392279 | F75: -8.9737384 | G75: 2.6552188 | H75: 19.702891 | I75: 1.0732304 | N75: 1.8719988 | O75: 84.607721 | P75: 14.747511 | Q75: 0 | R75: 0 | S75: 38.57 | T75: =IF(AND(ISNUMBER(Calculated_Ratios!C75),ISNUMBER(C75)),Calculated_Ratios!C75-C75,IF(AND(Calculated_Ratios!C75="",ISBLANK(C75)),0,"MISMATCH")) -> 0 | U75: =IF(AND(ISNUMBER(Calculated_Ratios!D75),ISNUMBER(D75)),Calculated_Ratios!D75-D75,IF(AND(Calculated_Ratios!D75="",ISBLANK(D75)),0,"MISMATCH")) -> 0 | V75: =IF(AND(ISNUMBER(Calculated_Ratios!E75),ISNUMBER(E75)),Calculated_Ratios!E75-E75,IF(AND(Calculated_Ratios!E75="",ISBLANK(E75)),0,"MISMATCH")) -> 0 | W75: =IF(AND(ISNUMBER(Calculated_Ratios!F75),ISNUMBER(F75)),Calculated_Ratios!F75-F75,IF(AND(Calculated_Ratios!F75="",ISBLANK(F75)),0,"MISMATCH")) -> 0 | X75: =IF(AND(ISNUMBER(Calculated_Ratios!G75),ISNUMBER(G75)),Calculated_Ratios!G75-G75,IF(AND(Calculated_Ratios!G75="",ISBLANK(G75)),0,"MISMATCH")) -> 0 | Y75: =IF(AND(ISNUMBER(Calculated_Ratios!H75),ISNUMBER(H75)),Calculated_Ratios!H75-H75,IF(AND(Calculated_Ratios!H75="",ISBLANK(H75)),0,"MISMATCH")) -> 0 | Z75: =IF(AND(ISNUMBER(Calculated_Ratios!I75),ISNUMBER(I75)),Calculated_Ratios!I75-I75,IF(AND(Calculated_Ratios!I75="",ISBLANK(I75)),0,"MISMATCH")) -> 0 | AA75: =IF(AND(ISNUMBER(Calculated_Ratios!J75),ISNUMBER(J75)),Calculated_Ratios!J75-J75,IF(AND(Calculated_Ratios!J75="",ISBLANK(J75)),0,"MISMATCH")) -> 0 | ... AJ75: =IF(AND(ISNUMBER(Calculated_Ratios!S75),ISNUMBER(S75)),Calculated_Ratios!S75-S75,IF(AND(Calculated_Ratios!S75="",ISBLANK(S75)),0,"MISMATCH")) -> 0
A76: UBA | B76: 2017 | C76: 2735705.5 | D76: 1.5131746 | E76: 13.672708 | F76: 2.1621845 | G76: 2.5914419 | H76: 20.158851 | I76: 1.112437 | N76: 1.4119528 | O76: 86.327292 | P76: 14.891136 | Q76: 0 | R76: 0 | S76: 49.69 | T76: =IF(AND(ISNUMBER(Calculated_Ratios!C76),ISNUMBER(C76)),Calculated_Ratios!C76-C76,IF(AND(Calculated_Ratios!C76="",ISBLANK(C76)),0,"MISMATCH")) -> 0 | U76: =IF(AND(ISNUMBER(Calculated_Ratios!D76),ISNUMBER(D76)),Calculated_Ratios!D76-D76,IF(AND(Calculated_Ratios!D76="",ISBLANK(D76)),0,"MISMATCH")) -> 0 | V76: =IF(AND(ISNUMBER(Calculated_Ratios!E76),ISNUMBER(E76)),Calculated_Ratios!E76-E76,IF(AND(Calculated_Ratios!E76="",ISBLANK(E76)),0,"MISMATCH")) -> 0 | W76: =IF(AND(ISNUMBER(Calculated_Ratios!F76),ISNUMBER(F76)),Calculated_Ratios!F76-F76,IF(AND(Calculated_Ratios!F76="",ISBLANK(F76)),0,"MISMATCH")) -> 0 | X76: =IF(AND(ISNUMBER(Calculated_Ratios!G76),ISNUMBER(G76)),Calculated_Ratios!G76-G76,IF(AND(Calculated_Ratios!G76="",ISBLANK(G76)),0,"MISMATCH")) -> 0 | Y76: =IF(AND(ISNUMBER(Calculated_Ratios!H76),ISNUMBER(H76)),Calculated_Ratios!H76-H76,IF(AND(Calculated_Ratios!H76="",ISBLANK(H76)),0,"MISMATCH")) -> 0 | Z76: =IF(AND(ISNUMBER(Calculated_Ratios!I76),ISNUMBER(I76)),Calculated_Ratios!I76-I76,IF(AND(Calculated_Ratios!I76="",ISBLANK(I76)),0,"MISMATCH")) -> 0 | AA76: =IF(AND(ISNUMBER(Calculated_Ratios!J76),ISNUMBER(J76)),Calculated_Ratios!J76-J76,IF(AND(Calculated_Ratios!J76="",ISBLANK(J76)),0,"MISMATCH")) -> 0 | ... AJ76: =IF(AND(ISNUMBER(Calculated_Ratios!S76),ISNUMBER(S76)),Calculated_Ratios!S76-S76,IF(AND(Calculated_Ratios!S76="",ISBLANK(S76)),0,"MISMATCH")) -> 0
A77: UBA | B77: 2018 | C77: 3261565.5 | D77: 1.2585061 | E77: 10.152243 | F77: 14.981333 | G77: 4.7335713 | H77: 19.662013 | I77: 0.13052014 | N77: 1.142955 | O77: 89.847757 | P77: 15.094026 | Q77: 0 | R77: 0 | S77: 55.84 | T77: =IF(AND(ISNUMBER(Calculated_Ratios!C77),ISNUMBER(C77)),Calculated_Ratios!C77-C77,IF(AND(Calculated_Ratios!C77="",ISBLANK(C77)),0,"MISMATCH")) -> 0 | U77: =IF(AND(ISNUMBER(Calculated_Ratios!D77),ISNUMBER(D77)),Calculated_Ratios!D77-D77,IF(AND(Calculated_Ratios!D77="",ISBLANK(D77)),0,"MISMATCH")) -> 0 | V77: =IF(AND(ISNUMBER(Calculated_Ratios!E77),ISNUMBER(E77)),Calculated_Ratios!E77-E77,IF(AND(Calculated_Ratios!E77="",ISBLANK(E77)),0,"MISMATCH")) -> 0 | W77: =IF(AND(ISNUMBER(Calculated_Ratios!F77),ISNUMBER(F77)),Calculated_Ratios!F77-F77,IF(AND(Calculated_Ratios!F77="",ISBLANK(F77)),0,"MISMATCH")) -> 0 | X77: =IF(AND(ISNUMBER(Calculated_Ratios!G77),ISNUMBER(G77)),Calculated_Ratios!G77-G77,IF(AND(Calculated_Ratios!G77="",ISBLANK(G77)),0,"MISMATCH")) -> 0 | Y77: =IF(AND(ISNUMBER(Calculated_Ratios!H77),ISNUMBER(H77)),Calculated_Ratios!H77-H77,IF(AND(Calculated_Ratios!H77="",ISBLANK(H77)),0,"MISMATCH")) -> 0 | Z77: =IF(AND(ISNUMBER(Calculated_Ratios!I77),ISNUMBER(I77)),Calculated_Ratios!I77-I77,IF(AND(Calculated_Ratios!I77="",ISBLANK(I77)),0,"MISMATCH")) -> 0 | AA77: =IF(AND(ISNUMBER(Calculated_Ratios!J77),ISNUMBER(J77)),Calculated_Ratios!J77-J77,IF(AND(Calculated_Ratios!J77="",ISBLANK(J77)),0,"MISMATCH")) -> 0 | ... AJ77: =IF(AND(ISNUMBER(Calculated_Ratios!S77),ISNUMBER(S77)),Calculated_Ratios!S77-S77,IF(AND(Calculated_Ratios!S77="",ISBLANK(S77)),0,"MISMATCH")) -> 0
A78: UBA | B78: 2019 | C78: 3863899 | D78: 1.6240073 | E78: 10.7947 | F78: -8.2158721 | G78: 3.4659982 | H78: 21.507102 | I78: 0.42363944 | N78: 1.5169855 | O78: 89.2053 | P78: 15.235359 | Q78: 0 | R78: 0 | S78: 43.99 | T78: =IF(AND(ISNUMBER(Calculated_Ratios!C78),ISNUMBER(C78)),Calculated_Ratios!C78-C78,IF(AND(Calculated_Ratios!C78="",ISBLANK(C78)),0,"MISMATCH")) -> 0 | U78: =IF(AND(ISNUMBER(Calculated_Ratios!D78),ISNUMBER(D78)),Calculated_Ratios!D78-D78,IF(AND(Calculated_Ratios!D78="",ISBLANK(D78)),0,"MISMATCH")) -> 0 | V78: =IF(AND(ISNUMBER(Calculated_Ratios!E78),ISNUMBER(E78)),Calculated_Ratios!E78-E78,IF(AND(Calculated_Ratios!E78="",ISBLANK(E78)),0,"MISMATCH")) -> 0 | W78: =IF(AND(ISNUMBER(Calculated_Ratios!F78),ISNUMBER(F78)),Calculated_Ratios!F78-F78,IF(AND(Calculated_Ratios!F78="",ISBLANK(F78)),0,"MISMATCH")) -> 0 | X78: =IF(AND(ISNUMBER(Calculated_Ratios!G78),ISNUMBER(G78)),Calculated_Ratios!G78-G78,IF(AND(Calculated_Ratios!G78="",ISBLANK(G78)),0,"MISMATCH")) -> 0 | Y78: =IF(AND(ISNUMBER(Calculated_Ratios!H78),ISNUMBER(H78)),Calculated_Ratios!H78-H78,IF(AND(Calculated_Ratios!H78="",ISBLANK(H78)),0,"MISMATCH")) -> 0 | Z78: =IF(AND(ISNUMBER(Calculated_Ratios!I78),ISNUMBER(I78)),Calculated_Ratios!I78-I78,IF(AND(Calculated_Ratios!I78="",ISBLANK(I78)),0,"MISMATCH")) -> 0 | AA78: =IF(AND(ISNUMBER(Calculated_Ratios!J78),ISNUMBER(J78)),Calculated_Ratios!J78-J78,IF(AND(Calculated_Ratios!J78="",ISBLANK(J78)),0,"MISMATCH")) -> 0 | ... AJ78: =IF(AND(ISNUMBER(Calculated_Ratios!S78),ISNUMBER(S78)),Calculated_Ratios!S78-S78,IF(AND(Calculated_Ratios!S78="",ISBLANK(S78)),0,"MISMATCH")) -> 0
A79: UBA | B79: 2020 | C79: 4672163 | D79: 1.2180868 | E79: 9.1773296 | F79: 15.733912 | G79: 3.3240917 | H79: 19.695215 | I79: 0.46796313 | N79: 1.0927962 | O79: 90.82267 | P79: 15.465674 | Q79: 0 | R79: 0 | S79: 44.3 | T79: =IF(AND(ISNUMBER(Calculated_Ratios!C79),ISNUMBER(C79)),Calculated_Ratios!C79-C79,IF(AND(Calculated_Ratios!C79="",ISBLANK(C79)),0,"MISMATCH")) -> 0 | U79: =IF(AND(ISNUMBER(Calculated_Ratios!D79),ISNUMBER(D79)),Calculated_Ratios!D79-D79,IF(AND(Calculated_Ratios!D79="",ISBLANK(D79)),0,"MISMATCH")) -> 0 | V79: =IF(AND(ISNUMBER(Calculated_Ratios!E79),ISNUMBER(E79)),Calculated_Ratios!E79-E79,IF(AND(Calculated_Ratios!E79="",ISBLANK(E79)),0,"MISMATCH")) -> 0 | W79: =IF(AND(ISNUMBER(Calculated_Ratios!F79),ISNUMBER(F79)),Calculated_Ratios!F79-F79,IF(AND(Calculated_Ratios!F79="",ISBLANK(F79)),0,"MISMATCH")) -> 0 | X79: =IF(AND(ISNUMBER(Calculated_Ratios!G79),ISNUMBER(G79)),Calculated_Ratios!G79-G79,IF(AND(Calculated_Ratios!G79="",ISBLANK(G79)),0,"MISMATCH")) -> 0 | Y79: =IF(AND(ISNUMBER(Calculated_Ratios!H79),ISNUMBER(H79)),Calculated_Ratios!H79-H79,IF(AND(Calculated_Ratios!H79="",ISBLANK(H79)),0,"MISMATCH")) -> 0 | Z79: =IF(AND(ISNUMBER(Calculated_Ratios!I79),ISNUMBER(I79)),Calculated_Ratios!I79-I79,IF(AND(Calculated_Ratios!I79="",ISBLANK(I79)),0,"MISMATCH")) -> 0 | AA79: =IF(AND(ISNUMBER(Calculated_Ratios!J79),ISNUMBER(J79)),Calculated_Ratios!J79-J79,IF(AND(Calculated_Ratios!J79="",ISBLANK(J79)),0,"MISMATCH")) -> 0 | ... AJ79: =IF(AND(ISNUMBER(Calculated_Ratios!S79),ISNUMBER(S79)),Calculated_Ratios!S79-S79,IF(AND(Calculated_Ratios!S79="",ISBLANK(S79)),0,"MISMATCH")) -> 0
